Workbook

Sheet Doors
A1: ID | B1: Title | C1: Subtitle | D1: Location | E1: Floor | F1: Telephone | G1: Description | H1: Category | I1: Web | J1: Logo | K1: LogoName | L1: Cat_TR | M1: https://inmapper.com/zorlucenter/img/logo/
A2: carpark-301 | B2: {“id”:”carpark”} | E2: -3 | F2: - | G2: otopark, araç, otomobil, motosiklet, manevra, parking, vehicle, automobile, motorcycle, maneuver
A3: carpark-301 | B3: DRN Oto Yıkama | C3: {“id”:”floorparking”} | E3: -3 | F3: +905313051112 | G3: otomobil, yıkama, pasta, cila, temizlik, automobile, washing, cake, lacquer, cleaning | H3: servicestores | I3: www.drncarcare.com | J3: =CONCATENATE($M$1,$K3) -> https://inmapper.com/zorlucenter/img/logo/WILLIAMSCARCARE.png | K3: WILLIAMSCARCARE.png | L3: Hizmet Mağazaları
A4: entrance-301 | B4: {“id”:”entrance”} {“id”:”floormetro”} | E4: -3 | F4: - | G4: giriş, çıkış, kapı, bekleme, güvenlik, entrance, exit, door, waiting, security
A5: entrance-302 | B5: {“id”:”carpark”} {“id”:”entrance”} Zincirlikuyu | E5: -3 | F5: - | G5: giriş, çıkış, kapı, bekleme, güvenlik, entrance, exit, door, waiting, security
A6: entrance-303 | B6: {“id”:”entrance”} {“id”:”floormetro”} | E6: -3 | F6: - | G6: giriş, çıkış, kapı, bekleme, güvenlik, entrance, exit, door, waiting, security
A7: entrance-304 | B7: {“id”:”carpark”} {“id”:”entrance”} Levazım | E7: -3 | F7: - | G7: giriş, çıkış, kapı, bekleme, güvenlik, entrance, exit, door, waiting, security
A8: entrance-305 | B8: {“id”:”entrance”} {“id”:”floorparking”} | E8: -3 | F8: - | G8: giriş, çıkış, kapı, bekleme, güvenlik, entrance, exit, door, waiting, security
A9: entrance-306 | B9: {“id”:”carpark”} {“id”:”entrance”} Eataly | E9: -3 | F9: - | G9: giriş, çıkış, kapı, bekleme, güvenlik, entrance, exit, door, waiting, security
A10: ID-301 | B10: Etstur | E10: -3 | F10: +902122820808-07 | G10: tatil, deniz, bayram, otel, fırsat, holiday, sea, holidays, hotel, occasion | H10: culture_entertainment | I10: www.etstur.com | J10: =CONCATENATE($M$1,$K10) -> https://inmapper.com/zorlucenter/img/logo/ETSTUR.png | K10: ETSTUR.png | L10: Kültür & Eğlence
A11: ID-302 | B11: Levent Lostra | E11: -3 | F11: +902123536303 | G11: ayakkabı, tamir, boya, bakım, cüzdan, shoe, repair, paint, maintenance, wallet | H11: servicestores | I11: www.leventlostra.com.tr | J11: =CONCATENATE($M$1,$K11) -> https://inmapper.com/zorlucenter/img/logo/LEVENTLOSTRA.png | K11: LEVENTLOSTRA.png | L11: Hizmet Mağazaları
A12: ID-303 | B12: Dry Corner | E12: -3 | F12: +902123536337 | G12: kuru temizleme, ütü, gömlek, ceket, organik, dry cleaning, ironing, shirt, jacket, organic, dıray kornır | H12: servicestores | I12: www.drycorner.com | J12: =CONCATENATE($M$1,$K12) -> https://inmapper.com/zorlucenter/img/logo/DRYCORNER.png | K12: DRYCORNER.png | L12: Hizmet Mağazaları
A13: ID-304 | B13: Z Terzi | E13: -3 | F13: +902123536986 | G13: dikiş, onarım, tadilat, küçültme, büyültme, sewing, repair, modification, reduction, magnification | H13: servicestores | I13: www.zterzi.com | J13: =CONCATENATE($M$1,$K13) -> https://inmapper.com/zorlucenter/img/logo/ZTERZİ.png | K13: ZTERZİ.png | L13: Hizmet Mağazaları
A14: ID-306 | B14: Rossmann | E14: -3 | F14: +902123536933 | G14: kozmetik, bakım, temizlik, makyaj, aksesuar, cosmetic, care, cleaning, makeup, accessory, rosman | H14: cosmetics_health | I14: www.rossmann.com.tr | J14: =CONCATENATE($M$1,$K14) -> https://inmapper.com/zorlucenter/img/logo/ROSSMANN.png | K14: ROSSMANN.png | L14: Kozmetik & Sağlık
A15: ID-308 | B15: Vennüs Telefon Teknik | E15: -3 | F15: +902124030025 | G15: venüs, venus, telefon, tablet, teknik, teknoloji, mobil, phone, tablet, technic, technology, mobile | H15: servicestores | J15: =CONCATENATE($M$1,$K15) -> https://inmapper.com/zorlucenter/img/logo/VENNUS.png | K15: VENNUS.png | L15: Hizmet Mağazaları
A16: ID-309 | B16: Balonika | E16: -3 | F16: +902123536944 | G16: oyuncak, parti, çocuk, bebek, baskı, oyuncak, parti, çocuk, bebek, baskı | H16: culture_entertainment | J16: =CONCATENATE($M$1,$K16) -> https://inmapper.com/zorlucenter/img/logo/BALONIKA.png | K16: BALONIKA.png | L16: Kültür & Eğlence
A17: ID-310 | B17: Usta Saat | E17: -3 | F17: +902123248353 | G17: saat, pil, kayış, kordon, kadran, watch, battery, strap, cord, dial, tamir, repair | H17: servicestores | J17: =CONCATENATE($M$1,$K17) -> https://inmapper.com/zorlucenter/img/logo/USTASAAT.png | K17: USTASAAT.png | L17: Hizmet Mağazaları
A18: ID-312 | B18: Uranüs | E18: -3 | F18: +902123536912 | G18: telefon, kap, ekran koruyucu, phone, cover, screen protector, mobile oufitters | H18: electronics | J18: =CONCATENATE($M$1,$K18) -> https://inmapper.com/zorlucenter/img/logo/URANUS.png | K18: URANUS.png | L18: Elektronik
A19: ID-313 | B19: MediaMarkt | D19: ID-312 | E19: -3 | F19: +908502221500 | G19: medyamarket, elektronik, telefon, bilgisayar, laptop, teknoloji, electronics, phone, computer, laptop, technology | H19: electronics | I19: www.mediamarkt.com.tr | J19: =CONCATENATE($M$1,$K19) -> https://inmapper.com/zorlucenter/img/logo/MEDIAMARKT.png | K19: MEDIAMARKT.png | L19: Elektronik
A20: ID-314 | B20: Eve | E20: -3 | F20: - | H20: cosmetics_health | I20: www.eveshop.com.tr | J20: =CONCATENATE($M$1,$K20) -> https://inmapper.com/zorlucenter/img/logo/EVE.png | K20: EVE.png | L20: Kozmetik & Sağlık
A21: ID-315 | B21: Erkan Taş Podyum Terzi | E21: -3 | F21: +905458523899 | G21: dikiş, onarım, tadilat, küçültme, büyültme, sewing, repair, modification, reduction, magnification | H21: servicestores | J21: =CONCATENATE($M$1,$K21) -> https://inmapper.com/zorlucenter/img/logo/ERKANTAS.png | K21: ERKANTAS.png | L21: Hizmet Mağazaları
A22: ID-316 | B22: Yalçınlar | E22: -3 | F22: +902123536700 | G22: fotoğraf, makine, film, baskı, vesikalık, photography, machine, film, printing, mug shot | H22: servicestores | I22: www.fotomaks.com.tr | J22: =CONCATENATE($M$1,$K22) -> https://inmapper.com/zorlucenter/img/logo/YALÇINLAR.png | K22: YALÇINLAR.png | L22: Hizmet Mağazaları
A23: ID-317 | B23: Zorlu PSM | C23: {“id”:”floormetro”} | E23: -3 | F23: +908502226776 | G23: etkinlik, gösteri, tiyatro, konser, bilet, activity, show, theater, concert, ticket | H23: culture_entertainment | L23: Kültür & Eğlence
A24: ID-318 | B24: Penelope | E24: -3 | F24: +902123536963 | G24: yatak, uyku, yastık, kılıf, tekstil, bed, sleeping, pillow, sheath, textile, penelop | H24: home_decoration | I24: www.penelopebedroom.com | J24: =CONCATENATE($M$1,$K24) -> https://inmapper.com/zorlucenter/img/logo/PENELOPE.png | K24: PENELOPE.png | L24: Ev & Dekorasyon
A25: locker-301 | B25: {“id”:”locker”} | E25: -3 | F25: - | G25: emanet dolabı, safety deposit locker, box | H25: services | L25: Hizmet Mağazaları
A26: metrobus-301 | B26: {“id”:”metro”} {“id”:”metrobus”} | E26: -3 | F26: - | G26: metro, metrobüs, iett, otobüs, durak, subway, metrobus, iett, bus, stall
A27: baby-201 | B27: {“id”:”baby”} | E27: -2 | F27: - | G27: bebek, oda, bakım, emzik, meme, baby, room, care, pacifier, breast
A28: baby-202 | B28: {“id”:”baby”} | E28: -2 | F28: - | G28: bebek, oda, bakım, emzik, meme, baby, room, care, pacifier, breast
A29: ID-201 | B29: Zor {“id”:”exchange”} | E29: -2 | F29: +902123536268 | G29: döviz, para, dolar, euro, altın, currency, currency, dollar, euro, gold | H29: servicestores | J29: =CONCATENATE($M$1,$K29) -> https://inmapper.com/zorlucenter/img/logo/ZORDÖVİZ.png | K29: ZORDÖVİZ.png | L29: Hizmet Mağazaları
A30: ID-201A | B30: Paribu Cineverse | E30: -2 | F30: +908502200967 | G30: sinema, bilet, film, mısır, koltuk, cinema, ticket, movie, popcorn, seat | H30: culture_entertainment | I30: www.paribucineverse.com | J30: =CONCATENATE($M$1,$K30) -> https://inmapper.com/zorlucenter/img/logo/PARIBUCINEVERSE.png | K30: PARIBUCINEVERSE.png | L30: Kültür & Eğlence
A31: ID-201B | B31: House of Design | E31: -2 | F31: +905427330715 | G31: tasarım, akesuar, design, accessories | H31: accessories_jewellery | I31: www.houseofdesign.store.com | J31: =CONCATENATE($M$1,$K31) -> https://inmapper.com/zorlucenter/img/logo/HOUSEOFDESIGN.png | K31: HOUSEOFDESIGN.png | L31: Aksesuar & Mücevher
A32: ID-202 | B32: Dagi | E32: -2 | F32: +908502597504 | G32: iç çamaşırı, pijama, mayo, çorap, uyku, lingerie, pajamas, swimsuit, stockings, sleeping | H32: fashion | I32: www.dagi.com.tr | J32: =CONCATENATE($M$1,$K32) -> https://inmapper.com/zorlucenter/img/logo/DAGİ.png | K32: DAGİ.png | L32: Giyim
A33: ID-203 | B33: Tartine et Chocolat | E33: -2 | F33: +902123536050 | G33: çocuk, bebek, elbise, oyuncak, yatak, child, baby, dress, toy, bed, tartin et çaklıt | H33: kids | I33: www.tartine-et-chocolat.fr | J33: =CONCATENATE($M$1,$K33) -> https://inmapper.com/zorlucenter/img/logo/TARTINEETCHOCOLAT.png | K33: TARTINEETCHOCOLAT.png | L33: Çocuk
A34: ID-204 | B34: Skechers | E34: -2 | F34: +902123536543 | G34: ayakkabı, spor, sandalet, shoes, sports, sandals | H34: shoes_bags | I34: www.skechers.com | J34: =CONCATENATE($M$1,$K34) -> https://inmapper.com/zorlucenter/img/logo/SKECHERS.png | K34: SKECHERS.png | L34: Ayakkabı & Çanta
A35: ID-205 | B35: Starbucks | E35: -2 | F35: +902123536110 | G35: kahve, içecek, yiyecek, kek, sandviç, coffee, beverage, food, cake, sandwich, sıtarbaks | H35: restaurant_cafe | I35: www.starbucks.com.tr | J35: =CONCATENATE($M$1,$K35) -> https://inmapper.com/zorlucenter/img/logo/STARBUCKS.png | K35: STARBUCKS.png | L35: Restoran & Cafe
A36: ID-206 | B36: House of SuperStep | E36: -2 | F36: - | H36: shoes_bags | I36: www.houseofsuperstep.com | J36: =CONCATENATE($M$1,$K36) -> https://inmapper.com/zorlucenter/img/logo/HOUSEOFSUPERSTEP.png | K36: HOUSEOFSUPERSTEP.png | L36: Ayakkabı & Çanta
A37: ID-207 | B37: Sephora | E37: -2 | F37: +902127032087 | G37: makyaj, krem, bakım, ruj, pudra, makeup, cream, care, lipstick | H37: cosmetics_health | I37: www.sephora.com | J37: =CONCATENATE($M$1,$K37) -> https://inmapper.com/zorlucenter/img/logo/SEPHORA.png | K37: SEPHORA.png | L37: Kozmetik & Sağlık
A38: ID-208 | B38: Under Armour | E38: -2 | F38: +902123536544 | G38: spor, giyim, ayakkabı, tshirt, eşofman, sport, clothing, shoes, tshirt, tracksuit, andır armor | H38: fashion | I38: www.underarmour.com | J38: =CONCATENATE($M$1,$K38) -> https://inmapper.com/zorlucenter/img/logo/UNDERARMOUR.png | K38: UNDERARMOUR.png | L38: Giyim
A39: ID-209 | B39: Adidas | E39: -2 | F39: +902123536230 | G39: spor, giyim, ayakkabı, tshirt, eşofman, sport, clothing, shoes, tshirt, tracksuit | H39: fashion | I39: www.adidas.com | J39: =CONCATENATE($M$1,$K39) -> https://inmapper.com/zorlucenter/img/logo/ADİDAS.png | K39: ADİDAS.png | L39: Giyim
A40: ID-210 | B40: Asics | E40: -2 | F40: +902123536292 | G40: spor, giyim, ayakkabı, tshirt, eşofman, sport, clothing, shoes, tshirt, tracksuit | H40: fashion | I40: www.asicstr.com | J40: =CONCATENATE($M$1,$K40) -> https://inmapper.com/zorlucenter/img/logo/ASICS.png | K40: ASICS.png | L40: Giyim
A41: ID-211 | B41: Mavi | E41: -2 | F41: +902127033023 | G41: giyim, ayakkabı, jeans, gömlek, tshirt, clothing, shoes, jeans, shirt, tshirt | H41: fashion | I41: www.mavi.com | J41: =CONCATENATE($M$1,$K41) -> https://inmapper.com/zorlucenter/img/logo/MAVİ.png | K41: MAVİ.png | L41: Giyim
A42: ID-212 | B42: Gap | E42: -2 | F42: +902123536139 | G42: giyim, ayakkabı, jeans, gömlek, tshirt, clothing, shoes, jeans, shirt, tshirt, gep | H42: fashion | I42: www.gap.com.tr | J42: =CONCATENATE($M$1,$K42) -> https://inmapper.com/zorlucenter/img/logo/GAP.png | K42: GAP.png | L42: Giyim
A43: ID-213 | B43: İpekyol | E43: -2 | F43: +902123536707 | G43: kadın, giyim, moda, aksesuar, ayakkabı, woman, clothing, fashion, accessory, shoe | H43: fashion | I43: www.ipekyol.com.tr | J43: =CONCATENATE($M$1,$K43) -> https://inmapper.com/zorlucenter/img/logo/İPEKYOL.png | K43: İPEKYOL.png | L43: Giyim
A44: ID-214 | B44: Brandy's | E44: -2 | F44: +902123536370 | G44: Emporio Armani, Versace Jeans Couture, Hugo Boss, Calvin Klein, EA7 Emporio Armani, Tommy Hilfiger, Lacoste, kadın, giyim, moda, aksesuar, ayakkabı, woman, clothing, fashion, accessory, shoe | H44: fashion | I44: www.brandys.com.tr | J44: =CONCATENATE($M$1,$K44) -> https://inmapper.com/zorlucenter/img/logo/BRANDY'S.png | K44: BRANDY'S.png | L44: Giyim
A45: ID-215 | B45: Nike by Levazım | E45: -2 | F45: +908502236000/311 | H45: fashion | I45: www.nike.com.tr | J45: =CONCATENATE($M$1,$K45) -> https://inmapper.com/zorlucenter/img/logo/NIKE.png | K45: NIKE.png | L45: Giyim
A46: ID-216 | B46: Victoria's Secret Pink | E46: -2 | F46: +908503127055 | G46: iç çamaşırı, mayo, pijama, çorap, uyku, lingerie, swimsuit, pajamas, stockings, sleep, viktoryas sikrıt pink | H46: fashion | I46: www.victoriassecret.com.tr/pink | L46: Giyim
A47: ID-217 | B47: Victoria's Secret | E47: -2 | F47: +908503127055 | G47: iç çamaşırı, mayo, pijama, çorap, uyku, lingerie, swimsuit, pajamas, stockings, sleep, viktoryas sikrıt | H47: fashion | I47: www.victoriassecret.com.tr | J47: =CONCATENATE($M$1,$K47) -> https://inmapper.com/zorlucenter/img/logo/VICTORIA'SSECRET.png | K47: VICTORIA'SSECRET.png | L47: Giyim
A48: ID-218 | B48: Abdullah Kiğılı Exclusive Cut | E48: -2 | F48: +902123536130 | G48: erkek, giyim, takım, gömlek, ayakkabı, men, clothing, team, shirt, shoes, ekskulisiv kat | H48: fashion | I48: www.abdullahkigili.com | J48: =CONCATENATE($M$1,$K48) -> https://inmapper.com/zorlucenter/img/logo/ABDULLAHKİĞILI.png | K48: ABDULLAHKİĞILI.png | L48: Giyim
A49: ID-219 | B49: Penti | E49: -2 | F49: +902123536320 | G49: çorap, iç çamaşırı, pijama, aksesuar, ev giyim, socks, lingerie, pajamas, accessories, home clothing | H49: fashion | I49: www.penti.com.tr | J49: =CONCATENATE($M$1,$K49) -> https://inmapper.com/zorlucenter/img/logo/PENTİ.png | K49: PENTİ.png | L49: Giyim
A50: ID-220 | B50: H&M | E50: -2 | F50: +902123536002-03-04-05 | G50: giyim, moda, jeans, tshirt, aksesuar, clothing, fashion, jeans, tshirt, accessory, eyç en em | H50: fashion | I50: www.hm.com.tr | J50: =CONCATENATE($M$1,$K50) -> https://inmapper.com/zorlucenter/img/logo/H&M.png | K50: H&M.png | L50: Giyim
A51: ID-221 | B51: Perspective | E51: -2 | F51: +908504500322 | G51: kadın, giyim, aksesuar, ayakkabı, elbise, woman, clothing, accessories, shoes, dress, perspektiv | H51: fashion | I51: www.perspective.com.tr | J51: =CONCATENATE($M$1,$K51) -> https://inmapper.com/zorlucenter/img/logo/PERSPECTIVE.png | K51: PERSPECTIVE.png | L51: Giyim
A52: ID-222 | B52: Twist | E52: -2 | F52: +902123536800 | G52: kadın, giyim, aksesuar, ayakkabı, elbise, woman, clothing, accessories, shoes, dress, tivist | H52: fashion | I52: www.twist.com.tr | J52: =CONCATENATE($M$1,$K52) -> https://inmapper.com/zorlucenter/img/logo/TWIST.png | K52: TWIST.png | L52: Giyim
A53: ID-223 | B53: Aldo | E53: -2 | F53: +908505024880 | G53: ayakkabı, çanta, bot, aksesuar, sandalet, shoes, bags, boots, accessories, sandals | H53: shoes_bags | I53: www.aldoshoes.com.tr | J53: =CONCATENATE($M$1,$K53) -> https://inmapper.com/zorlucenter/img/logo/ALDO.png | K53: ALDO.png | L53: Ayakkabı & Çanta
A54: ID-224 | B54: Cacharel | E54: -2 | F54: +902123536221 | G54: erkek, giyim, takım, gömlek, ayakkabı, men, clothing, team, shirt, shoes, kaşarel | H54: fashion | I54: www.cacharel-tr.com | J54: =CONCATENATE($M$1,$K54) -> https://inmapper.com/zorlucenter/img/logo/CACHAREL.png | K54: CACHAREL.png | L54: Giyim
A55: ID-225 | B55: Camper | E55: -2 | F55: +902123536437 | G55: spor, ayakkabı, sport, shoes, sneaker | H55: shoes_bags | I55: www.camper.com | J55: =CONCATENATE($M$1,$K55) -> https://inmapper.com/zorlucenter/img/logo/CAMPER.png | K55: CAMPER.png | L55: Ayakkabı & Çanta
A56: ID-226 | B56: Yves Rocher | E56: -2 | F56: +902123536357 | G56: bakım, makyaj, saç, parfüm, vücut, care, makeup, hair, perfume, body, iv roşe | H56: cosmetics_health | I56: www.yvesrocher.com.tr | J56: =CONCATENATE($M$1,$K56) -> https://inmapper.com/zorlucenter/img/logo/YVESROCHER.png | K56: YVESROCHER.png | L56: Kozmetik & Sağlık
A57: ID-227 | B57: MAC | E57: -2 | F57: +902123536910 | G57: bakım, makyaj, ruj, pudra, allık, care, makeup, lipstick, powder, blush, mek | H57: cosmetics_health | I57: www.maccosmetics.com.tr | J57: =CONCATENATE($M$1,$K57) -> https://inmapper.com/zorlucenter/img/logo/M.A.C.png | K57: M.A.C.png | L57: Kozmetik & Sağlık
A58: ID-228 | B58: Mango | E58: -2 | F58: +902123536150 | G58: kadın, giyim, moda, aksesuar, ayakkabı, woman, clothing, fashion, accessory, shoe | H58: fashion | I58: www.mango.com | J58: =CONCATENATE($M$1,$K58) -> https://inmapper.com/zorlucenter/img/logo/MANGO.png | K58: MANGO.png | L58: Giyim
... A60: ID-230 | B60: Massimo Dutti | E60: -2 | F60: +902129550420 | G60: giyim, takım, ayakkabı, aksesuar, elbise, clothing, suit, shoes, accessory, dress | H60: fashion | I60: www.massimodutti.com | J60: =CONCATENATE($M$1,$K60) -> https://inmapper.com/zorlucenter/img/logo/MASSIMODUTTI.png | K60: MASSIMODUTTI.png | L60: Giyim
A61: ID-232 | B61: HeartBeat | E61: -2 | F61: +905303990097 | G61: ayakkabı, spor, bot, sandalet, terlik, shoes, sport, boots, sandals, slippers, süpersitep | H61: shoes_bags | J61: =CONCATENATE($M$1,$K61) -> https://inmapper.com/zorlucenter/img/logo/HEARTBEAT.png | K61: HEARTBEAT.png | L61: Ayakkabı & Çanta
A62: ID-233 | B62: Saat & Saat | E62: -2 | F62: +902123536565 | G62: saat, kayış, aksesuar, klasik, spor, watch, strap, accessory, classic, sport | H62: accessories_jewellery | I62: www.saatvesaat.com.tr | J62: =CONCATENATE($M$1,$K62) -> https://inmapper.com/zorlucenter/img/logo/SAAT&SAAT.png | K62: SAAT&SAAT.png | L62: Aksesuar & Mücevher
A63: ID-234 | B63: Sneaks Up | E63: -2 | F63: +905363298536 | G63: spor, basketball, koşu, ayakkabı, giyim, sport, basketball, running, shoes, clothing, sineks ap | H63: shoes_bags | I63: www.sneaksup.com.tr | J63: https://inmapper.com/zorlucenter/img/logo/SNEAKS UP.png | K63: SNEAKS UP.png | L63: Ayakkabı & Çanta
A64: ID-235 | B64: Jacadi Paris | E64: -2 | F64: +902123536329 | G64: bebek, çocuk, ayakkabı, kız, erkek, baby, child, shoes, girl, boy, cakadi | H64: kids | I64: www.jacadi.com | J64: =CONCATENATE($M$1,$K64) -> https://inmapper.com/zorlucenter/img/logo/JACADIPARIS.png | K64: JACADIPARIS.png | L64: Çocuk
A65: ID-236 | B65: Columbia | E65: -2 | F65: +908502831797 | G65: outdoor, giyim, ayakkabı, ekipman, polar, outdoor, clothing, shoes, equipment, fleece, kolumbiya | H65: fashion | I65: www.columbia.com.tr | J65: =CONCATENATE($M$1,$K65) -> https://inmapper.com/zorlucenter/img/logo/COLUMBIA.png | K65: COLUMBIA.png | L65: Giyim
A66: ID-237 | B66: B&G Store | E66: -2 | F66: +902123536263 | G66: çocuk, bebek, giyim, kız, erkek, child, baby, clothing, girl, boy | H66: kids | I66: www.bgstoreonline.com | J66: =CONCATENATE($M$1,$K66) -> https://inmapper.com/zorlucenter/img/logo/B&GSTORE.png | K66: B&GSTORE.png | L66: Çocuk
A67: ID-238 | B67: Levi's | E67: -2 | F67: +902123536918 | G67: kot pantolon, gömlek, erkek, kadın, tshirt, jeans, shirt, men, women, tshirt, livays | H67: fashion | I67: www.levis.com.tr | J67: =CONCATENATE($M$1,$K67) -> https://inmapper.com/zorlucenter/img/logo/LEVI'S.png | K67: LEVI'S.png | L67: Giyim
A68: ID-239 | B68: Minycenter Carter’s | E68: -2 | F68: +902123536366 | G68: çocuk, bebek, giyim, kız, erkek, child, baby, clothing, girl, boy, karters, carter's, oshkosh b'gosh | H68: kids | I68: www.minycenter.com.tr | J68: =CONCATENATE($M$1,$K68) -> https://inmapper.com/zorlucenter/img/logo/MINYCENTERCARTER'S.png | K68: MINYCENTERCARTER'S.png | L68: Çocuk
A69: ID-240 | B69: Atelier Rebul | E69: -2 | F69: +908505498157 | G69: parfüm, koku, amber, kolonya, bakım, perfume, fragrance, amber, cologne, care, ateliyer | H69: cosmetics_health | I69: www.atelierrebul.com | J69: =CONCATENATE($M$1,$K69) -> https://inmapper.com/zorlucenter/img/logo/ATELIERREBUL.png | K69: ATELIERREBUL.png | L69: Kozmetik & Sağlık
A70: ID-241 | B70: Emo Optik | E70: -2 | F70: +902123536616 | G70: gözlük, güneş, ray-ban, armani, prada, glasses, sun, ray-ban, armani, prada | H70: accessories_jewellery | I70: www.emooptik.com.tr | J70: =CONCATENATE($M$1,$K70) -> https://inmapper.com/zorlucenter/img/logo/EMOOPTİK.png | K70: EMOOPTİK.png | L70: Aksesuar & Mücevher
A71: ID-243 | B71: Hello Sweetie | E71: -2 | F71: +902123536952 | G71: şeker, jelibon, çocuk, yiyecek, ayıcık, candy, jellybeans, child, food, teddy bear, hello siviti, haribo | H71: turkishdelight_confectionery | J71: =CONCATENATE($M$1,$K71) -> https://inmapper.com/zorlucenter/img/logo/HELLOSWEETIE.png | K71: HELLOSWEETIE.png | L71: Lokum & Şekerleme
A72: ID-244 | B72: Apple | E72: -2 | F72: +902127083700 | G72: iphone, macbook, ipad, genius bar, pro, iphone, macbook, ipad, genius bar, pro, epıl | H72: electronics | I72: www.apple.com | J72: =CONCATENATE($M$1,$K72) -> https://inmapper.com/zorlucenter/img/logo/APPLESTORE.png | K72: APPLESTORE.png | L72: Elektronik
A73: ID-245 | B73: Cheers Bar&Bar Food | E73: -2 | F73: +902129240125 | G73: bar, psm, alkol, kokteyl, içki, bar, psm, alcohol, cocktail, drink | H73: restaurant_cafe | L73: Restoran & Cafe
A74: ID-245 | B74: Studio | E74: -2 | F74: - | G74: kulüp, performans, etkinlik, club, performance, event, psm | H74: culture_entertainment | L74: Kültür & Eğlence
A75: ID-245 | B75: Touche | E75: -2 | F75: +902129240128 | G75: kulüp, performans, etkinlik, club, performance, event, psm | H75: culture_entertainment | L75: Kültür & Eğlence
A76: ID-245 | B76: Zorlu PSM | C76: {“id”:”floormetro”} | E76: -2 | F76: +908502226776 | G76: etkinlik, gösteri, tiyatro, konser, bilet, activity, show, theater, concert, ticket | H76: culture_entertainment | L76: Kültür & Eğlence
A77: ID-247 | B77: Tumi | E77: -2 | F77: +902126922323 | H77: shoes_bags | I77: www.tumi.com.tr | J77: =CONCATENATE($M$1,$K77) -> https://inmapper.com/zorlucenter/img/logo/TUMI.png | K77: TUMI.png | L77: Ayakkabı & Çanta
A78: ID-248 | B78: Dyson | E78: -2 | F78: +905394701299 | G78: daysın, süpürge, vakum, toz, vacuum cleaner, vacuum, dust, kablosuz , wireless | H78: electronics | I78: www.dyson.com | J78: =CONCATENATE($M$1,$K78) -> https://inmapper.com/zorlucenter/img/logo/DYSON.png | K78: DYSON.png | L78: Elektronik
A79: ID-248A | B79: Pembecida | E79: -2 | F79: +908505200511 | G79: kırtasiye, hobi, parti, ev, yaşam, stationery, hobby, party, home, life, pembesida | H79: kids | I79: www.pembecida.com | J79: =CONCATENATE($M$1,$K79) -> https://inmapper.com/zorlucenter/img/logo/PEMBECİDA.png | K79: PEMBECİDA.png | L79: Çocuk
A80: ID-249 | B80: Ametist | E80: -2 | F80: +902123536174 | G80: aksesuar, küpe, kolye, bileklik, yüzük, accessory, earring, necklace, wristband, ring | H80: accessories_jewellery | I80: www.ametististanbul.com | J80: =CONCATENATE($M$1,$K80) -> https://inmapper.com/zorlucenter/img/logo/AMETIST.png | K80: AMETIST.png | L80: Aksesuar & Mücevher
A81: ID-250 | B81: Lamy | E81: -2 | F81: +902122586715 | G81: lamy, kalem, dolma kalem, tükenmez kalem, versatil kalem, uçlu kalem, roller kalem, alman, lamyshop | H81: accessories_jewellery | I81: www.lamyshop.com.tr | J81: =CONCATENATE($M$1,$K81) -> https://inmapper.com/zorlucenter/img/logo/LAMY.png | K81: LAMY.png | L81: Aksesuar & Mücevher
A82: ID-253 | B82: Maison Pereja | E82: -2 | F82: - | G82: pereja,kolonya,parfüm,mum,oda parfümü,diffuser, çubuklu oda kokusu, lüks koku | H82: cosmetics_health | I82: www.maisonpereja.com | J82: =CONCATENATE($M$1,$K82) -> https://inmapper.com/zorlucenter/img/logo/MAISONPEREJA.png | K82: MAISONPEREJA.png | L82: Kozmetik & Sağlık
A83: ID-254 | B83: KIKO Milano | E83: -2 | F83: +908508005456 | H83: cosmetics_health | I83: www.kikomilano.com.tr | J83: =CONCATENATE($M$1,$K83) -> https://inmapper.com/zorlucenter/img/logo/KIKOMILANO.png | K83: KIKOMILANO.png | L83: Kozmetik & Sağlık
A84: ID-255 | B84: MediaMarkt | D84: ID-201A | E84: -2 | F84: +908502221500 | G84: medyamarket, elektronik, telefon, bilgisayar, laptop, teknoloji, electronics, phone, computer, laptop, technology | H84: electronics | I84: www.mediamarkt.com.tr | J84: =CONCATENATE($M$1,$K84) -> https://inmapper.com/zorlucenter/img/logo/MEDIAMARKT.png | K84: MEDIAMARKT.png | L84: Elektronik
A85: ID-256 | B85: Alo Yoga | E85: -2 | F85: - | H85: fashion | I85: www.aloyoga.com | J85: =CONCATENATE($M$1,$K85) -> https://inmapper.com/zorlucenter/img/logo/ALO.png | K85: ALO.png | L85: Giyim
A86: infirmaryEN-201 | B86: {“id”:”infirmary”} | E86: -2 | F86: - | G86: eczane, ilaç, reçete, doktor, tedavi, pharmacy, medicine, prescription, doctor, treatment | H86: services | L86: Hizmetler
A87: infirmaryTR-201 | B87: {“id”:”infirmary”} | E87: -2 | F87: - | G87: eczane, ilaç, reçete, doktor, tedavi, pharmacy, medicine, prescription, doctor, treatment | H87: services | L87: Hizmetler
A88: info-201 | B88: {“id”:”infodesk”} | E88: -2 | F88: +902129240124 | G88: bilgi, danışma, soru, telefon, duyuru, information, consultation, question, phone, announcement | H88: services | L88: Hizmetler
A89: wc-201 | B89: {“id”:”wc”} | E89: -2 | F89: - | G89: tuvalet, lavabo, sabun, mendil, su, toilet, sink, soap, handkerchief, water
A90: wc-202 | B90: {“id”:”wc”} | E90: -2 | F90: - | G90: tuvalet, lavabo, sabun, mendil, su, toilet, sink, soap, handkerchief, water
A91: baby-101 | B91: {“id”:”baby”} | E91: -1 | F91: - | G91: bebek, oda, bakım, emzik, meme, baby, room, care, pacifier, breast
A92: baby-102 | B92: {“id”:”baby”} | E92: -1 | F92: - | G92: bebek, oda, bakım, emzik, meme, baby, room, care, pacifier, breast
A93: entrance-101 | B93: {“id”:”entrance”} Levazım | E93: -1 | F93: - | G93: giriş, çıkış, kapı, bekleme, güvenlik, entrance, exit, door, waiting, security
A94: ID-101 | B94: Zara | E94: -1 | F94: - | G94: giyim, kadın, erkek, ayakkabı, moda, clothing, women, men, shoes, fashion | H94: fashion | I94: www.zara.com | J94: =CONCATENATE($M$1,$K94) -> https://inmapper.com/zorlucenter/img/logo/ZARA.png | K94: ZARA.png | L94: Giyim
A95: ID-102 | B95: Bakırkazan | E95: -1 | F95: +902128060351 | G95: yemek, tatlı, lokum, şekerleme, badem, food, sweet, turkish delight, confectionery, almond | H95: turkishdelight_confectionery | I95: www.bakirkazan.com | J95: =CONCATENATE($M$1,$K95) -> https://inmapper.com/zorlucenter/img/logo/BAKIRKAZAN.png | K95: BAKIRKAZAN.png | L95: Lokum & Şekerleme
A96: ID-104 | B96: Watsons | E96: -1 | F96: +902123536647 | G96: kozmetik, bakım, makyaj, temizlik, banyo, cosmetic, care, makeup, cleaning, bathroom, vatsıns, vatsons | H96: cosmetics_health | I96: www.watsons.com.tr | J96: =CONCATENATE($M$1,$K96) -> https://inmapper.com/zorlucenter/img/logo/WATSONS.png | K96: WATSONS.png | L96: Kozmetik & Sağlık
A97: ID-105 | B97: Turkcell | E97: -1 | F97: +902123536200 | G97: telefon, hat, sim, tarife, internet, phone, line, sim, tariff, internet, türksell | H97: electronics | I97: www.turkcell.com.tr | J97: =CONCATENATE($M$1,$K97) -> https://inmapper.com/zorlucenter/img/logo/TURKCELL.png | K97: TURKCELL.png | L97: Elektronik
A98: ID-106 | B98: Tobacco Shop | E98: -1 | F98: +902123536279 | G98: tütün, sigara, çakmak, puro, gaz, tobacco, cigarette, lighter, cigar, gas, tobakko şop | H98: servicestores | I98: www.tobaccoshop.com.tr | J98: =CONCATENATE($M$1,$K98) -> https://inmapper.com/zorlucenter/img/logo/TOBACCOSHOP.png | K98: TOBACCOSHOP.png | L98: Hizmet Mağazaları
A99: ID-107 | B99: Plus Kitchen | E99: -1 | F99: +905377788650 | G99: kahvaltı, sandviç, wrap, meze, yemek, breakfast, sandwich, wrap, appetizer, food, pılas kiçın | H99: restaurant_cafe | I99: www.pluskitchen.com.tr | J99: =CONCATENATE($M$1,$K99) -> https://inmapper.com/zorlucenter/img/logo/PLUSKITCHEN.png | K99: PLUSKITCHEN.png | L99: Restoran & Cafe
A100: ID-108 | B100: Intimissimi | E100: -1 | F100: +902123536117 | G100: iç çamaşırı, erkek, kadın, sütyen, çorap, lingerie, men, women, bra, stockings | H100: fashion | I100: www.intimissimi.com | J100: =CONCATENATE($M$1,$K100) -> https://inmapper.com/zorlucenter/img/logo/INTIMISSIMI.png | K100: INTIMISSIMI.png | L100: Giyim
A101: ID-109 | B101: Falconeri | E101: -1 | F101: +902123536904 | G101: cashmere, wool, yarn, kaşmir, yün, iplik, elbise, clothing | H101: fashion | I101: www.falconeri.com | J101: =CONCATENATE($M$1,$K101) -> https://inmapper.com/zorlucenter/img/logo/FALCONERI.png | K101: FALCONERI.png | L101: Giyim
...

Sheet Extension
A1: Time | B1: Stage | C1: ID | D1: title_tr | E1: subtext_tr | F1: footnote_tr | G1: title_en | H1: subtext_en | I1: footnote_en | J1: icon | K1: img | L1: enabled | M1: start_date | N1: end_date | O1: status
A2: 17.11.2022 09:00:00 | B2: PROD | C2: ID116 | D2: Memorial Wellness'de X-Scan ile Ücretsiz Vücut Analizi! | E2: Uygulamayı indirerek QR okutmak için aşağıdaki butonu tıklayınız! | F2: Kampanya dahilinde Memorial Wellness Zorlu'da X-Scan ile Ücretsiz Vücut Analizi yapılacaktır. 31 Ağustos 2023 tarihine kadar geçerlidir. Zorlu World üyelerinin kampanyadan yararlanması için Zorlu World uygulamasından Memorial Wellness mağazasındaki QR kodu okutması gerekmektedir. Zorlu World ve Memorial Wellness kampanyada değişiklik yapma hakkını saklı tutar. Zorlu World, Zorlu Yapı Yatırım A.Ş. Müşteri Ödül Programı’dır. | G2: Free Body Analysis with X-Scan at Memorial Wellness! | H2: The app can be downloaded via button below in order to scan the QR code! | I2: In the scope of the campaign, body analysis with X-Scan can be benefit as free of charge at Memorial Wellness Zorlu until 31 May 2023. Zorlu World members are required to open the QR reading from the Zorlu World application and scan the QR code next to the cash register at Memorial Wellness in order to benefit from the campaign. Zorlu World and Memorial Wellness reserve the right to change the campaign. Zorlu World, Zorlu Yapı Yatırım A.Ş. Customer Reward Program. | J2: img/zw/icon/offer.png | K2: Memorial-Wellnessb-750x600.jpg | L2: TRUE | M2: 17.11.2022 | N2: 31.08.2023 | O2: active
A3: 05.12.2022 09:00:00 | B3: PROD | C3: ID061R | D3: Long Bar'da %10 İndirim! | E3: Uygulamayı indirerek kod almak için aşağıdaki butonu tıklayınız! | F3: Benzersiz lezzetler ve imza kokteyller ile dünyanın en iyilerini seyretmek için sen de Long Bar’da yerini al, futbol heyecanını Zorlu World’e özel %10 indirimli yaşa! Kampanya, Long Bar’dan vereceğiniz 200 TL ve üzeri siparişlerinizde 18 Aralık 2022 tarihine kadar geçerlidir. Diğer kampanyalarla birleştirilemez. Zorlu World üyelerinin kampanyadan yararlanması için Zorlu World uygulamasından kod alması ve alınmış olan kodu Long Bar kasasında bildirmesi gerekmektedir. Zorlu World ve Raffles Istanbul kampanyada değişiklik yapma hakkını saklı tutar. Zorlu World, Zorlu Yapı Yatırım A.Ş. Müşteri Ödül Programı’dır. 18 Aralık 2022 tarihine kadar geçerlidir. | G3: 10% Off at Long Bar! | H3: The app can be downloaded via button below in order to get the campaign code! | I3: Show up for your team, and watch all the games with delicious drafts, snacks, and signature cocktails to pitch your excitement with a 10% discount privilege for Zorlu World! The campaign is valid for the orders that is 200 TL or more, to be made at Long Bar until 18 December 2022. Cannot be combined with other campaigns. Zorlu World members are required to obtain a code from the Zorlu World application and notify the representative at the Long Bar cash register in order to benefit from the campaign. Zorlu World and Long Bar reserve the right to make changes to the campaign. Zorlu World, Zorlu Yapı Yatırım A.Ş. It is the Customer Reward Program. Valid until 18 December 2022 | J3: img/zw/icon/offer.png | K3: Long-Bar-750x600.jpg | L3: TRUE | M3: 05.12.2022 | N3: 18.12.2022 | O3: passive
A4: 05.12.2022 09:00:00 | B4: PROD | C4: ID013 | D4: Tommi Brasserie'de Kahvaltı veya Öğle Yemeği Alımına %20 İndirim! | E4: Uygulamayı indirerek kod almak için aşağıdaki butonu tıklayınız! | F4: Kampanya kapsamında, Tommi Brasserie’den her gün saat 15:00 öncesinde vereceğiniz kahvaltı veya öğle yemeği siparişinize %20 indirim uygulanacaktır. 31 Aralık 2022 tarihine kadar geçerlidir. Diğer kampanyalarla birleştirilemez. Zorlu World üyelerinin kampanyadan yararlanması için Zorlu World uygulamasından kod alması ve alınmış olan kodu Tommi Brasserie kasasında restoran yetkilisine bildirmesi gerekmektedir. Zorlu World ve Tommi Brasserie kampanyada değişiklik yapma hakkını saklı tutar. Zorlu World, Zorlu Yapı Yatırım A.Ş. Müşteri Ödül Programı’dır. 31 Aralık 2022 tarihine kadar geçerlidir. | G4: %20 Off for Breakfeast or Lunch at Tommi Brasserie! | H4: The app can be downloaded via button below in order to get the campaign code! | I4: The campaign is valid until 3:00 pm every day for breakfeast or lunch orders to be made at Tommi Braserrie Zorlu until 31 December 2022. %20 discount will be applied within the scope of the campaign. Cannot be combined with other campaigns. Zorlu World members are required to obtain a code from the Zorlu World application and notify the restaurant representative at the Tommi Brasserie cash register in order to benefit from the campaign. Zorlu World and Tommi Brasserie reserve the right to make changes to the campaign. Zorlu World, Zorlu Yapı Yatırım A.Ş. It is the Customer Reward Program. Valid until 31 December 2022 | J4: img/zw/icon/offer.png | K4: Tommi-750x600.jpg | L4: TRUE | M4: 05.12.2022 | N4: 31.12.2022 | O4: passive
A5: 14.09.2022 09:00:00 | B5: PROD | C5: ID-235 | D5: Jacadi Paris Zorlu'da Tüm İndirimlere Ek %10 İndirim! | E5: Uygulamayı indirerek kod almak için aşağıdaki butonu tıklayınız! | F5: Kampanya, Jacadi Paris Zorlu mağazasında 31 Aralık 2023 tarihine kadar yapılacak tüm ürün alışverişlerinde geçerlidir. Tüm indirimlere ek %10 indirim uygulanacaktır. Zorlu World üyelerinin kampanyadan yararlanması için Zorlu World uygulamasından kod alması ve alınmış olan kodu Jacadi Paris kasasında mağaza yetkilisine bildirmesi gerekmektedir. Zorlu World ve Jacadi Paris kampanyada değişiklik yapma hakkını saklı tutar. Zorlu World, Zorlu Yapı Yatırım A.Ş. Müşteri Ödül Programı’dır. 31 Aralık 2023 tarihine kadar geçerlidir. | G5: Additional 10% Discount Privilege at Jacadi Paris! | H5: The app can be downloaded via button below in order to get the campaign code! | I5: The campaign is valid forall merchandise purchases made at Zorlu Center Jacadi Paris store until 31 December 2023. Additional 10% discount will be applied after all other valid discounts. Zorlu World members are required to obtain a code from the Zorlu World application and notify the store representative at the Jacadi Paris cash register in order to benefit from the campaign. Zorlu World and Jacadi Paris reserve the right to make changes to the campaign. Zorlu World, Zorlu Yapı Yatırım A.Ş. It is the Customer Reward Program. Valid until 31 December 2023 | J5: img/zw/icon/offer.png | K5: Jakardi-750x600.jpg | L5: TRUE | M5: 02.01.2023 | N5: 31.12.2023 | O5: active
A6: 14.04.2023 09:00:00 | B6: PROD | C6: ID113 | D6: Penelope Bedroom'da Seçili Ürünlerde %25 İndirim! | E6: Uygulamayı indirerek kod almak için aşağıdaki butonu tıklayınız! | F6: Kampanya, Zorlu Center Penelope Bedroom mağazasında 30 Nisan 2023 tarihine kadar yapılacak Bamboo Yorgan ve Bamboo Yastık model alışverişlerinde geçerlidir. %25 indirim uygulanacaktır. Zorlu World üyelerinin kampanyadan yararlanması için Zorlu World uygulamasından kod alması ve alınmış olan kodu Penelope Bedroom mağaza kasasında mağaza yetkilisine bildirmesi gerekmektedir. Zorlu World ve Penelope Bedroom kampanyada değişiklik yapma hakkını saklı tutar. Zorlu World, Zorlu Yapı Yatırım A.Ş. Müşteri Ödül Programı’dır. 30 Nisan 2023 tarihine kadar geçerlidir. | G6: 25% Off at Penelope Bedroom! | H6: The app can be downloaded via button below in order to get the campaign code! | I6: The campaign is valid for Bamboo pillow and Bamboo blanket purchases made at Zorlu Center Penelope Bedroom store until 30 April 2023. 25% discount will be applied. Zorlu World members are required to obtain a code from the Zorlu World application and notify the store representative at the Penelope Bedroom cash register in order to benefit from the campaign. Zorlu World and Penelope Bedroom reserve the right to make changes to the campaign. Zorlu World, Zorlu Yapı Yatırım A.Ş. It is the Customer Reward Program. Valid until 30 April 2023 | J6: img/zw/icon/offer.png | K6: Penelope-750x600-4.jpg | L6: TRUE | M6: 14.04.2023 | N6: 30.04.2023 | O6: passive
A7: 14.09.2022 09:00:00 | B7: PROD | C7: ID108 | D7: English Home’da 400 TL ve üzeri Alışverişlerinizde 50 TL indirim! | E7: Uygulamayı indirerek kod almak için aşağıdaki butonu tıklayınız! | F7: Kampanya, sadece English Home Zorlu mağazasında 31 Aralık 2023 tarihine kadar yapılacak 400 TL ve üzeri alışverişlerde geçerlidir. Tüm kampanya ve indirimlere ek 50 TL indirim uygulanacaktır. Matrah katlarında geçerli değildir. Zorlu World üyelerinin kampanyadan yararlanması için Zorlu World uygulamasından kod alması ve alınmış olan kodu English Home mağaza kasasında mağaza yetkilisine bildirmesi gerekmektedir. Zorlu World ve English Home kampanyada değişiklik yapma hakkını saklı tutar. Zorlu World, Zorlu Yapı Yatırım A.Ş. Müşteri Ödül Programı’dır. 31 Aralık 2023 tarihine kadar geçerlidir. | G7: 50 TL Off for 400 TL and more purchases at English Home! | H7: The app can be downloaded via button below in order to get the campaign code! | I7: The campaign is valid for 400 TL and more purchases to be made at only English Home Zorlu store until 31 December 2023. 50 TL discount will be applied to these purchases and can be discounted after all other campaigns and discounts. The campaign is not valid for the exponential tax base applications. Zorlu World members are required to obtain a code from the Zorlu World application and notify the store representative at the English Home cash register in order to benefit from the campaign. Zorlu World and English Home reserve the right to make changes to the campaign. Zorlu World, Zorlu Yapı Yatırım A.Ş. It is the Customer Reward Program. Valid until 31 December 2023 | J7: img/zw/icon/offer.png | K7: English-Home-750X600.jpg | L7: TRUE | M7: 04.01.2023 | N7: 31.12.2023 | O7: active
A8: 14.09.2022 09:00:00 | B8: PROD | C8: ID-154 | D8: BAQA'da 10.000 TL ve Üzeri Alışverişinize %10 İndirim! | E8: Uygulamayı indirerek kod almak için aşağıdaki butonu tıklayınız! | F8: Kampanya dahilinde 31 Aralık 2023 tarihine kadar, sadece BAQA Zorlu mağazasından yapacağınız 10.000 TL ve üzeri alışverişlerinize %10 indirim uygulanacaktır. Mağazada geçerli başka indirim ve kampanyalara ek olarak kullanılabilir. Zorlu World üyelerinin kampanyadan yararlanması için Zorlu World uygulamasından kod alması ve alınmış olan kodu BAQA mağaza kasasında mağaza yetkilisine bildirmesi gerekmektedir. Zorlu World ve BAQA kampanyada değişiklik yapma hakkını saklı tutar. Zorlu World, Zorlu Yapı Yatırım A.Ş. Müşteri Ödül Programı’dır. 31 Aralık 2023 tarihine kadar geçerlidir. | G8: %10 Off at BAQA Zorlu! | H8: The app can be downloaded via button below in order to get the campaign code! | I8: Within the scope of the campaign, until 31 December 2023, 10% discount can be received in addition to all discounts for the 10.000 TL and more purchases to be made at BAQA Zorlu store only. The campaign is valid for all product purchases. A code must be obtained from the Zorlu World mobile application to benefit from the campaign. Zorlu World members are required to obtain a code from the Zorlu World application and notify the store representative at the BAQA cash register in order to benefit from the campaign. Zorlu World and BAQA reserve the right to make changes to the campaign. Zorlu World, Zorlu Yapı Yatırım A.Ş. the Customer Reward Program. Valid until 31 December 2023 | J8: img/zw/icon/offer.png | K8: BAQA-750X600.jpg | L8: TRUE | M8: 03.01.2023 | N8: 31.12.2023 | O8: active
A9: 14.09.2022 09:00:00 | B9: PROD | C9: ID024 | D9: MAC Zorlu'da Hediye Ders Ayrıcalığı | E9: Uygulamayı indirerek kod almak için aşağıdaki butonu tıklayınız! | F9: Kampanya, MAC Zorlu'da 31 Aralık 2023 tarihine kadar geçerlidir. Kampanya kampsamında yapılacak %10 indirimli ve blokajlı yıllık üyelik kayıtlarında geçerli; aletli pilates, boks veya yüzme alanlarının birinden özel ders hediye edilecektir. Diğer kampanyalarla birleştirilemez. Zorlu World üyelerinin kampanyadan yararlanması için Zorlu World uygulamasından kod alması ve alınmış olan kodu MAC Zorlu yetkilisine bildirmesi gerekmektedir. Detaylı bilgi için ; 0212 970 16 53 Zorlu World ve MAC Zorlu mağazası kampanyada değişiklik yapma hakkını saklı tutar. Zorlu World, Zorlu Yapı Yatırım A.Ş. Müşteri Ödül Programı’dır. 31 Aralık 2023'e kadar geçerlidir. | G9: Private Lesson Privilege at MAC Zorlu | H9: The app can be downloaded via button below in order to get the campaign code! | I9: The campaign will be valid at MAC Zorlu until 31 December 2023 for %10 discounted 1 year membership registration(Blockage will be applied.). Private lesson on pilates with eqipment, boxing and swimming are the options for the campaign and one of them need to be choosen. The campaign cannot be combined with other campaigns. Do not forget to obtain your code from Zorlu World! For the details get contact with; 0212 970 16 53. In order to benefit from the campaign, Zorlu World members are required to obtain a code from the Zorlu World application and notify the store representative at the MAC Zorlu store cash register. Zorlu World and MAC Zorlu store reserve the right to change the campaign. Zorlu World, Zorlu Yapı Yatırım A.Ş. Customer Reward Program. Valid until 31 December 2023 | J9: img/zw/icon/offer.png | K9: Mac-750X600.jpg | L9: TRUE | M9: 02.01.2023 | N9: 31.12.2023 | O9: active
A10: 14.09.2022 09:00:00 | B10: PROD | C10: ID-146 | D10: Vario Zorlu'da %10 İndirim | E10: Uygulamayı indirerek kod almak için aşağıdaki butonu tıklayınız! | F10: Kampanya dahilinde 31 Aralık 2023 tarihine kadar sadece Vario Zorlu mağazasında, tüm indirimlere ek olarak %10 indirim uygulanacaktır. Kampanya tüm ürün alışverişlerinde geçerlidir. Kampanyadan faydalanmak için Zorlu World mobil uygulamasından kod alınması gerekmektedir. Zorlu World üyelerinin kampanyadan yararlanması için Zorlu World uygulamasından kod alması ve alınmış olan kodu Vario kasasında mağaza yetkilisine bildirmesi gerekmektedir. Zorlu World ve Vario kampanyada değişiklik yapma hakkını saklı tutar. Zorlu World, Zorlu Yapı Yatırım A.Ş. Müşteri Ödül Programı’dır. 31 Aralık 2023 tarihine kadar geçerlidir. | G10: 10% Off at Vario Zorlu! | H10: The app can be downloaded via button below in order to get the campaign code! | I10: Within the scope of the campaign, until 31 December 2023, only Vario Zorlu store will receive 10% discount in addition to all discounts. The campaign is valid for all product purchases. A code must be obtained from the Zorlu World mobile application to benefit from the campaign. Zorlu World members are required to obtain a code from the Zorlu World application and notify the store representative at the Vario cash register in order to benefit from the campaign. Zorlu World and Vario reserve the right to make changes to the campaign. Zorlu World, Zorlu Yapı Yatırım A.Ş. the Customer Reward Program. Valid until 31 December 2023 | J10: img/zw/icon/offer.png | K10: Vario-750x600.jpg | L10: TRUE | M10: 02.01.2023 | N10: 31.12.2023 | O10: active
A11: 14.09.2022 09:00:00 | B11: PROD | C11: ID035 | D11: Valeron'da 4.000 TL ve Üzeri Alışverişinize 750 TL İndirim! | E11: Uygulamayı indirerek kod almak için aşağıdaki butonu tıklayınız! | F11: Kampanya dahilinde 31 Aralık 2023 tarihine kadar Valeron Zorlu'dan yapılacak 4.000 TL ve üzeri alışverişlerde 750 TL indirim uygulanacaktır. Zorlu World üyelerinin kampanyadan yararlanması için Zorlu World uygulamasından kod alması ve alınmış olan kodu Valeron kasasında mağaza yetkilisine bildirmesi gerekmektedir. Zorlu World ve Valeron kampanyada değişiklik yapma hakkını saklı tutar. Zorlu World, Zorlu Yapı Yatırım A.Ş. Müşteri Ödül Programı’dır. 31 Aralık 2023 tarihine kadar geçerlidir. | G11: 750 TL Discount at Valeron Zorlu! | H11: The app can be downloaded via button below in order to get the campaign code! | I11: "Within the scope of the campaign, 750TL discount will be applied for purchases of 4.000 TL and above from Linens Zorlu until 31 December 2023. In order to benefit from the campaign, Zorlu World members are required to obtain a code from the Zorlu World application and notify the store representative at the Valeron cash register. Zorlu World and Valeron reserve the right to make changes to the campaign. Zorlu World, Zorlu Yapı Yatırım A.Ş. It is the Customer Reward Program. Valid until 31 December 2023" | J11: img/zw/icon/offer.png | K11: VALERON-750x600.jpg | L11: TRUE | M11: 03.01.2023 | N11: 31.12.2023 | O11: active
A12: 14.09.2022 09:00:00 | B12: PROD | C12: ID101 | D12: Linens'de 1.500 TL ve Üzeri Alışverişinize 250 TL İndirim! | E12: Uygulamayı indirerek kod almak için aşağıdaki butonu tıklayınız! | F12: Kampanya dahilinde 31 Aralık 2023 tarihine kadar Linens Zorlu'dan yapılacak 1.500 TL ve üzeri alışverişlere 250TL indirim uygulanacaktır. Perde kategorisindeki ürünler kampanyaya dahil değildir. Zorlu World üyelerinin kampanyadan yararlanması için Zorlu World uygulamasından kod alması ve alınmış olan kodu Linens mağaza kasasında mağaza yetkilisine bildirmesi gerekmektedir. Zorlu World ve Linens kampanyada değişiklik yapma hakkını saklı tutar. Zorlu World, Zorlu Yapı Yatırım A.Ş. Müşteri Ödül Programı’dır. 31 Aralık 2023 tarihine kadar geçerlidir. | G12: 250 TL Discount at Linens Zorlu! | H12: The app can be downloaded via button below in order to get the campaign code! | I12: Within the scope of the campaign, 250TL discount will be applied for purchases of 1.500 TL and above from Linens Zorlu until 31 December 2023. Products in the curtain category are not included in the campaign. In order to benefit from the campaign, Zorlu World members are required to obtain a code from the Zorlu World application and notify the store representative at the Linens cash register. Zorlu World and Linens reserve the right to make changes to the campaign. Zorlu World, Zorlu Yapı Yatırım A.Ş. It is the Customer Reward Program. Valid until 31 December 2023 | J12: img/zw/icon/offer.png | K12: LINENS-750x600.jpg | L12: TRUE | M12: 03.01.2023 | N12: 31.12.2023 | O12: active
A13: 14.09.2022 09:00:00 | B13: PROD | C13: ID-236 | D13: Columbia Zorlu'da Tüm İndirimlere Ek %5 İndirim! | E13: Uygulamayı indirerek kod almak için aşağıdaki butonu tıklayınız! | F13: Kampanya dahilinde; Columbia Zorlu mağazasından yapılacak 10.000 TL ve üzeri tüm alışverişlerde, tüm indirimlere ek olarak %5 indirim uygulanacaktır. 31 Aralık 2023 tarihine kadar geçerlidir. Zorlu World üyelerinin kampanyadan yararlanması için Zorlu World uygulamasından kod alması ve alınmış olan kodu Columbia mağaza kasasında mağaza yetkilisine bildirmesi gerekmektedir. Zorlu World ve Columbia kampanyada değişiklik yapma hakkını saklı tutar. Zorlu World, Zorlu Yapı Yatırım A.Ş. Müşteri Ödül Programı’dır. 31 Aralık 2023 tarihine kadar geçerlidir. | G13: Additional 5% Discount at Columbia Zorlu! | H13: The app can be downloaded via button below in order to get the campaign code! | I13: Within the scope of the campaign, an additional 5% discount on all other discounts, will be applied to your shopping that has a price of 10.000 TL and more. In order to benefit from the campaign, Zorlu World members are required to obtain a code from the Zorlu World application and notify the store representative at the Columbia Zorlu cash register. Zorlu World and Columbia reserve the right to change the campaign. Zorlu World, Zorlu Yapı Yatırım A.Ş. Customer Reward Program. Valid until 31 December 2023 | J13: img/zw/icon/offer.png | K13: Columbia-V3-750x600.jpg | L13: TRUE | M13: 02.01.2023 | N13: 31.12.2023 | O13: active
... A42: 22.12.2022 09:00:00 | B42: PROD | C42: ID119B | D42: Collection Point’de 2.000 TL ve üzeri Alışverişlerinde %5 indirim! | E42: Uygulamayı indirerek kod almak için aşağıdaki butonu tıklayınız! | F42: Kampanya, Collection Point Zorlu mağazasında 31 Aralık 2023 tarihine kadar yapılacak 2.000 TL ve üzeri alışverişlerde geçerlidir.%5 indirim uygulanacaktır. Mücevher ürünleri kampanyaya dahil değildir. Zorlu World üyelerinin kampanyadan yararlanması için Zorlu World uygulamasından QR okumayı açması ve Collection Point mağazasında kasa yanındaki QR kodu okutması gerekmektedir. Zorlu World ve Collection Point kampanyada değişiklik yapma hakkını saklı tutar. Zorlu World, Zorlu Yapı Yatırım A.Ş. Müşteri Ödül Programı’dır. 31 Aralık 2023 tarihine kadar geçerlidir. | G42: 5% Off for 2.000 TL and more purchases at Collection Point! | H42: The app can be downloaded via button below in order to get the campaign code! | I42: The campaign is valid for 2.000 TL and more purchases to be made at Collection Point Zorlu store until 31 December 2023. 5% discount will be applied to the merchandises. Moser and George Jensen merchandises are not included to the campaign. Zorlu World members are required to open the QR reading from the Zorlu World application and scan the QR code next to the cash register at Collection Point store in order to benefit from the campaign. Zorlu World and Collection Point reserve the right to make changes to the campaign. Zorlu World, Zorlu Yapı Yatırım A.Ş. It is the Customer Reward Program. Valid until 31 December 2023 | J42: img/zw/icon/offer.png | K42: Collection-Point-750X600-a.jpg | L42: TRUE | M42: 10.05.2023 | N42: 31.12.2023 | O42: active

Sheet Changes
A1: ID | B1: Title | C1: Subtitle | D1: Location | E1: Floor | F1: Telephone | G1: Description | H1: Category | I1: Web | J1: Logo | K1: LogoName | L1: Cat_TR | M1: DATE | N1: STATUS | O1: UNTIL
A2: ID-246 | B2: Primestore | E2: -2 | F2: +902129123776 | G2: ayakkabı, çanta, bot, aksesuar, sandalet, shoes, bags, boots, accessories, sandals | H2: Ayakkabı & Çanta | I2: www.primestore.com.tr | J2: =CONCATENATE(Doors!$M$1,$K2) -> https://inmapper.com/zorlucenter/img/logo/PRIMESTORE.png | K2: PRIMESTORE.png | N2: CLOSED
A3: ID-250 | B3: Luzdemia | E3: -2 | F3: +902125148260 | G3: aksesuar, küpe, kolye, bileklik, yüzük, accessory, earring, necklace, wristband, ring | H3: Aksesuar & Mücevher | I3: www.luzdemia.com | J3: =CONCATENATE(Doors!$M$1,$K3) -> https://inmapper.com/zorlucenter/img/logo/LUZDEMIA.png | K3: LUZDEMIA.png | N3: CLOSED
A4: ID-127 | B4: Pizza Hut | E4: -1 | F4: +908502149034 | G4: yemek, lazanya, fast food, sarımsaklı ekmek, food, lasagna, fast food, garlic bread, pizza hat | H4: fastfood | I4: www.pizzahut.com.tr | J4: =CONCATENATE(Doors!$M$1,$K4) -> https://inmapper.com/zorlucenter/img/logo/PIZZAHUT.png | K4: PIZZAHUT.png | L4: Fast Food | N4: CLOSED
A5: valet-301 | B5: Bob {“id”:”valet”} ({“id”:”floorparking”}) | E5: -3 | F5: +908502590262 | G5: vale, park, araba, bilet, rezervasyon, valet, parking, car, ticket, booking | H5: services | L5: Hizmetler | N5: CLOSED
A6: ID070 | B6: Electrip Park Alanı | E6: 0 | F6: - | G6: araç, elektrik, şarj, vehicle, electric, charger | H6: services | L6: Hizmetler | N6: CLOSED
A7: ID061R | B7: Huqqa | E7: 0 | F7: - | G7: pizza, hamburger, et, salata, nargile, pizza, hamburger, meat, salad, hookah, hukka | H7: restaurant_cafe | L7: Restoran & Cafe | N7: CLOSED
A8: ID-124 | B8: MMY Tantuni | E8: -1 | F8: +902123431555 | G8: yemek, fast food, tantuni | H8: fastfood | I8: www.mmytantuni.com | J8: =CONCATENATE(Doors!$M$1,$K8) -> https://inmapper.com/zorlucenter/img/logo/MMYTANTUNİ.png | K8: MMYTANTUNİ.png | L8: Fast Food | N8: CLOSED
A9: ID055 | B9: La Vina | E9: 0 | F9: +902123536655 | G9: ispanyol, paella, tapas, gazpacho, içki, spanish, paella, tapas, gazpacho, drink | H9: restaurant_cafe | I9: www.lavinarestaurant.com | J9: =CONCATENATE(Doors!$M$1,$K9) -> https://inmapper.com/zorlucenter/img/logo/LAVINA.png | K9: LAVINA.png | L9: Restoran & Cafe | N9: CLOSED
A10: ID-126 | B10: Cold Stone | E10: -1 | F10: +905313687836 | G10: koldsıton, creamery, dondurma, ice cream | H10: restaurant_cafe | I10: www.coldstonecreamery.com.tr | J10: =CONCATENATE(Doors!$M$1,$K10) -> https://inmapper.com/zorlucenter/img/logo/COLDSTONE.png | K10: COLDSTONE.png | L10: Restoran & Cafe | N10: CLOSED
A11: ID119F | B11: MUSE FOR ALL | E11: 1 | F11: +902122250777 | H11: fashion | I11: www.museforall.com/tr | J11: =CONCATENATE(Doors!$M$1,$K11) -> https://inmapper.com/zorlucenter/img/logo/MUSEFORALL.png | K11: MUSEFORALL.png | L11: Giyim | M11: 01.02.2023 | N11: CLOSED
A12: ID001B | B12: Vakko Couture | E12: 0 | F12: +902127085036 | G12: erkek, kadın, giyim, moda, ayakkabı, man, woman, clothing, fashion, shoes, sen loren | H12: fashion | I12: www.vakko.com | J12: =CONCATENATE(Doors!$M$1,$K12) -> https://inmapper.com/zorlucenter/img/logo/VAKKOCOUTURE.png | K12: VAKKOCOUTURE.png | L12: Giyim | M12: 15.02.2023 | N12: CLOSED
A13: ID001B | B13: Fabiana Filippi | E13: 0 | F13: - | G13: erkek, kadın, giyim, moda, ayakkabı, man, woman, clothing, fashion, shoes, sen loren | H13: fashion | I13: www.fabianafilippi.com | J13: =CONCATENATE(Doors!$M$1,$K13) -> https://inmapper.com/zorlucenter/img/logo/FABIANAFILIPPI.png | K13: FABIANAFILIPPI.png | L13: Giyim | M13: 15.02.2023 | N13: OPENED
A14: ID119F | B14: Boho Loves Elif Mısırlı | E14: 1 | H14: fashion | I14: www.boholoves.com | J14: =CONCATENATE(Doors!$M$1,$K14) -> https://inmapper.com/zorlucenter/img/logo/BOHOLOVESELIFMISIRLI.png | K14: BOHOLOVESELIFMISIRLI.png | L14: Giyim | M14: 01.03.2023 | N14: OPENED
A15: ID075 | B15: Walkers Market | E15: 0 | F15: - | G15: alkol, içki, kokteyl, alcohol, drink, cocktail, viski, whisky | H15: restaurant_cafe | L15: Restoran & Cafe | N15: CLOSED
A16: ID126 | B16: Mariposa | E16: 1 | F16: +908505324386 | G16: çocuk, uyku, bebek, elbise, oyuncak, child, sleeping, baby, dress, toy | H16: restaurant_cafe | I16: www.funloft.com.tr | J16: =CONCATENATE(Doors!$M$1,$K16) -> https://inmapper.com/zorlucenter/img/logo/MARIPOSABURGER.png | K16: MARIPOSABURGER.png | L16: Restoran & Cafe | M16: 09.03.2023 | N16: CLOSED
A17: ID-315 | B17: Erkan Taş Podyum Terzi | E17: -3 | F17: +905458523899 | G17: dikiş, onarım, tadilat, küçültme, büyültme, sewing, repair, modification, reduction, magnification | H17: servicestores | J17: =CONCATENATE($M$1,$K17) -> DATEERKANTAS.png | K17: ERKANTAS.png | L17: Hizmet Mağazaları | M17: 27.04.2023 | N17: OPENED
A18: ID121A | B18: Vakko L'Atelier | E18: 1 | F18: +905494715909 | G18: çikolata, patisserie, dondurma, bistrot, chocolate, ice cream | H18: restaurant_cafe | I18: www.vakkolatelier.com | J18: =CONCATENATE($M$1,$K18) -> DATEVAKKOLATELIER.png | K18: VAKKOLATELIER.png | L18: Restoran & Cafe | M18: 27.04.2023 | N18: OPENED
A19: ID055 | B19: Gucci | E19: 0 | F19: +902123536533 | H19: fashion | I19: www.gucci.com | J19: =CONCATENATE(Doors!$M$1,$K19) -> https://inmapper.com/zorlucenter/img/logo/GUCCI.png | K19: GUCCI.png | L19: Giyim | M19: 05.05.2023 | N19: OPENED
A20: ID-314 | B20: Design Market | E20: -3 | F20: +902123536847 | G20: takı, tasarım, aksesuar, jewelry, design, accessories | H20: accessories_jewellery | I20: www.designmarket.com.tr | J20: =CONCATENATE($M$1,$K20) -> DATEDESIGNMARKET.png | K20: DESIGNMARKET.png | L20: Aksesuar & Mücevher | M20: 01.06.2023 | N20: CLOSED
A21: ID-137 | B21: Brooks Brothers | E21: -1 | F21: +902123536393 | G21: giyim, kadın, erkek, ayakkabı, moda, clothing, women, men, shoes, fashion, buruks bıradırs | H21: fashion | I21: www.brooksbrothers.com | J21: =CONCATENATE($M$1,$K21) -> DATEBROOKSBROTHERS.png | K21: BROOKSBROTHERS.png | L21: Giyim | M21: 15.06.2023 | N21: CLOSED
A22: ID008 | B22: Saint Laurent | E22: 0 | F22: +902123063390 | G22: erkek, kadın, giyim, moda, ayakkabı, man, woman, clothing, fashion, shoes, sen loren | H22: fashion | I22: www.ysl.com | J22: =CONCATENATE($M$1,$K22) -> DATESAINTLAURENT.png | K22: SAINTLAURENT.png | L22: Giyim | M22: 30.06.2023 | N22: CLOSED
A23: ID008 | B23: Celine | E23: 0 | H23: fashion | L23: Giyim | M23: 30.06.2023 | N23: SOON
A24: ID119F | B24: Boho Loves Elif Mısırlı | E24: 1 | H24: fashion | I24: www.boholoves.com | J24: =CONCATENATE(Doors!$M$1,$K24) -> https://inmapper.com/zorlucenter/img/logo/BOHOLOVESELIFMISIRLI.png | K24: BOHOLOVESELIFMISIRLI.png | L24: Giyim | M24: 11.07.2023 | N24: CLOSED
A25: ID119F | B25: Sagaza | E25: 1 | F25: - | H25: fashion | I25: https://sagaza.com/tr/ | J25: =CONCATENATE(Doors!$M$1,$K25) -> https://inmapper.com/zorlucenter/img/logo/SAGAZA.png | K25: SAGAZA.png | L25: Giyim | M25: 11.07.2023 | N25: OPENED
A26: ID-247 | B26: Tumi | E26: -2 | F26: +902123536676 | H26: shoes_bags | I26: www.tumi.com.tr | J26: =CONCATENATE($M$1,$K26) -> DATETUMI.png | K26: TUMI.png | L26: Ayakkabı & Çanta | M26: 13.07.2023 | N26: OPENED
A27: ID075 | B27: Loro Piana | E27: 0 | F27: +902123536743 | H27: fashion | I27: us.loropiana.com/en | J27: =CONCATENATE($M$1,$K27) -> DATELOROPIANA.png | K27: LOROPIANA.png | L27: Giyim | M27: 27.07.2023 | N27: OPENED
A28: ID-137 | B28: Edwards | E28: -1 | F28: +902123536393 | G28: giyim, kadın, erkek, ayakkabı, moda, clothing, women, men, shoes, fashion, edvırds | H28: fashion | I28: www.edwards.com.tr | J28: =CONCATENATE($M$1,$K28) -> DATEEDWARDS.png | K28: EDWARDS.png | L28: Giyim | M28: 04.08.2023 | N28: OPENED
A29: ID-308 | B29: Watch Doctor | E29: -3 | F29: +902123536949 | G29: saat, pil, kayış, kordon, kadran, watch, battery, strap, cord, dial, voç doktor | H29: servicestores | I29: www.watchdoctor.com.tr | J29: =CONCATENATE(Doors!$M$1,$K29) -> https://inmapper.com/zorlucenter/img/logo/WATCHDOCTOR.png | K29: WATCHDOCTOR.png | L29: Hizmet Mağazaları | M29: 08.08.2023 | N29: CLOSED
A30: ID-118A | B30: Döner Stop | E30: -1 | F30: +902123536622 | G30: fast food, patates, dürüm, sandviç, yemek, fast food, potato roll, sandwich, food, döner sıtop | H30: fastfood | I30: www.donerstop.com.tr | J30: =CONCATENATE(Doors!$M$1,$K30) -> https://inmapper.com/zorlucenter/img/logo/DÖNERSTOP.png | K30: DÖNERSTOP.png | L30: Fast Food | M30: 08.08.2023 | N30: CLOSED
A31: ID066 | B31: Poppin' Bubble Tea & Coffee | E31: 0 | F31: - | G31: Bubble Tea, Coffee, Tea, Mochi, Toppings | H31: restaurant_cafe | I31: www.poppinbubbletea.com | K31: POPPIN.png | L31: Restoran & Cafe | M31: 29.08.2023 | N31: OPENED | O31: N/A 31.12.2023
A32: ID076 | B32: Les Benjamins | E32: 0 | F32: +902123536875 | H32: fashion | I32: www.lesbenjamins.com | J32: =CONCATENATE(Doors!$M$1,$K32) -> https://inmapper.com/zorlucenter/img/logo/LESBENJAMINS.png | K32: LESBENJAMINS.png | L32: Giyim | M32: 09.09.2023 | N32: OPENED
A33: ID-118A | B33: Usta Dönerci | E33: -1 | F33: - | H33: fastfood | I33: www.ustadonerci.com | J33: =CONCATENATE(Doors!$M$1,$K33) -> https://inmapper.com/zorlucenter/img/logo/USTADONERCI.png | K33: USTADONERCI.png | L33: Fast Food | M33: 07.10.2023 | N33: OPENED
A34: ID-308 | B34: Usta Saat | E34: -3 | F34: - | G34: saat, pil, kayış, kordon, kadran, watch, battery, strap, cord, dial, tamir, repair | H34: servicestores | J34: =CONCATENATE(Doors!$M$1,$K34) -> https://inmapper.com/zorlucenter/img/logo/USTASAAT.png | K34: USTASAAT.png | L34: Hizmet Mağazaları | M34: 09.10.2023 | N34: OPENED
A35: ID119F | B35: Sagaza | E35: 1 | F35: - | H35: fashion | I35: www.sagaza.com/tr | J35: =CONCATENATE(Doors!$M$1,$K35) -> https://inmapper.com/zorlucenter/img/logo/SAGAZA.png | K35: SAGAZA.png | L35: Giyim | M35: 05.12.2023 | N35: CLOSED
A36: ID119F | B36: Wabi Sabi | E36: 1 | F36: - | H36: fashion | I36: www.thewabisabi.shop | J36: =CONCATENATE(Doors!$M$1,$K36) -> https://inmapper.com/zorlucenter/img/logo/WABISABI.png | K36: WABISABI.png | L36: Giyim | M36: 15.12.2023 | N36: OPENED | O36: 31.03.2024
A37: ID125 | B37: Yalçınlar | E37: 1 | F37: +902123536700 | G37: fotoğraf, makine, film, baskı, vesikalık, photography, machine, film, printing, mug shot | H37: servicestores | I37: www.fotomaks.com.tr | J37: =CONCATENATE($M$1,$K37) -> DATEYALÇINLAR.png | K37: YALÇINLAR.png | L37: Hizmet Mağazaları | M37: 15.12.2023 | N37: MOVED
A38: ID-316 | B38: Yalçınlar | E38: -3 | F38: +902123536700 | G38: fotoğraf, makine, film, baskı, vesikalık, photography, machine, film, printing, mug shot | H38: servicestores | I38: www.fotomaks.com.tr | J38: =CONCATENATE($M$1,$K38) -> DATEYALÇINLAR.png | K38: YALÇINLAR.png | L38: Hizmet Mağazaları | M38: 15.12.2023 | N38: OPENED
A39: ID-252 | B39: Godiva (Kiosk) | E39: -2 | F39: - | G39: çikolata, tatlı, ülker, hedite, trüf, chocolate, sweet, turkish, gift, truffle | H39: turkishdelight_confectionery | I39: www.godivatr.com | J39: =CONCATENATE($M$1,$K39) -> DATEGODIVA.png | K39: GODIVA.png | L39: Lokum & Şekerleme | M39: 31.12.2023 | N39: CLOSED
A40: ID122 | B40: Riceteria | E40: 1 | F40: +902123536061 | G40: kahve, fincan, hediye, tatlı, coffee, cup, gift, sweet | H40: home_decoration | I40: www.riceteriabyrice.com | J40: =CONCATENATE($M$1,$K40) -> DATERICETERIA.png | K40: RICETERIA.png | L40: Ev & Dekorasyon | M40: 03.01.2024 | N40: CLOSED
A41: ID-233 | B41: Saat & Saat | E41: -2 | F41: +902123536565 | G41: saat, kayış, aksesuar, klasik, spor, watch, strap, accessory, classic, sport | H41: accessories_jewellery | I41: www.saatvesaat.com.tr | J41: =CONCATENATE($M$1,$K41) -> DATESAAT&SAAT.png | K41: SAAT&SAAT.png | L41: Aksesuar & Mücevher | M41: 05.01.2024 | N41: RENOVATING
A42: ID025 | B42: Bonesserie İstanbul | E42: 0 | F42: +905336645787 | G42: bakery, hande önel | H42: restaurant_cafe | J42: =CONCATENATE($M$1,$K42) -> DATEBONESSERIEISTANBUL.png | K42: BONESSERIEISTANBUL.png | L42: Restoran & Cafe | M42: 06.01.2024 | N42: CLOSED
A43: ID-213 | B43: İpekyol | E43: -2 | F43: +902123536707 | G43: kadın, giyim, moda, aksesuar, ayakkabı, woman, clothing, fashion, accessory, shoe | H43: fashion | I43: www.ipekyol.com.tr | J43: =CONCATENATE($M$1,$K43) -> DATEİPEKYOL.png | K43: İPEKYOL.png | L43: Giyim | M43: 15.01.2024 | N43: RENOVATING | O43: 22.01.2024
A44: ID-213 | B44: İpekyol | E44: -2 | F44: +902123536707 | G44: kadın, giyim, moda, aksesuar, ayakkabı, woman, clothing, fashion, accessory, shoe | H44: fashion | I44: www.ipekyol.com.tr | J44: =CONCATENATE($M$1,$K44) -> DATEİPEKYOL.png | K44: İPEKYOL.png | L44: Giyim | M44: 15.01.2024 | N44: OPENED
A45: ID-233 | B45: Saat & Saat | E45: -2 | F45: +902123536565 | G45: saat, kayış, aksesuar, klasik, spor, watch, strap, accessory, classic, sport | H45: accessories_jewellery | I45: www.saatvesaat.com.tr | J45: =CONCATENATE($M$1,$K45) -> DATESAAT&SAAT.png | K45: SAAT&SAAT.png | L45: Aksesuar & Mücevher | M45: 31.01.2024 | N45: OPENED
A46: ID008 | B46: Celine | E46: 0 | F46: +902123063390 | G46: erkek, kadın, giyim, moda, ayakkabı, man, woman, clothing, fashion, shoes | H46: fashion | I46: www.celine.com | J46: =CONCATENATE($M$1,$K46) -> DATECELINE.png | K46: CELINE.png | L46: Giyim | M46: 03.02.2024 | N46: OPENED
A47: ID-147 | B47: Diesel | E47: -1 | F47: +902123536070 | G47: kadın, erkek, giyim, ayakkabı, mont, women, men, clothing, shoes, coats, dizel | H47: fashion | I47: www.diesel.com | J47: =CONCATENATE($M$1,$K47) -> DATEDIESEL.png | K47: DIESEL.png | L47: Giyim | M47: 18.02.2024 | N47: RENOVATING | O47: 09.04.2024 | P47: 17.03.2024
A48: ID101 | B48: Linens | E48: 1 | F48: +902123536312 | G48: perde, nevresim, örtü, kılıf, kumaş, curtain, duvet, cover, cover, fabric | H48: home_decoration | I48: www.linens.com.tr | J48: =CONCATENATE($M$1,$K48) -> DATELINENS.png | K48: LINENS.png | L48: Ev & Dekorasyon | M48: 27.02.2024 | N48: RENOVATING
A49: ID032 | B49: Tiffany & Co. | E49: 0 | F49: +902123536260 | G49: mücevher, pırlanta, yüzük, bileklik, kolye, jewel, diamond, ring, bracelet, necklace, tifani end ko | H49: accessories_jewellery | I49: www.tiffany.com | J49: =CONCATENATE($M$1,$K49) -> DATETIFFANY&CO.png | K49: TIFFANY&CO.png | L49: Aksesuar & Mücevher | M49: 01.03.2024 | N49: RENOVATING | O49: 11.03.2024
A50: ID101 | B50: Linens | E50: 1 | F50: +902123536312 | G50: perde, nevresim, örtü, kılıf, kumaş, curtain, duvet, cover, cover, fabric | H50: home_decoration | I50: www.linens.com.tr | J50: =CONCATENATE($M$1,$K50) -> DATELINENS.png | K50: LINENS.png | L50: Ev & Dekorasyon | M50: 02.03.2024 | N50: OPENED
A51: ID001 | B51: Vakkorama Cafe | E51: 0 | F51: +902129423326 | G51: kahve, tatlı, kek, içecek, pasta, coffee, dessert, cake, drink, muffin | H51: restaurant_cafe | I51: www.vakkorama.com.tr | J51: =CONCATENATE($M$1,$K51) -> DATEVAKKORAMACAFE.png | K51: VAKKORAMACAFE.png | L51: Restoran & Cafe | M51: 05.03.2024 | N51: CLOSED
A52: ID001 | B52: Sail Loft Vakkorama | E52: 0 | F52: +902129423326 | G52: kahve, tatlı, kek, içecek, pasta, coffee, dessert, cake, drink, muffin | H52: restaurant_cafe | I52: www.vakkorama.com.tr | J52: =CONCATENATE($M$1,$K52) -> DATEVAKKORAMACAFE.png | K52: VAKKORAMACAFE.png | L52: Restoran & Cafe | M52: 05.03.2024 | N52: OPENED
A53: ID114B | B53: Enplus | E53: 1 | F53: - | G53: enplas | H53: home_decoration | I53: www.enplus.com.tr | J53: =CONCATENATE($M$1,$K53) -> DATEVAKKORAMACAFE.png | K53: VAKKORAMACAFE.png | L53: Ev & Dekorasyon | M53: 12.09.2023 | N53: OPENED
A54: ID114C | B54: Coni & Co | E54: 1 | F54: - | G54: tavuk, chicken | H54: restaurant_cafe | J54: =CONCATENATE($M$1,$K54) -> DATEVAKKORAMACAFE.png | K54: VAKKORAMACAFE.png | L54: Restoran & Cafe | M54: 07.03.2024 | N54: OPENED
A55: ID-237 | B55: B&G Store | E55: -2 | F55: +902123536263 | G55: çocuk, bebek, giyim, kız, erkek, child, baby, clothing, girl, boy | H55: kids | I55: www.bgstoreonline.com | J55: =CONCATENATE($M$1,$K55) -> DATEB&GSTORE.png | K55: B&GSTORE.png | L55: Çocuk | M55: 10.03.2024 | N55: RENOVATING | O55: 15.03.2024
A56: ID032 | B56: Tiffany & Co. | E56: 0 | F56: +902123536260 | G56: mücevher, pırlanta, yüzük, bileklik, kolye, jewel, diamond, ring, bracelet, necklace, tifani end ko | H56: accessories_jewellery | I56: www.tiffany.com | J56: =CONCATENATE($M$1,$K56) -> DATETIFFANY&CO.png | K56: TIFFANY&CO.png | L56: Aksesuar & Mücevher | M56: 13.03.2024 | N56: OPENED
A57: ID061R | B57: Rocca | E57: 0 | F57: +902129240200 | H57: restaurant_cafe | L57: Restoran & Cafe | M57: 14.03.2024 | N57: CLOSED
A58: ID061R2 | B58: Sakhalin İstanbul | E58: 0 | F58: +905308118888 | G58: akdeniz, asya, suşi, mediterranean, asia, sushi | H58: restaurant_cafe | I58: www.sakhalin.rest/istanbul/tr | J58: =CONCATENATE($M$1,$K58) -> DATESAKHALINISTANBUL.png | K58: SAKHALINISTANBUL.png | L58: Restoran & Cafe | M58: 14.03.2024 | N58: OPENED
A59: ID-237 | B59: B&G Store | E59: -2 | F59: +902123536263 | G59: çocuk, bebek, giyim, kız, erkek, child, baby, clothing, girl, boy | H59: kids | I59: www.bgstoreonline.com | J59: =CONCATENATE($M$1,$K59) -> DATEB&GSTORE.png | K59: B&GSTORE.png | L59: Çocuk | M59: 15.03.2024 | N59: OPENED
A60: ID-254 | B60: KIKO Milano | E60: -2 | F60: +908508005456 | H60: cosmetics_health | I60: www.kikomilano.com.tr | J60: =CONCATENATE($M$1,$K60) -> DATEKIKOMILANO.png | K60: KIKOMILANO.png | L60: Kozmetik & Sağlık | M60: 29.03.2024 | N60: OPENED
A61: ID119F | B61: Wabi Sabi | E61: 1 | F61: +905324992939 | H61: fashion | I61: www.thewabisabi.shop | J61: =CONCATENATE(Doors!$M$1,$K61) -> https://inmapper.com/zorlucenter/img/logo/WABISABI.png | K61: WABISABI.png | L61: Giyim | M61: 31.03.2024 | N61: CLOSED
A62: ID119F | B62: Muse For All | E62: 1 | F62: +902122250777 | H62: fashion | I62: www.museforall.com/tr | J62: =CONCATENATE(Doors!$M$1,$K62) -> https://inmapper.com/zorlucenter/img/logo/MUSEFORALL.png | K62: MUSEFORALL.png | L62: Giyim | M62: 05.04.2024 | N62: SOON | O62: 15.04.2024
A63: ID101 | B63: Linens | E63: 1 | F63: +902123536312 | G63: perde, nevresim, örtü, kılıf, kumaş, curtain, duvet, cover, cover, fabric | H63: home_decoration | I63: www.linens.com.tr | J63: =CONCATENATE($M$1,$K63) -> DATELINENS.png | K63: LINENS.png | L63: Ev & Dekorasyon | M63: 02.04.2024 | N63: RENOVATING | O63: 06.04.2024
A64: ID-314 | B64: Eve | E64: -3 | F64: - | H64: cosmetics_health | I64: www.eveshop.com.tr | J64: =CONCATENATE($M$1,$K64) -> DATEEVE.png | K64: EVE.png | L64: Kozmetik & Sağlık | M64: 04.04.2024 | N64: OPENED
A65: ID101 | B65: Linens | E65: 1 | F65: +902123536312 | G65: perde, nevresim, örtü, kılıf, kumaş, curtain, duvet, cover, cover, fabric | H65: home_decoration | I65: www.linens.com.tr | J65: =CONCATENATE($M$1,$K65) -> DATELINENS.png | K65: LINENS.png | L65: Ev & Dekorasyon | M65: 06.04.2024 | N65: OPENED
A66: ID-147 | B66: Diesel | E66: -1 | F66: +902123536070 | G66: kadın, erkek, giyim, ayakkabı, mont, women, men, clothing, shoes, coats, dizel | H66: fashion | I66: www.diesel.com | J66: =CONCATENATE($M$1,$K66) -> DATEDIESEL.png | K66: DIESEL.png | L66: Giyim | M66: 09.04.2024 | N66: OPENED
A67: ID119F | B67: Muse For All | E67: 1 | F67: +902122250777 | H67: fashion | I67: www.museforall.com/tr | J67: =CONCATENATE(Doors!$M$1,$K67) -> https://inmapper.com/zorlucenter/img/logo/MUSEFORALL.png | K67: MUSEFORALL.png | L67: Giyim | M67: 15.04.2024 | N67: OPENED | O67: 31.08.2024
A68: ID025 | B68: Rey Organic | E68: 0 | F68: - | H68: restaurant_cafe | I68: www.reyorganic.com | J68: =CONCATENATE($M$1,$K68) -> DATEREYORGANIC.png | K68: REYORGANIC.png | L68: Restoran & Cafe | M68: 16.04.2024 | N68: SOON
A69: ID-229 | B69: US Polo Assn. | E69: -2 | F69: +902123536206 | G69: giyim, tshirt, jeans, ayakkabı, gömlek, clothing, tshirt, jeans, shoes, shirt, yu es polo asasin | H69: fashion | I69: www.uspoloassn.com | J69: =CONCATENATE($M$1,$K69) -> DATEU.S.POLO ASSN.png | K69: U.S.POLO ASSN.png | L69: Giyim | M69: 19.04.2024 | N69: RENOVATING
A70: ID075 | B70: Loro Piana | E70: 0 | F70: +902123536743 | H70: fashion | I70: us.loropiana.com/en | J70: =CONCATENATE($M$1,$K70) -> DATELOROPIANA.png | K70: LOROPIANA.png | L70: Giyim | M70: 06.05.2024 | N70: RENOVATING | O70: 17.05.2024
A71: ID-152 | B71: Lacoste | E71: -1 | F71: +902123536066 | G71: kadın, erkek, giyim, polo, tshirt, woman, man, clothing, polo, tshirt, lakost | H71: fashion | I71: www.lacoste.com | J71: =CONCATENATE($M$1,$K71) -> DATELACOSTE.png | K71: LACOSTE.png | L71: Giyim | M71: 12.05.2024 | N71: RENOVATING
A72: ID-152 | B72: Lacoste | E72: -1 | F72: +902123536066 | G72: kadın, erkek, giyim, polo, tshirt, woman, man, clothing, polo, tshirt, lakost | H72: fashion | I72: www.lacoste.com | J72: =CONCATENATE($M$1,$K72) -> DATELACOSTE.png | K72: LACOSTE.png | L72: Giyim | M72: 17.05.2024 | N72: OPENED
A73: ID075 | B73: Loro Piana | E73: 0 | F73: +902123536743 | H73: fashion | I73: us.loropiana.com/en | J73: =CONCATENATE($M$1,$K73) -> DATELOROPIANA.png | K73: LOROPIANA.png | L73: Giyim | M73: 23.05.2024 | N73: OPENED
A74: ID-141 | B74: Atasay | E74: -1 | F74: +902123536464 | G74: altın, gümüş, yüzük, kolye, pırlanta, gold, silver, ring, necklace, diamond | H74: accessories_jewellery | I74: www.atasay.com | J74: =CONCATENATE($M$1,$K74) -> DATEATASAY.png | K74: ATASAY.png | L74: Aksesuar & Mücevher | M74: 05.06.2024 | N74: RENOVATING
A75: ID025 | B75: Rey Organic | E75: 0 | F75: - | H75: restaurant_cafe | I75: www.reyorganic.com | J75: =CONCATENATE($M$1,$K75) -> DATEREYORGANIC.png | K75: REYORGANIC.png | L75: Restoran & Cafe | M75: 07.06.2024 | N75: OPENED
A76: ID-229 | B76: US Polo Assn. | E76: -2 | F76: +902123536206 | G76: giyim, tshirt, jeans, ayakkabı, gömlek, clothing, tshirt, jeans, shoes, shirt, yu es polo asasin | H76: fashion | I76: www.uspoloassn.com | J76: =CONCATENATE($M$1,$K76) -> DATEU.S.POLO ASSN.png | K76: U.S.POLO ASSN.png | L76: Giyim | M76: 10.06.2024 | N76: OPENED
A77: ID024 | B77: MAC/One | E77: 0 | F77: +902129701652-53 | G77: spor, üyelik, vücut geliştirme, bisiklet, koşu, sport, membership, bodybuilding, cycling, running | H77: fitness | I77: www.marsathletic.com | J77: =CONCATENATE($M$1,$K77) -> DATEMACMARSATHLETICCLUB.png | K77: MACMARSATHLETICCLUB.png | L77: Spor | M77: 24.06.2024 | N77: RENOVATING
A78: ID111 | B78: Casa | E78: 1 | F78: +902123536432-33 | G78: mobilya, kanepe, koltuk, yatak | H78: home_decoration | I78: www.casa.com.tr | J78: =CONCATENATE(Doors!$M$1,$K78) -> https://inmapper.com/zorlucenter/img/logo/CASA.png | K78: CASA.png | L78: Ev & Dekorasyon | M78: 26.06.2024 | N78: CLOSED
A79: ID-230 | B79: Massimo Dutti | E79: -2 | F79: +902123536948 | G79: giyim, takım, ayakkabı, aksesuar, elbise, clothing, suit, shoes, accessory, dress | H79: fashion | I79: www.massimodutti.com | J79: =CONCATENATE($M$1,$K79) -> DATEMASSIMODUTTI.png | K79: MASSIMODUTTI.png | L79: Giyim | M79: 30.06.2024 | N79: RENOVATING
A80: ID014 | B80: Günaydın Kasap & Steakhouse | E80: 0 | F80: +902123536250 | G80: et, ızgara, hamburger, salata, köfte, soup, food, meat, grilled, olive oil | H80: restaurant_cafe | I80: www.gunaydinet.com | J80: =CONCATENATE($M$1,$K80) -> DATEGÜNAYDINSTEAKHOUSE.png | K80: GÜNAYDINSTEAKHOUSE.png | L80: Restoran & Cafe | M80: 09.07.2024 | N80: RENOVATING
A81: ID-141 | B81: Atasay | E81: -1 | F81: +902123536464 | G81: altın, gümüş, yüzük, kolye, pırlanta, gold, silver, ring, necklace, diamond | H81: accessories_jewellery | I81: www.atasay.com | J81: =CONCATENATE($M$1,$K81) -> DATEATASAY.png | K81: ATASAY.png | L81: Aksesuar & Mücevher | M81: 15.07.2024 | N81: OPENED
A82: ID078 | B82: The Sundae Society | E82: 0 | F82: - | G82: dondurma, ice cream | H82: restaurant_cafe | J82: =CONCATENATE($M$1,$K82) -> DATETHESUNDAESOCIETY.png | K82: THESUNDAESOCIETY.png | L82: Restoran & Cafe | M82: 23.07.2024 | N82: OPENED
A83: ID122A | B83: Voi Coffee Company | E83: 1 | F83: - | G83: kahve, çay, pasta, kek, tatlı, coffee, tea, cake, muffin, dessert | H83: restaurant_cafe | I83: www.voi.com.tr | J83: =CONCATENATE($M$1,$K83) -> DATEVOICOFFEECOMPANY.png | K83: VOICOFFEECOMPANY.png | L83: Restoran & Cafe | M83: 12.08.2024 | N83: UPDATED-PHONE-NUMBER | O83: +902123536061
A84: ID016 | B84: SushiCo | E84: 0 | F84: +905309543168 | G84: suşi, makarna, erişte, tatlı, balık, sushi, pasta, noodles, sweet, fish, suşiko | H84: restaurant_cafe | I84: www.sushico.com.tr | J84: =CONCATENATE($M$1,$K84) -> DATESUSHICO.png | K84: SUSHICO.png | L84: Restoran & Cafe | M84: 27.08.2024 | N84: RENOVATING
A85: ID-135 | B85: Bobbi Brown | E85: -1 | F85: +902123536449 | G85: kozmetik, makyaj, bakım, kadın, cosmetics, makeup, care, women | H85: cosmetics_health | I85: www.bobbibrown.com.tr | J85: =CONCATENATE($M$1,$K85) -> DATEBOBBIBROWN.png | K85: BOBBIBROWN.png | L85: Kozmetik & Sağlık | M85: 28.08.2024 | N85: UPDATED-PHONE-NUMBER | O85: +902123536448
A86: ID125 | B86: Zwilling | E86: 1 | M86: 28.08.2024 | N86: SOON
A87: ID016 | B87: SushiCo | E87: 0 | F87: +905309543168 | G87: suşi, makarna, erişte, tatlı, balık, sushi, pasta, noodles, sweet, fish, suşiko | H87: restaurant_cafe | I87: www.sushico.com.tr | J87: =CONCATENATE($M$1,$K87) -> DATESUSHICO.png | K87: SUSHICO.png | L87: Restoran & Cafe | M87: 28.08.2024 | N87: OPENED-AFTER-RENOVATION
A88: ID119F | B88: Muse For All | E88: 1 | H88: fashion | I88: www.museforall.com/tr | J88: =CONCATENATE(Doors!$M$1,$K88) -> https://inmapper.com/zorlucenter/img/logo/MUSEFORALL.png | K88: MUSEFORALL.png | L88: Giyim | M88: 28.08.2024 | N88: CLOSED
A89: ID-132 | B89: Tavuk Dünyası | E89: -1 | F89: 4448850 | H89: fastfood | I89: www.tavukdunyasi.com | L89: Fast Food | M89: 12.09.2024 | N89: OPENED
A90: ID114C | B90: Coni & Co | E90: 1 | F90: +905336911987 | G90: tavuk, chicken | H90: restaurant_cafe | J90: =CONCATENATE($M$1,$K90) -> DATECONICO.png | K90: CONICO.png | L90: Restoran & Cafe | M90: 16.09.2024 | N90: UPDATED-PHONE-NUMBER | O90: +905496128987
A91: ID024 | B91: MAC/One | C91: ({\"id\":\"renovating\"}) | E91: 0 | F91: +902129701652-53 | G91: spor, üyelik, vücut geliştirme, bisiklet, koşu, sport, membership, bodybuilding, cycling, running | H91: fitness | I91: www.marsathletic.com | J91: =CONCATENATE($M$1,$K91) -> DATEMACMARSATHLETICCLUB.png | K91: MACMARSATHLETICCLUB.png | L91: Spor | M91: 16.09.2024 | N91: OPENED-AFTER-RENOVATION
A92: ID-230 | B92: Massimo Dutti | E92: -2 | F92: +902123536948 | G92: giyim, takım, ayakkabı, aksesuar, elbise, clothing, suit, shoes, accessory, dress | H92: fashion | I92: www.massimodutti.com | J92: =CONCATENATE($M$1,$K92) -> DATEMASSIMODUTTI.png | K92: MASSIMODUTTI.png | L92: Giyim | M92: 19.09.2024 | N92: OPENING-AFTER-RENOVATION
A93: ID119F | B93: A Simple Way | E93: 1 | F93: +905318667265 | G93: Giyim, Elbise, Etek, T-Shirt, Triko, Pantolon, Sweatshirt, Dress, Skirt, Knitwear, Trousers | H93: fashion | I93: www.asimpleway.co | J93: =CONCATENATE(Doors!$M$1,$K93) -> https://inmapper.com/zorlucenter/img/logo/ASIMPLEWAY.png | K93: ASIMPLEWAY.png | L93: Giyim | M93: 17.09.2024 | N93: OPENED
A94: ID-173 | B94: Walkers Bar | E94: -1 | F94: +905304190130 | G94: bar, alkol, kokteyl, içki, bar, alcohol, cocktail, drink | H94: restaurant_cafe | I94: www.walkersbar.com | L94: Restoran & Cafe | M94: 23.09.2024 | N94: OPENED
A95: lobyy002 | B95: ABS Gayrimenkul | E95: 0 | F95: - | G95: TB Lobi | H95: offices | L95: Ofisler | M95: 24.09.2024 | N95: CLOSED
A96: lobyy002 | B96: Özkancalar Ltd. Şti. | E96: 0 | F96: - | G96: TB Lobi | H96: offices | L96: Ofisler | M96: 24.09.2024 | N96: CLOSED
A97: lobyy-101 | B97: Heinemann Africa GmbH | E97: -1 | F97: - | G97: TD Lobi | H97: offices | L97: Ofisler | M97: 24.09.2024 | N97: OPENED
A98: lobyy001 | B98: İnterra Kapital | E98: 0 | F98: - | G98: TA Lobi | H98: offices | L98: Ofisler | M98: 24.09.2024 | N98: OPENED
A99: lobyy003 | B99: Blockville | E99: 0 | F99: - | G99: Ofis AVM Lobi | H99: offices | L99: Ofisler | M99: 25.09.2024 | N99: CLOSED
A100: ID-124 | B100: Dönerci Kadir Usta | E100: -1 | F100: - | G100: döner | H100: fastfood | I100: www.donercikadirusta.com | L100: Fast Food | M100: 25.09.2024 | N100: SOON
...

Sheet Rooms
A1: ID | B1: Title | C1: Subtitle | D1: Location | E1: Floor | F1: Category | G1: Phone | H1: Description
A2: carpark-301 | B2: {“id”:”carpark”} | E2: -3 | F2: other | G2: - | H2: otopark, araç, otomobil, motosiklet, manevra, parking, vehicle, automobile, motorcycle, maneuver
A3: carpark-301 | B3: DRN Oto Yıkama | C3: {“id”:”floorparking”} | E3: -3 | F3: other | G3: +905313051112 | H3: otomobil, yıkama, pasta, cila, temizlik, automobile, washing, cake, lacquer, cleaning
A4: entrance-301 | B4: {“id”:”entrance”} {“id”:”floormetro”} | E4: -3 | F4: other | G4: - | H4: giriş, çıkış, kapı, bekleme, güvenlik, entrance, exit, door, waiting, security
A5: entrance-302 | B5: {“id”:”entrance”} Zincirlikuyu | E5: -3 | F5: other | G5: - | H5: giriş, çıkış, kapı, bekleme, güvenlik, entrance, exit, door, waiting, security
A6: entrance-303 | B6: {“id”:”entrance”} {“id”:”floormetro”} | E6: -3 | F6: other | G6: - | H6: giriş, çıkış, kapı, bekleme, güvenlik, entrance, exit, door, waiting, security
A7: entrance-304 | B7: {“id”:”entrance”} Levazım | E7: -3 | F7: other | G7: - | H7: giriş, çıkış, kapı, bekleme, güvenlik, entrance, exit, door, waiting, security
A8: entrance-305 | B8: {“id”:”entrance”} {“id”:”floorparking”} | E8: -3 | F8: other | G8: - | H8: giriş, çıkış, kapı, bekleme, güvenlik, entrance, exit, door, waiting, security
A9: entrance-306 | B9: {“id”:”entrance”} Eataly | E9: -3 | F9: other | G9: - | H9: giriş, çıkış, kapı, bekleme, güvenlik, entrance, exit, door, waiting, security
A10: ID-301 | B10: Etstur | E10: -3 | F10: other | G10: +902122820808-07 | H10: tatil, deniz, bayram, otel, fırsat, holiday, sea, holidays, hotel, occasion
A11: ID-302 | B11: Levent Lostra | E11: -3 | F11: other | G11: +902123536303 | H11: ayakkabı, tamir, boya, bakım, cüzdan, shoe, repair, paint, maintenance, wallet
A12: ID-303 | B12: Dry Corner | E12: -3 | F12: other | G12: +902123536337 | H12: kuru temizleme, ütü, gömlek, ceket, organik, dry cleaning, ironing, shirt, jacket, organic, dıray kornır
A13: ID-304 | B13: Z Terzi | E13: -3 | F13: other | G13: +902123536986 | H13: dikiş, onarım, tadilat, küçültme, büyültme, sewing, repair, modification, reduction, magnification
A14: ID-306 | B14: Rossmann | E14: -3 | F14: shop | G14: +902123536933 | H14: kozmetik, bakım, temizlik, makyaj, aksesuar, cosmetic, care, cleaning, makeup, accessory, rosman
A15: ID-308 | B15: Watch Doctor | E15: -3 | F15: other | G15: +902123536949 | H15: saat, pil, kayış, kordon, kadran, clock, battery, strap, cord, dial, voç doktor
... A70: ID-245 | B70: Touche | E70: -2 | F70: other | G70: +902129240128 | H70: kulüp, performans, etkinlik, club, performance, event, psm
A71: ID-245 | B71: Zorlu PSM | C71: {“id”:”floormetro”} | E71: -2 | F71: other | G71: +908502226776 | H71: etkinlik, gösteri, tiyatro, konser, bilet, activity, show, theater, concert, ticket
A72: ID-249 | B72: Ametist | E72: -2 | F72: shop | G72: +902123536174 | H72: aksesuar, küpe, kolye, bileklik, yüzük, accessory, earring, necklace, wristband, ring
A73: ID-250 | B73: Lamy | E73: -2 | F73: shop | G73: +902122586715 | H73: lamy, kalem, dolma kalem, tükenmez kalem, versatil kalem, uçlu kalem, roller kalem, alman, lamyshop
A74: ID-251 | B74: Godiva (Kiosk) | E74: -2 | F74: food | G74: - | H74: çikolata, tatlı, ülker, hedite, trüf, chocolate, sweet, turkish, gift, truffle
A75: ID-252 | B75: Dyson | E75: -2 | F75: shop | G75: +905394701299 | H75: süpürge, vakum, toz, vacuum cleaner, vacuum, dust, kablosuz , wireless
A76: ID-253 | B76: Maison Pereja | E76: -2 | F76: shop | G76: - | H76: pereja,kolonya,parfüm,mum,oda parfümü,diffuser, çubuklu oda kokusu, lüks koku
A77: infirmaryEN-201 | B77: {“id”:”infirmary”} | E77: -2 | F77: other | G77: - | H77: eczane, ilaç, reçete, doktor, tedavi, pharmacy, medicine, prescription, doctor, treatment
A78: infirmaryTR-201 | B78: {“id”:”infirmary”} | E78: -2 | F78: other | G78: - | H78: eczane, ilaç, reçete, doktor, tedavi, pharmacy, medicine, prescription, doctor, treatment
A79: info-201 | B79: {“id”:”infodesk”} | E79: -2 | F79: other | G79: +902129240124 | H79: bilgi, danışma, soru, telefon, duyuru, information, consultation, question, phone, announcement
A80: wc-201 | B80: {“id”:”wc”} | E80: -2 | F80: wc | G80: - | H80: tuvalet, lavabo, sabun, mendil, su, toilet, sink, soap, handkerchief, water
A81: wc-202 | B81: {“id”:”wc”} | E81: -2 | F81: wc | G81: - | H81: tuvalet, lavabo, sabun, mendil, su, toilet, sink, soap, handkerchief, water
A82: baby-101 | B82: {“id”:”baby”} | E82: -1 | F82: other | G82: - | H82: bebek, oda, bakım, emzik, meme, baby, room, care, pacifier, breast
A83: baby-102 | B83: {“id”:”baby”} | E83: -1 | F83: other | G83: - | H83: bebek, oda, bakım, emzik, meme, baby, room, care, pacifier, breast
... A108: ID-125 | B108: Et İşleri | E108: -1 | F108: food | G108: - | H108: yemek, ızgara, et, food, grill, meat
A109: ID-126 | B109: Cold Stone Creamery ({"id":"soon"}) | E109: -1 | F109: food | G109: -
A110: ID-127 | B110: Pizza Hut | E110: -1 | F110: food | G110: +908502149034 | H110: yemek, lazanya, fast food, sarımsaklı ekmek, food, lasagna, fast food, garlic bread, pizza hat
A111: ID-128 | B111: Carl's Jr. | E111: -1 | F111: food | G111: +902123536367 | H111: hamburger, patates, fast food, yemek, et, hamburger, potato, fast food, food, meat, karls jünyır
A112: ID-129 | B112: KFC | E112: -1 | F112: food | G112: +905334898893 | H112: tavuk, patates, fast food, yemek, kova, chicken, potato, fast food, food, bucket, keyefsi
A113: ID-130 | B113: Tahin | E113: -1 | F113: food | G113: +902129997078 | H113: yemek, humus, falafel, lübnan, food, humus, falafel, lebanese, ızgara, grill
A114: ID-131 | B114: McDonald's | E114: -1 | F114: food | G114: +905337691842 | H114: hamburger, patates, fast food, yemek, big mac, hamburger, potato, fast food, food, big mac, mekdanılds
A115: ID-133 | B115: Sosa | E115: -1 | F115: food | G115: +902123536280 | H115: yemek, ızgara, salata, makarna, et, food, grilled, salad, pasta, meat
A116: ID-134 | B116: Green Salads | E116: -1 | F116: food | G116: +902123536166 | H116: yemek, ızgara, salata, tavuk, makarna, food, grilled, salad, chicken, pasta, gırin salats
A117: ID-135 | B117: Bobbi Brown | E117: -1 | F117: shop | G117: +902123536449 | H117: kozmetik, makyaj, bakım, kadın, cosmetics, makeup, care, women
A118: ID-135A | B118: Pandora | E118: -1 | F118: shop | G118: +902123536621 | H118: takı, mücevher, pırlanta, yüzük, kolye, jewelry, jewel, diamond, ring, necklace
A119: ID-136 | B119: Network | E119: -1 | F119: shop | G119: +902123536079 | H119: giyim, kadın, erkek, ayakkabı, moda, clothing, women, men, shoes, fashion, netvörk
A120: ID-137 | B120: Brooks Brothers | E120: -1 | F120: shop | G120: +902123536393 | H120: giyim, kadın, erkek, ayakkabı, moda, clothing, women, men, shoes, fashion, buruks bıradırs
A121: ID-138 | B121: Tommy Hilfiger | E121: -1 | F121: shop | G121: +902123536085 | H121: giyim, kadın, erkek, ayakkabı, moda, clothing, women, men, shoes, fashion, tomi hilfigır
A122: ID-139 | B122: Beymen | D122: {“id”:”ID-138”} | E122: -1 | F122: shop | G122: +902123063300 | H122: giyim, kadın, erkek, ayakkabı, moda, clothing, women, men, shoes, fashion
A123: ID-140 | B123: Twinset Milano | E123: -1 | F123: shop | G123: +902124038865 | H123: kadın, giyim, çanta, ayakkabı, tasarım, woman, clothing, bag, shoes, design
A124: ID-140A | B124: NU | E124: -1 | F124: shop | G124: +902123536143 | H124: kadın, giyim, çanta, ayakkabı, tasarım, woman, clothing, bag, shoes, design
A125: ID-140B | B125: Cup of Joy | E125: -1 | F125: food | G125: +902123536413 | H125: kahve, tatlı, kek, pasta, içecek, coffee, sweet, cake, cake, drink, kap of coy
A126: ID-141 | B126: Atasay | E126: -1 | F126: shop | G126: +902123536464 | H126: altın, gümüş, yüzük, kolye, pırlanta, gold, silver, ring, necklace, diamond
A127: ID-142 | B127: Pinko | E127: -1 | F127: shop | G127: +902123536045 | H127: kadın, giyim, çanta, ayakkabı, tasarım, woman, clothing, bag, shoes, design
A128: ID-143 | B128: Machka | E128: -1 | F128: shop | G128: +902123536869 | H128: kadın, giyim, çanta, moda, aksesuar, woman, clothing, bag, fashion, accessory, maçka
A129: ID-144 | B129: Ramsey | E129: -1 | F129: shop | G129: +902123536666 | H129: erkek, giyim, takım, gömlek, ayakkabı, erkek, giyim, takım, gömlek, ayakkabı
A130: ID-145 | B130: Calvin Klein Jeans | E130: -1 | F130: shop | G130: +902123536973 | H130: kadın, erkek, giyim, ayakkabı, mont, women, men, clothing, shoes, coats, kalvin kılayn
A131: ID-146 | B131: Vario | E131: -1 | F131: shop | G131: +905438197043 | H131: ayakkabı, topuklu, çizme, bot, sandalet, shoes, heels, boots, boots, sandals, varyo
A132: ID-147 | B132: Diesel | E132: -1 | F132: shop | G132: +902123536070 | H132: kadın, erkek, giyim, ayakkabı, mont, women, men, clothing, shoes, coats, dizel
A133: ID-148 | B133: Mocassini | E133: -1 | F133: shop | G133: +902127090909 | H133: ayakkabı, deri, erkek, kadın, mont, shoes, leather, men, women, coats, mokassini
A134: ID-149 | B134: Beymen Club | E134: -1 | F134: shop | G134: +902123063386 | H134: kadın, erkek, giyim, ayakkabı, aksesuar, women, men, clothing, shoes, accessories, beymen kılap
... A152: ID-166 | B152: Passo Bilet Gişesi | E152: -1 | F152: other | G152: +902129240110 | H152: etkinlik, gösteri, tiyatro, konser, bilet, activity, show, theater, concert, ticket
A153: ID-166 | B153: Zorlu PSM | C153: {“id”:”floorbosphorus”} | E153: -1 | F153: other | G153: +908502226776 | H153: etkinlik, gösteri, tiyatro, konser, bilet, activity, show, theater, concert, ticket
A154: ID-170 | B154: Pembecida | E154: -1 | F154: shop | G154: +908505200511 | H154: kırtasiye, hobi, parti, ev, yaşam, stationery, hobby, party, home, life, pembesida
A155: info-101 | B155: {“id”:”infodesk”} | E155: -1 | F155: other | G155: +902129240124 | H155: bilgi, danışma, soru, telefon, duyuru, information, consultation, question, phone, announcement
A156: pharmacyEN-101 | B156: {“id”:”pharmacy”} Zorlu Center | E156: -1 | F156: other | G156: +902123536333 | H156: ilaç, hasta, bakım, reçete, nöbetçi, drug, patient, care, prescription, duty
A157: pharmacyTR-101 | B157: {“id”:”pharmacy”} Zorlu Center | E157: -1 | F157: other | G157: +902123536333 | H157: ilaç, hasta, bakım, reçete, nöbetçi, drug, patient, care, prescription, duty
A158: taxfree-101 | B158: Tax Free Zone ({“id”:”infodesk”} {“id”:”floorbosphorus”}) | E158: -1 | F158: other | G158: +902129240100 | H158: vergi, iade, fatura, fiş, form, tax, refund, invoice, receipt, form
A159: taxfree-102 | B159: Global Blue (Beymen) | E159: -1 | F159: other | G159: +902129240100 | H159: vergi, iade, fatura, fiş, form, tax, refund, invoice, receipt, form
A160: taxi-101 | B160: {“id”:”taxi”} | E160: -1 | F160: other | G160: +902125580606 | H160: araç, taksi, yolculuk, ödeme, transfer, vehicle, taxi, journey, payment, transfer
A161: valet-101 | B161: Bob {“id”:”valet”} (Levazım/Beymen) | E161: -1 | F161: other | G161: +908502590262 | H161: vale, park, araba, bilet, rezervasyon, valet, parking, car, ticket, booking
A162: wc-101 | B162: {“id”:”wc”} | E162: -1 | F162: wc | G162: - | H162: tuvalet, lavabo, sabun, mendil, su, toilet, sink, soap, handkerchief, water
A163: wc-102 | B163: {“id”:”wc”} | E163: -1 | F163: wc | G163: - | H163: tuvalet, lavabo, sabun, mendil, su, toilet, sink, soap, handkerchief, water
A164: atm001 | B164: {“id”:”atm”} | E164: 0 | F164: atm | G164: - | H164: para, çekme, yatırma, nakit, kart, money, withdrawal, deposit, cash, card
A165: atm001 | B165: Akbank | C165: ({“id”:”atm”}) | E165: 0 | F165: atm | G165: - | H165: para, çekme, yatırma, nakit, kart, money, withdrawal, deposit, cash, card
A166: atm001 | B166: DenizBank | C166: ({“id”:”atm”}) | E166: 0 | F166: atm | G166: - | H166: para, çekme, yatırma, nakit, kart, money, withdrawal, deposit, cash, card
A167: atm001 | B167: Halkbank | C167: ({“id”:”atm”}) | E167: 0 | F167: atm | G167: - | H167: para, çekme, yatırma, nakit, kart, money, withdrawal, deposit, cash, card
A168: atm001 | B168: HSBC | C168: ({“id”:”atm”}) | E168: 0 | F168: atm | G168: - | H168: para, çekme, yatırma, nakit, kart, money, withdrawal, deposit, cash, card
A169: atm001 | B169: QNB Finansbank | C169: ({“id”:”atm”}) | E169: 0 | F169: atm | G169: - | H169: para, çekme, yatırma, nakit, kart, money, withdrawal, deposit, cash, card
A170: atm001 | B170: VakıfBank | C170: ({“id”:”atm”}) | E170: 0 | F170: atm | G170: - | H170: para, çekme, yatırma, nakit, kart, money, withdrawal, deposit, cash, card
A171: atm001 | B171: Ziraat Bankası | C171: ({“id”:”atm”}) | E171: 0 | F171: atm | G171: - | H171: para, çekme, yatırma, nakit, kart, money, withdrawal, deposit, cash, card
A172: atm002 | B172: {“id”:”atm”} | E172: 0 | F172: atm | G172: - | H172: para, çekme, yatırma, nakit, kart, money, withdrawal, deposit, cash, card
A173: atm002 | B173: Garanti Bankası | C173: ({“id”:”atm”}) | E173: 0 | F173: atm | G173: - | H173: para, çekme, yatırma, nakit, kart, money, withdrawal, deposit, cash, card
A174: atm002 | B174: Türkiye İş Bankası | C174: ({“id”:”atm”}) | E174: 0 | F174: atm | G174: - | H174: para, çekme, yatırma, nakit, kart, money, withdrawal, deposit, cash, card
A175: atm002 | B175: Yapı Kredi | C175: ({“id”:”atm”}) | E175: 0 | F175: atm | G175: - | H175: para, çekme, yatırma, nakit, kart, money, withdrawal, deposit, cash, card
A176: baby001 | B176: {“id”:”baby”} | E176: 0 | F176: other | G176: - | H176: bebek, oda, bakım, emzik, meme, baby, room, care, pacifier, breast
A177: entrance001 | B177: {“id”:”entrance”} Zincirlikuyu | E177: 0 | F177: other | G177: - | H177: giriş, çıkış, kapı, bekleme, güvenlik, entrance, exit, door, waiting, security
A178: entrance002 | B178: {“id”:”entrance”} Levazım | E178: 0 | F178: other | G178: - | H178: giriş, çıkış, kapı, bekleme, güvenlik, entrance, exit, door, waiting, security
A179: entrance003 | B179: {“id”:”entrance”} Ulus | E179: 0 | F179: other | G179: - | H179: giriş, çıkış, kapı, bekleme, güvenlik, entrance, exit, door, waiting, security
A180: ID001 | B180: Vakkorama Cafe | E180: 0 | F180: food | G180: +902129423326 | H180: kahve, tatlı, kek, içecek, pasta, coffee, dessert, cake, drink, muffin
A181: ID001A | B181: Vakkorama | E181: 0 | F181: shop | G181: +902129422639 | H181: aksesuar, hediyelik, giyim, moda, ayakkabı, accessory, gift, clothing, fashion, shoes
A182: ID001B | B182: Vakko Couture | E182: 0 | F182: shop | G182: +902127085036 | H182: erkek, kadın, giyim, moda, ayakkabı, man, woman, clothing, fashion, shoes, sen loren
A183: ID002 | B183: Golden Goose | E183: 0 | F183: shop | G183: +902123536806 | H183: erkek, kadın, giyim, moda, ayakkabı, man, woman, clothing, fashion, shoes
A184: ID003 | B184: Welldone | E184: 0 | F184: food | G184: +902123536656 | H184: yemek, hamburger, makarna, et, salata, food, hamburger, pasta, meat, salad, veldan
A185: ID004 | B185: Crossing | E185: 0 | F185: food | G185: +905372767464 | H185: yemek, kahve, pasta, içecek, kek, food, coffee, cake, drink, muffin, krossing
A186: ID005 | B186: Vakko | E186: 0 | F186: shop | G186: +902127083333 | H186: giyim, moda, erkek, kadın, ayakkabı, clothing, fashion, men, women, shoes
A187: ID006 | B187: Tod's | E187: 0 | F187: shop | G187: +902123063388
A188: ID007 | B188: Happy Moon's | E188: 0 | F188: food | G188: +902123536308 | H188: yemek, hamburger, makarna, et, salata, food, hamburger, pasta, meat, salad, hepi muns
A189: ID008 | B189: Saint Laurent | E189: 0 | F189: shop | G189: +902123063390 | H189: erkek, kadın, giyim, moda, ayakkabı, man, woman, clothing, fashion, shoes, sen loren
A190: ID009 | B190: Alexander McQueen | E190: 0 | F190: shop | G190: +902123063396 | H190: erkek, kadın, giyim, moda, ayakkabı, man, woman, clothing, fashion, shoes, sen loren
A191: ID010 | B191: Rolex | E191: 0 | F191: shop | G191: +902123536898 | H191: saat, aksesuar, kayış,watch, accessory, strap
A192: ID011 | B192: Valentino | E192: 0 | F192: shop | G192: +902123063392 | H192: kadın, erkek, ayakkabı, çanta, giyim, women, men, shoes, bag, clothing
A193: ID012 | B193: Big Chefs | E193: 0 | F193: food | G193: +902123536384 | H193: burger, salata, sandviç, et, makarna, tatlı
A194: ID013 | B194: Tommi Brasserie | E194: 0 | F194: food | G194: +902123536310-11
A195: ID014 | B195: Günaydın Kasap&Steakhouse | E195: 0 | F195: food | G195: +902123536250 | H195: et, ızgara, hamburger, salata, köfte, soup, food, meat, grilled, olive oil
...

Sheet Portals
A1: ID | B1: Floor | C1: Status
A2: Elev.2.-2 | B2: -3 | C2: On
A3: Elev.3.-2 | B3: -3 | C3: On
A4: Elev.4.-1 | B4: -3 | C4: On
A5: Elev.5.0 | B5: -3 | C5: On
A6: Elev.8.0 | B6: -3 | C6: On
A7: Stairs.10.-2 | B7: -3 | C7: On
A8: Stairs.11.-2 | B8: -3 | C8: On
A9: Stairs.8.0 | B9: -3 | C9: On
A10: Stairs.9.-2 | B10: -3 | C10: On
A11: Elev.2.-1 | B11: -2 | C11: On
A12: Elev.2.-3 | B12: -2 | C12: On
A13: Elev.3.-1 | B13: -2 | C13: On
... A61: Stairs.9.0 | B61: 1 | C61: On

Sheet Info
A1: Angle | B1: 330
A2: W1 | B2: 0
A3: H1 | B3: 0
A4: W2 | B4: 655
A5: H2 | B5: 528
A6: Lat1 | B6: 41.067832
A7: Long1 | B7: 29.018151
A8: Lat2 | B8: 41.065531
A9: Long2 | B9: 29.014361
A10: Wground | B10: =2*6371000*ASIN(SQRT((SIN((B6*(3.14159/180)-B6*(3.14159/180))/2))^2+COS(B6*(3.14159/180))*COS(B6*(3.14159/180))*SIN(((B9*(3.14159/180)-B7*(3.14159/180))/2))^2)) -> 317.72868
A11: Hground | B11: =2*6371000*ASIN(SQRT((SIN((B8*(3.14159/180)-B6*(3.14159/180))/2))^2+COS(B8*(3.14159/180))*COS(B6*(3.14159/180))*SIN(((B7*(3.14159/180)-B7*(3.14159/180))/2))^2)) -> 255.85931
A12: Dground | B12: =2*6371000*ASIN(SQRT((SIN((B8*(3.14159/180)-B6*(3.14159/180))/2))^2+COS(B8*(3.14159/180))*COS(B6*(3.14159/180))*SIN(((B9*(3.14159/180)-B7*(3.14159/180))/2))^2)) -> 407.94489
A13: Dmap | B13: =SQRT((B2-B4)^2+(B3-B5)^2)*0.0002645833 -> 0.2225976
A15: W/H | B15: =B4/B5 -> 1.2405303
A16: Wground/Hground | B16: =B10/B11 -> 1.2418101
A18: var map center | B18: ="["&(B6+B8)/2&", "&(B7+B9)/2&"]" -> [41.0666815, 29.016256]
A19: var bounds | B19: ="["&B6&", "&B7&"]"&", "&"["&B8&", "&B9&"]" -> [41.067832, 29.018151], [41.065531, 29.014361]
A20: var maxBounds | B20: ="["&B6+0.003&", "&B7+0.003&"]"&", "&"["&B8-0.003&", "&B9-0.003&"]" -> [41.070832, 29.021151], [41.062531, 29.011361]
A21: L.inmapperOverlay scale | B21: =B13/B12 -> 0.00054565604

Sheet Kiosk
A1: ID | B1: IP | C1: URL | D1: Konum | E1: Kat | F1: Tip | G1: Yorum | H1: Liste | I1: Kod | J1: Yön | K1: Boyut | M1: Notlar
A2: K-301 | B2: 192.168.187.51 | D2: Güney otopark | F2: Yatay | H2: 1 | I2: wh | J2: Batı (+30 saat yönü) | K2: 692x490 | M2: Kaldırılmış.
A3: K-302 | B3: 192.168.187.52 | C3: =CONCATENATE($N$3,I3,$O$3,A3) -> http://192.168.187.30:8000/eh.html?mode=kiosk&from=K-302 | D3: Balonika önü | E3: P1 Otopark | F3: Yatay | G3: Kalktı mı? | H3: 2 | I3: eh | J3: Doğu (+30 saat yönü) | K3: 692x490 | L3: X-WW | N3: http://192.168.187.30:8000/ | O3: .html?mode=kiosk&from=
A4: K-203 | B4: 192.168.187.53 | C4: =CONCATENATE($N$3,I4,$O$3,A4) -> http://192.168.187.30:8000/sh.html?mode=kiosk&from=K-203 | D4: House of Design yanı, Metro girişi | E4: -2 Metro | F4: Yatay | G4: ripple, RESTART_CHECK | H4: 3 | I4: sh | J4: Güney (+30 saat yönü) | K4: 490x692
A5: K-204 | B5: 192.168.187.54 | C5: =CONCATENATE($N$3,I5,$O$3,A5) -> http://192.168.187.30:8000/sh.html?mode=kiosk&from=K-204 | D5: Tartine et Chocolat önü | F5: Yatay | H5: 4 | I5: sh | J5: Güney (+30 saat yönü) | K5: 490x692 | M5: Kaldırılmış.
A6: K-207 | B6: 192.168.187.55 | C6: =CONCATENATE($N$3,I6,$O$3,A6) -> http://192.168.187.30:8000/nh.html?mode=kiosk&from=K-207 | D6: H&M önü, Penti tarafı | E6: -2 Metro | F6: Yatay | G6: msedge, RESTART_CHECK | I6: nh | J6: Kuzey (+30 saat yönü) | K6: 490x692 | L6: W | M6: Dokunmatiği çalışmıyor.
A7: K-206 | B7: 192.168.187.56 | C7: =CONCATENATE($N$3,I7,$O$3,A7) -> http://192.168.187.30:8000/sh.html?mode=kiosk&from=K-206 | D7: H&M önü, Perspective tarafı | E7: -2 Metro | F7: Yatay | G7: RESTART, ripple | H7: 6 | I7: sh | J7: Güney (+30 saat yönü) | K7: 490x692 | L7: X
A8: K-110 | B8: 192.168.187.100 | C8: =CONCATENATE($N$3,I8,$O$3,A8) -> http://192.168.187.30:8000/nh.html?mode=kiosk&from=K-110 | D8: Apple (Boğaz) önü, Zen Pırlanta tarafı | E8: -1 Boğaz | F8: Yatay | G8: RESTART, ripple | I8: nh | J8: Kuzey (+30 saat yönü) | K8: 490x692 | L8: W
A9: K-108 | B9: 192.168.187.58 | C9: =CONCATENATE($N$3,I9,$O$3,A9) -> http://192.168.187.30:8000/sh.html?mode=kiosk&from=K-108 | D9: Apple (Boğaz) önü, Lacoste tarafı | E9: -1 Boğaz | F9: Yatay | G9: radmin | H9: 8 | I9: sh | J9: Güney (+30 saat yönü) | K9: 490x692 | L9: W | M9: Görsel geçişi sorunlu. / Formatlandı.
A10: K-109 | B10: 192.168.187.59 | C10: =CONCATENATE($N$3,I10,$O$3,A10) -> http://192.168.187.30:8000/wh.html?mode=kiosk&from=K-109 | D10: Levazım girişi, Brooks Brothers karşısı | E10: -1 Boğaz | F10: Yatay | G10: radmin | H10: 9 | I10: wh | J10: Batı (+30 saat yönü) | K10: 692x490 | L10: W | M10: Görsel geçişi sorunlu. / Formatlandı.
A11: K021 | B11: 192.168.187.60 | C11: =CONCATENATE($N$3,I11,$O$3,A11) -> http://192.168.187.30:8000/sv.html?mode=kiosk&from=K021 | D11: Meydan katı Metro çıkışı, Sail Loft Vakkorama önde kalacak | E11: 0 Meydan | F11: Dikey | G11: - | H11: 21 | I11: sv | J11: Güney (+30 saat yönü) | K11: 490x692 | L11: X | M11: Görsel geçişi sorunlu. / Dokunmatiği çalışmıyor.
A12: K022 | B12: 192.168.187.61 | C12: =CONCATENATE($N$3,I12,$O$3,A12) -> http://192.168.187.30:8000/sv.html?mode=kiosk&from=K022 | D12: Vakko önü, Vakko sağda kalacak | E12: 0 Meydan | F12: Dikey | G12: RADMIN, CONN_CHECK | H12: 22 | I12: sv | J12: Güney (+30 saat yönü) | K12: 490x692 | M12: Dokunmatiği çalışmıyor.
A13: K012 | B13: 192.168.187.62 | C13: =CONCATENATE($N$3,I13,$O$3,A13) -> http://192.168.187.30:8000/nh.html?mode=kiosk&from=K012 | D13: Godiva yanı, asansör önü | E13: 0 Meydan | F13: Yatay | G13: RESTART, ripple | H13: 12 | I13: nh | J13: Kuzey (+30 saat yönü) | K13: 490x692 | L13: W | M13: Görsel geçişi sorunlu. / Formatlandı.
A14: K014 | B14: 192.168.187.64 | C14: =CONCATENATE($N$3,I14,$O$3,A14) -> http://192.168.187.30:8000/nv.html?mode=kiosk&from=K014 | D14: Parle önü, Apple camı arkada kalacak | F14: Dikey | H14: 14 | I14: nv | J14: Kuzey (+30 saat yönü) | K14: 490x692 | M14: Kaldırılmış.
A15: K025 | B15: 192.168.187.65 | C15: =CONCATENATE($N$3,I15,$O$3,A15) -> http://192.168.187.30:8000/sv.html?mode=kiosk&from=K025 | D15: Dolce&Gabbana önü, Dolce&Gabbana sağda kalacak | E15: 0 Meydan | F15: Dikey | G15: - | H15: 25 | I15: sv | J15: Güney (+30 saat yönü) | K15: 490x692 | M15: Dokunmatiği çalışmıyor.
A16: K016 | B16: 192.168.187.66 | C16: =CONCATENATE($N$3,I16,$O$3,A16) -> http://192.168.187.30:8000/nh.html?mode=kiosk&from=K016 | D16: Saray Muhallebicisi önü | E16: 0 Meydan | F16: Yatay | G16: ripple | H16: 16 | I16: nh | J16: Kuzey (+30 saat yönü) | K16: 490x692 | L16: W | M16: Formatlandı. / Kapatıldı.
A17: K118 | B17: 192.168.187.68 | C17: =CONCATENATE($N$3,I17,$O$3,A17) -> http://192.168.187.30:8000/wh.html?mode=kiosk&from=K118 | D17: Miele önü, merdiven çıkışı | E17: 1 Köprü | F17: Yatay | G17: ripple | H17: 18 | I17: wh | J17: Batı (+30 saat yönü) | K17: 692x490 | L17: W | M17: Görsel geçişi sorunlu. / Formatlandı.
A18: K119 | B18: 192.168.187.69 | C18: =CONCATENATE($N$3,I18,$O$3,A18) -> http://192.168.187.30:8000/nv.html?mode=kiosk&from=K119 | D18: Zanzibar önü, Zanzibar önde kalacak | F18: Dikey | H18: 19 | I18: nv | J18: Kuzey (+30 saat yönü) | K18: 490x692 | M18: Kaldırılmış.
A19: K024 | B19: 192.168.187.74 | C19: =CONCATENATE($N$3,I19,$O$3,A19) -> http://192.168.187.30:8000/sv.html?mode=kiosk&from=K024 | D19: Parle önü, Apple camı önde kalacak | F19: Dikey | H19: 24 | I19: sv | J19: Güney (+30 saat yönü) | K19: 490x692 | M19: Kaldırılmış.
A20: K120 | B20: 192.168.187.70 | C20: =CONCATENATE($N$3,I20,$O$3,A20) -> http://192.168.187.30:8000/sh.html?mode=kiosk&from=K120 | D20: Funloft yanı | E20: 1 Köprü | F20: Yatay | G20: radmin | H20: 20 | I20: sh | J20: Güney (+30 saat yönü) | K20: 490x692 | L20: W | M20: Yeniden başlamış gibi. / Formatlandı.
A21: K010 | B21: 192.168.187.71 | C21: =CONCATENATE($N$3,I21,$O$3,A21) -> http://192.168.187.30:8000/nv.html?mode=kiosk&from=K010 | D21: Meydan katı Metro çıkışı, Sail Loft Vakkorama arkada kalacak | E21: 0 Meydan | F21: Dikey | G21: CONN_CHECK | H21: 10 | I21: nv | J21: Kuzey (+30 saat yönü) | K21: 490x692 | M21: Dokunmatik sorunu var, Vestel bakacak. / Düzeldi.
A22: K011 | B22: 192.168.187.72 | C22: =CONCATENATE($N$3,I22,$O$3,A22) -> http://192.168.187.30:8000/nv.html?mode=kiosk&from=K011 | D22: Vakko önü, Vakko solda kalacak | E22: 0 Meydan | F22: Dikey | G22: - | H22: 11 | I22: nv | J22: Kuzey (+30 saat yönü) | K22: 490x692 | M22: Görsel geçişi sorunlu.
A23: K015 | B23: 192.168.187.75 | C23: =CONCATENATE($N$3,I23,$O$3,A23) -> http://192.168.187.30:8000/nv.html?mode=kiosk&from=K015 | D23: Dolce&Gabbana önü, Dolce&Gabbana solda kalacak | E23: 0 Meydan | F23: Dikey | G23: - | H23: 15 | I23: nv | J23: Kuzey (+30 saat yönü) | K23: 490x692 | M23: Formatlandı.
A24: K023 | B24: 192.168.187.77 | C24: =CONCATENATE($N$3,I24,$O$3,A24) -> http://192.168.187.30:8000/wh.html?mode=kiosk&from=K023 | D24: Ulus girişi | E24: 0 Meydan | F24: Yatay | G24: Kalktı mı? | I24: wh | J24: Doğu (+30 saat yönü) | K24: 692x490 | L24: W
A25: K127 | B25: 192.168.187.77 | D25: Zanzibar önü, Zanzibar arkada kalacak | F25: Dikey | H25: 27 | I25: sv | J25: Güney (+30 saat yönü) | K25: 490x692 | M25: Kaldırılmış.
A26: TST | B26: 192.168.187.46 | M26: 65"
A27: TST | B27: 192.168.187.47
A28: K-205 | B28: 192.168.187.55 | D28: Apple (Metro) önü | F28: Yatay | H28: 5 | I28: sh | J28: Güney (+30 saat yönü) | K28: 490x692 | M28: Formatlandı. / 14.05.2020'ye kadar kalktı
A29: K-107 | B29: 192.168.187.57 | D29: Zip Car önü | F29: Yatay | H29: 7 | I29: sh | J29: Güney (+30 saat yönü) | K29: 490x692 | M29: Formatlandı.
A30: K023 | B30: 192.168.187.73 | D30: Five O'Clock önü, Sokak önde kalacak | F30: Dikey | H30: 23 | I30: ev | J30: Batı (+30 saat yönü) | K30: 692x490
A31: K013 | B31: 192.168.187.63 | D31: Five O'Clock önü, Sokak arkada kalacak | F31: Dikey | H31: 13 | I31: wv | J31: Doğu (+30 saat yönü) | K31: 692x490
A32: K026 | B32: 192.168.187.76 | D32: Tiffany önü, Sokak arkada kalacak | F32: Dikey | H32: 26 | I32: nv | J32: Kuzey (+30 saat yönü) | K32: 490x692
A33: K017 | B33: 192.168.187.67 | D33: Tiffany önü, Sokak önde kalacak | F33: Dikey | H33: 17 | I33: sv | J33: Güney (+30 saat yönü) | K33: 490x692

Sheet QR
A1: ID | B1: QR | C1: Floor | D1: Link | E1: Location
A2: 1 | B2: QR101 | C2: 1 | D2: https://zorlucenter.inmapper.com/qr/?id=1 | E2: Kafe Vesto Yanı
A3: 2 | B3: QR001 | C3: 0 | D3: https://zorlucenter.inmapper.com/qr/?id=2 | E3: Vakkorama Önü
A4: 3 | B4: QR002 | C4: 0 | D4: https://zorlucenter.inmapper.com/qr/?id=3 | E4: Vakkorama Önü
A5: 4 | B5: QR003 | C5: 0 | D5: https://zorlucenter.inmapper.com/qr/?id=4 | E5: Vakkorama Önü
A6: 5 | B6: QR004 | C6: 0 | D6: https://zorlucenter.inmapper.com/qr/?id=5 | E6: Valentino Önü
A7: 6 | B7: QR005 | C7: 0 | D7: https://zorlucenter.inmapper.com/qr/?id=6 | E7: Balenciage Önü
A8: 7 | B8: QR006 | C8: 0 | D8: https://zorlucenter.inmapper.com/qr/?id=7 | E8: Nespresso Önü
A9: 8 | B9: QR007 | C9: 0 | D9: https://zorlucenter.inmapper.com/qr/?id=8 | E9: BigChefs Önü
A10: 9 | B10: QR008 | C10: 0 | D10: https://zorlucenter.inmapper.com/qr/?id=9 | E10: Tommi Brasserie Önü
A11: 10 | B11: QR009 | C11: 0 | D11: https://zorlucenter.inmapper.com/qr/?id=10 | E11: Saray Muhallebicisi Önü
A12: 11 | B12: QR010 | C12: 0 | D12: https://zorlucenter.inmapper.com/qr/?id=11 | E12: Five O'Clock Önü
A13: 12 | B13: QR011 | C13: 0 | D13: https://zorlucenter.inmapper.com/qr/?id=12 | E13: Fauchon Paris Önü
... A33: 32 | B33: QR-302 | C33: -3 | D33: https://zorlucenter.inmapper.com/qr/?id=32 | E33: Levazım Otopark

Sheet QR-Arama
A1: No | C1: Name
A2: 116 | B2: Zara- | C2: Zara
A3: 65 | B3: Bonesserie İstanbul- | C3: Bonesserie İstanbul
A4: 54 | B4: Eat- | C4: Eataly
A5: 42 | B5: Zula- | C5: Zula
A6: 42 | B6: - | C6: BigChefs
A7: 37 | B7: - | C7: Eataly
A8: 35 | B8: Star- | C8: Starbucks
A9: 30 | B9: - | C9: Toyzz Shop
A10: 30 | B10: Ea- | C10: Eataly
A11: 28 | B11: H- | C11: H&M
A12: 27 | B12: - | C12: Burger King
A13: 26 | B13: - | C13: Happy Moon's
... A1323: 1 | B1323: İtaly- | C1323: Eataly

Sheet QR-Arama-Pivot

Sheet QR-Rota
A1: EVENTS | B1: EVENT NAME | D1: FROM | E1: > | F1: TO | G1: FROM>TO
A2: 47 | B2: Konumunuz | C2: QR-104 | D2: =IF(ISBLANK(C2), B2, C2) -> QR-104 | F2: Eataly | G2: =CONCATENATE(D2,$E$1,F2) -> QR-104>Eataly
A3: 28 | B3: Your Location | C3: QR006 | D3: =IF(ISBLANK(C3), B3, C3) -> QR006 | F3: Zara | G3: =CONCATENATE(D3,$E$1,F3) -> QR006>Zara
A4: 28 | B4: Konumunuz | C4: QR-104 | D4: =IF(ISBLANK(C4), B4, C4) -> QR-104 | F4: Happy Moon's | G4: =CONCATENATE(D4,$E$1,F4) -> QR-104>Happy Moon's
A5: 25 | B5: Konumunuz | C5: QR-104 | D5: =IF(ISBLANK(C5), B5, C5) -> QR-104 | F5: Zula | G5: =CONCATENATE(D5,$E$1,F5) -> QR-104>Zula
A6: 25 | B6: Konumunuz | C6: QR-104 | D6: =IF(ISBLANK(C6), B6, C6) -> QR-104 | F6: Zara | G6: =CONCATENATE(D6,$E$1,F6) -> QR-104>Zara
A7: 23 | B7: Your Location | C7: QR-104 | D7: =IF(ISBLANK(C7), B7, C7) -> QR-104 | F7: Eataly | G7: =CONCATENATE(D7,$E$1,F7) -> QR-104>Eataly
A8: 22 | B8: Konumunuz | C8: QR-104 | D8: =IF(ISBLANK(C8), B8, C8) -> QR-104 | F8: Starbucks | G8: =CONCATENATE(D8,$E$1,F8) -> QR-104>Starbucks
A9: 21 | B9: Your Location | C9: QR-104 | D9: =IF(ISBLANK(C9), B9, C9) -> QR-104 | F9: Zara | G9: =CONCATENATE(D9,$E$1,F9) -> QR-104>Zara
A10: 20 | B10: Konumunuz | C10: QR-104 | D10: =IF(ISBLANK(C10), B10, C10) -> QR-104 | F10: Macrocenter | G10: =CONCATENATE(D10,$E$1,F10) -> QR-104>Macrocenter
A11: 18 | B11: Konumunuz | C11: QR-104 | D11: =IF(ISBLANK(C11), B11, C11) -> QR-104 | F11: PSM | G11: =CONCATENATE(D11,$E$1,F11) -> QR-104>PSM
A12: 17 | B12: Konumunuz | C12: QR-104 | D12: =IF(ISBLANK(C12), B12, C12) -> QR-104 | F12: BigChefs | G12: =CONCATENATE(D12,$E$1,F12) -> QR-104>BigChefs
A13: 15 | B13: Zara | D13: =IF(ISBLANK(C13), B13, C13) -> Zara | F13: H&M | G13: =CONCATENATE(D13,$E$1,F13) -> Zara>H&M
A14: 15 | B14: Your Location | C14: QR-112 | D14: =IF(ISBLANK(C14), B14, C14) -> QR-112 | F14: Zara | G14: =CONCATENATE(D14,$E$1,F14) -> QR-112>Zara
A15: 14 | B15: Konumunuz | C15: QR-104 | D15: =IF(ISBLANK(C15), B15, C15) -> QR-104 | F15: D&R | G15: =CONCATENATE(D15,$E$1,F15) -> QR-104>D&R
A16: 14 | B16: Eataly | D16: =IF(ISBLANK(C16), B16, C16) -> Eataly | F16: Eataly | G16: =CONCATENATE(D16,$E$1,F16) -> Eataly>Eataly
A17: 13 | B17: Konumunuz | C17: QR-104 | D17: =IF(ISBLANK(C17), B17, C17) -> QR-104 | F17: Toyzz Shop | G17: =CONCATENATE(D17,$E$1,F17) -> QR-104>Toyzz Shop
A18: 12 | B18: Konumunuz | C18: QR-104 | D18: =IF(ISBLANK(C18), B18, C18) -> QR-104 | F18: Watsons | G18: =CONCATENATE(D18,$E$1,F18) -> QR-104>Watsons
A19: 11 | B19: Konumunuz | C19: QR-104 | D19: =IF(ISBLANK(C19), B19, C19) -> QR-104 | F19: Tobacco Shop | G19: =CONCATENATE(D19,$E$1,F19) -> QR-104>Tobacco Shop
A20: 11 | B20: Your Location | C20: QR-104 | D20: =IF(ISBLANK(C20), B20, C20) -> QR-104 | F20: Starbucks | G20: =CONCATENATE(D20,$E$1,F20) -> QR-104>Starbucks
A21: 11 | B21: Konumunuz | C21: QR-104 | D21: =IF(ISBLANK(C21), B21, C21) -> QR-104 | F21: MediaMarkt | G21: =CONCATENATE(D21,$E$1,F21) -> QR-104>MediaMarkt
A22: 11 | B22: Konumunuz | C22: QR-104 | D22: =IF(ISBLANK(C22), B22, C22) -> QR-104 | F22: Mescit | G22: =CONCATENATE(D22,$E$1,F22) -> QR-104>Mescit
A23: 10 | B23: Konumunuz | C23: QR-104 | D23: =IF(ISBLANK(C23), B23, C23) -> QR-104 | F23: H&M | G23: =CONCATENATE(D23,$E$1,F23) -> QR-104>H&M
A24: 10 | B24: Your Location | C24: QR-104 | D24: =IF(ISBLANK(C24), B24, C24) -> QR-104 | F24: Macrocenter | G24: =CONCATENATE(D24,$E$1,F24) -> QR-104>Macrocenter
A25: 10 | B25: Konumunuz | C25: QR-104 | D25: =IF(ISBLANK(C25), B25, C25) -> QR-104 | F25: Tuvalet | G25: =CONCATENATE(D25,$E$1,F25) -> QR-104>Tuvalet
A26: 10 | B26: Your Location | C26: QR-104 | D26: =IF(ISBLANK(C26), B26, C26) -> QR-104 | F26: Tax Free Zone (Info Desk) | G26: =CONCATENATE(D26,$E$1,F26) -> QR-104>Tax Free Zone (Info Desk)
A27: 9 | B27: Your Location | C27: QR-104 | D27: =IF(ISBLANK(C27), B27, C27) -> QR-104 | F27: H&M | G27: =CONCATENATE(D27,$E$1,F27) -> QR-104>H&M
A28: 9 | B28: Konumunuz | C28: QR-104 | D28: =IF(ISBLANK(C28), B28, C28) -> QR-104 | F28: Garanti BBVA (ATM) | G28: =CONCATENATE(D28,$E$1,F28) -> QR-104>Garanti BBVA (ATM)
... A62: 6 | B62: Your Location | C62: QR006 | D62: =IF(ISBLANK(C62), B62, C62) -> QR006 | F62: COS | G62: =CONCATENATE(D62,$E$1,F62) -> QR006>COS
A63: 6 | B63: Zara | D63: =IF(ISBLANK(C63), B63, C63) -> Zara | F63: Macrocenter | G63: =CONCATENATE(D63,$E$1,F63) -> Zara>Macrocenter
A64: 6 | B64: Beymen(Tommy Hilfiger yanı) | D64: =IF(ISBLANK(C64), B64, C64) -> Beymen(Tommy Hilfiger yanı) | F64: Starbucks | G64: =CONCATENATE(D64,$E$1,F64) -> Beymen(Tommy Hilfiger yanı)>Starbucks
A65: 6 | B65: Konumunuz | C65: QR-104 | D65: =IF(ISBLANK(C65), B65, C65) -> QR-104 | F65: Sephora | G65: =CONCATENATE(D65,$E$1,F65) -> QR-104>Sephora
A66: 6 | B66: Konumunuz | C66: QR006 | D66: =IF(ISBLANK(C66), B66, C66) -> QR006 | F66: Apple | G66: =CONCATENATE(D66,$E$1,F66) -> QR006>Apple
A67: 6 | B67: Etiler Marmaris | D67: =IF(ISBLANK(C67), B67, C67) -> Etiler Marmaris | F67: AI Analiz | G67: =CONCATENATE(D67,$E$1,F67) -> Etiler Marmaris>AI Analiz
A68: 5 | B68: Konumunuz | C68: QR-104 | D68: =IF(ISBLANK(C68), B68, C68) -> QR-104 | F68: Beymen | G68: =CONCATENATE(D68,$E$1,F68) -> QR-104>Beymen
A69: 5 | B69: Konumunuz | C69: QR-104 | D69: =IF(ISBLANK(C69), B69, C69) -> QR-104 | F69: Paşabahçe Mağazaları | G69: =CONCATENATE(D69,$E$1,F69) -> QR-104>Paşabahçe Mağazaları
A70: 5 | B70: Konumunuz | C70: QR-203 | D70: =IF(ISBLANK(C70), B70, C70) -> QR-203 | F70: Beymen | G70: =CONCATENATE(D70,$E$1,F70) -> QR-203>Beymen
A71: 5 | B71: Konumunuz | C71: QR-203 | D71: =IF(ISBLANK(C71), B71, C71) -> QR-203 | F71: D&R | G71: =CONCATENATE(D71,$E$1,F71) -> QR-203>D&R
A72: 5 | B72: Your Location | C72: QR-104 | D72: =IF(ISBLANK(C72), B72, C72) -> QR-104 | F72: D&R | G72: =CONCATENATE(D72,$E$1,F72) -> QR-104>D&R
A73: 5 | B73: Your Location | C73: QR-104 | D73: =IF(ISBLANK(C73), B73, C73) -> QR-104 | F73: MediaMarkt | G73: =CONCATENATE(D73,$E$1,F73) -> QR-104>MediaMarkt
A74: 5 | B74: Your Location | C74: QR-104 | D74: =IF(ISBLANK(C74), B74, C74) -> QR-104 | F74: Park Area | G74: =CONCATENATE(D74,$E$1,F74) -> QR-104>Park Area
A75: 5 | B75: Your Location | C75: QR-112 | D75: =IF(ISBLANK(C75), B75, C75) -> QR-112 | F75: H&M | G75: =CONCATENATE(D75,$E$1,F75) -> QR-112>H&M
A76: 5 | B76: Your Location | C76: QR-203 | D76: =IF(ISBLANK(C76), B76, C76) -> QR-203 | F76: D&R | G76: =CONCATENATE(D76,$E$1,F76) -> QR-203>D&R
A77: 5 | B77: Zara | D77: =IF(ISBLANK(C77), B77, C77) -> Zara | F77: Mango | G77: =CONCATENATE(D77,$E$1,F77) -> Zara>Mango
A78: 5 | B78: Konumunuz | C78: QR-104 | D78: =IF(ISBLANK(C78), B78, C78) -> QR-104 | F78: Kafe Vesto | G78: =CONCATENATE(D78,$E$1,F78) -> QR-104>Kafe Vesto
A79: 5 | B79: Konumunuz | C79: QR-104 | D79: =IF(ISBLANK(C79), B79, C79) -> QR-104 | F79: Saray Muhallebicisi | G79: =CONCATENATE(D79,$E$1,F79) -> QR-104>Saray Muhallebicisi
A80: 5 | B80: Konumunuz | C80: QR-104 | D80: =IF(ISBLANK(C80), B80, C80) -> QR-104 | F80: SushiCo | G80: =CONCATENATE(D80,$E$1,F80) -> QR-104>SushiCo
A81: 5 | B81: Konumunuz | C81: QR-104 | D81: =IF(ISBLANK(C81), B81, C81) -> QR-104 | F81: Welldone | G81: =CONCATENATE(D81,$E$1,F81) -> QR-104>Welldone
A82: 5 | B82: Konumunuz | C82: QR-112 | D82: =IF(ISBLANK(C82), B82, C82) -> QR-112 | F82: Watsons | G82: =CONCATENATE(D82,$E$1,F82) -> QR-112>Watsons
A83: 5 | B83: Konumunuz | C83: QR-301 | D83: =IF(ISBLANK(C83), B83, C83) -> QR-301 | F83: Togg Deneyim Merkezi | G83: =CONCATENATE(D83,$E$1,F83) -> QR-301>Togg Deneyim Merkezi
A84: 5 | B84: Konumunuz | C84: QR-302 | D84: =IF(ISBLANK(C84), B84, C84) -> QR-302 | F84: Apple | G84: =CONCATENATE(D84,$E$1,F84) -> QR-302>Apple
A85: 5 | B85: Yargıcı | D85: =IF(ISBLANK(C85), B85, C85) -> Yargıcı | F85: Toyzz Shop | G85: =CONCATENATE(D85,$E$1,F85) -> Yargıcı>Toyzz Shop
A86: 5 | B86: Your Location | C86: QR-104 | D86: =IF(ISBLANK(C86), B86, C86) -> QR-104 | F86: Happy Moon's | G86: =CONCATENATE(D86,$E$1,F86) -> QR-104>Happy Moon's
A87: 5 | B87: Your Location | C87: QR-104 | D87: =IF(ISBLANK(C87), B87, C87) -> QR-104 | F87: Watsons | G87: =CONCATENATE(D87,$E$1,F87) -> QR-104>Watsons
A88: 5 | B88: Zara | D88: =IF(ISBLANK(C88), B88, C88) -> Zara | F88: Zara | G88: =CONCATENATE(D88,$E$1,F88) -> Zara>Zara
A89: 5 | B89: Konumunuz | C89: QR-104 | D89: =IF(ISBLANK(C89), B89, C89) -> QR-104 | F89: Swarovski | G89: =CONCATENATE(D89,$E$1,F89) -> QR-104>Swarovski
A90: 5 | B90: Konumunuz | C90: QR-104 | D90: =IF(ISBLANK(C90), B90, C90) -> QR-104 | F90: Vakko | G90: =CONCATENATE(D90,$E$1,F90) -> QR-104>Vakko
A91: 5 | B91: Konumunuz | C91: QR-104 | D91: =IF(ISBLANK(C91), B91, C91) -> QR-104 | F91: Zara Home | G91: =CONCATENATE(D91,$E$1,F91) -> QR-104>Zara Home
A92: 5 | B92: Konumunuz | C92: QR-301 | D92: =IF(ISBLANK(C92), B92, C92) -> QR-301 | F92: Park Alanı | G92: =CONCATENATE(D92,$E$1,F92) -> QR-301>Park Alanı
A93: 5 | B93: Your Location | C93: QR-104 | D93: =IF(ISBLANK(C93), B93, C93) -> QR-104 | F93: WC | G93: =CONCATENATE(D93,$E$1,F93) -> QR-104>WC
A94: 5 | B94: Your Location | C94: QR-203 | D94: =IF(ISBLANK(C94), B94, C94) -> QR-203 | F94: Zula | G94: =CONCATENATE(D94,$E$1,F94) -> QR-203>Zula
A95: 5 | B95: Yargıcı | D95: =IF(ISBLANK(C95), B95, C95) -> Yargıcı | F95: Burger King | G95: =CONCATENATE(D95,$E$1,F95) -> Yargıcı>Burger King
A96: 5 | B96: Your Location | C96: QR-203 | D96: =IF(ISBLANK(C96), B96, C96) -> QR-203 | F96: Happy Moon's | G96: =CONCATENATE(D96,$E$1,F96) -> QR-203>Happy Moon's
A97: 5 | B97: English Home | D97: =IF(ISBLANK(C97), B97, C97) -> English Home | F97: English Home | G97: =CONCATENATE(D97,$E$1,F97) -> English Home>English Home
A98: 5 | B98: Kısmet by Milka | D98: =IF(ISBLANK(C98), B98, C98) -> Kısmet by Milka | F98: Kısmet by Milka | G98: =CONCATENATE(D98,$E$1,F98) -> Kısmet by Milka>Kısmet by Milka
A99: 5 | B99: Your Location | C99: QR-112 | D99: =IF(ISBLANK(C99), B99, C99) -> QR-112 | F99: Parle | G99: =CONCATENATE(D99,$E$1,F99) -> QR-112>Parle
A100: 5 | B100: Your Location | C100: QR006 | D100: =IF(ISBLANK(C100), B100, C100) -> QR006 | F100: SushiCo | G100: =CONCATENATE(D100,$E$1,F100) -> QR006>SushiCo
A101: 4 | B101: Caffe Nero | D101: =IF(ISBLANK(C101), B101, C101) -> Caffe Nero | F101: Eataly | G101: =CONCATENATE(D101,$E$1,F101) -> Caffe Nero>Eataly
A102: 4 | B102: Intimissimi | D102: =IF(ISBLANK(C102), B102, C102) -> Intimissimi | F102: Watsons | G102: =CONCATENATE(D102,$E$1,F102) -> Intimissimi>Watsons
A103: 4 | B103: Konumunuz | C103: QR-104 | D103: =IF(ISBLANK(C103), B103, C103) -> QR-104 | F103: Asics | G103: =CONCATENATE(D103,$E$1,F103) -> QR-104>Asics
A104: 4 | B104: Konumunuz | C104: QR-104 | D104: =IF(ISBLANK(C104), B104, C104) -> QR-104 | F104: Godiva | G104: =CONCATENATE(D104,$E$1,F104) -> QR-104>Godiva
A105: 4 | B105: Konumunuz | C105: QR-104 | D105: =IF(ISBLANK(C105), B105, C105) -> QR-104 | F105: Vestel | G105: =CONCATENATE(D105,$E$1,F105) -> QR-104>Vestel
A106: 4 | B106: Konumunuz | C106: QR-203 | D106: =IF(ISBLANK(C106), B106, C106) -> QR-203 | F106: Caffe Nero | G106: =CONCATENATE(D106,$E$1,F106) -> QR-203>Caffe Nero
A107: 4 | B107: Konumunuz | C107: QR-203 | D107: =IF(ISBLANK(C107), B107, C107) -> QR-203 | F107: Zula | G107: =CONCATENATE(D107,$E$1,F107) -> QR-203>Zula
A108: 4 | B108: Konumunuz | C108: QR-301 | D108: =IF(ISBLANK(C108), B108, C108) -> QR-301 | F108: Memorial Wellness | G108: =CONCATENATE(D108,$E$1,F108) -> QR-301>Memorial Wellness
A109: 4 | B109: Louis Vuitton | D109: =IF(ISBLANK(C109), B109, C109) -> Louis Vuitton | F109: Eataly | G109: =CONCATENATE(D109,$E$1,F109) -> Louis Vuitton>Eataly
A110: 4 | B110: Your Location | C110: QR-104 | D110: =IF(ISBLANK(C110), B110, C110) -> QR-104 | F110: Masjid | G110: =CONCATENATE(D110,$E$1,F110) -> QR-104>Masjid
A111: 4 | B111: Your Location | C111: QR-104 | D111: =IF(ISBLANK(C111), B111, C111) -> QR-104 | F111: US Polo Assn. | G111: =CONCATENATE(D111,$E$1,F111) -> QR-104>US Polo Assn.
A112: 4 | B112: Your Location | C112: QR-104 | D112: =IF(ISBLANK(C112), B112, C112) -> QR-104 | F112: Victoria's Secret | G112: =CONCATENATE(D112,$E$1,F112) -> QR-104>Victoria's Secret
A113: 4 | B113: Your Location | C113: QR-203 | D113: =IF(ISBLANK(C113), B113, C113) -> QR-203 | F113: Eataly | G113: =CONCATENATE(D113,$E$1,F113) -> QR-203>Eataly
A114: 4 | B114: Zara | D114: =IF(ISBLANK(C114), B114, C114) -> Zara | F114: WC | G114: =CONCATENATE(D114,$E$1,F114) -> Zara>WC
A115: 4 | B115: Eataly | D115: =IF(ISBLANK(C115), B115, C115) -> Eataly | F115: Burger King | G115: =CONCATENATE(D115,$E$1,F115) -> Eataly>Burger King
A116: 4 | B116: Intimissimi | D116: =IF(ISBLANK(C116), B116, C116) -> Intimissimi | F116: BigChefs | G116: =CONCATENATE(D116,$E$1,F116) -> Intimissimi>BigChefs
A117: 4 | B117: Konumunuz | C117: QR-104 | D117: =IF(ISBLANK(C117), B117, C117) -> QR-104 | F117: COS | G117: =CONCATENATE(D117,$E$1,F117) -> QR-104>COS
A118: 4 | B118: Konumunuz | C118: QR-104 | D118: =IF(ISBLANK(C118), B118, C118) -> QR-104 | F118: Skechers | G118: =CONCATENATE(D118,$E$1,F118) -> QR-104>Skechers
A119: 4 | B119: Konumunuz | C119: QR-203 | D119: =IF(ISBLANK(C119), B119, C119) -> QR-203 | F119: MediaMarkt | G119: =CONCATENATE(D119,$E$1,F119) -> QR-203>MediaMarkt
A120: 4 | B120: Konumunuz | C120: QR-203 | D120: =IF(ISBLANK(C120), B120, C120) -> QR-203 | F120: Pandora | G120: =CONCATENATE(D120,$E$1,F120) -> QR-203>Pandora
A121: 4 | B121: Konumunuz | C121: QR-203 | D121: =IF(ISBLANK(C121), B121, C121) -> QR-203 | F121: Toyzz Shop | G121: =CONCATENATE(D121,$E$1,F121) -> QR-203>Toyzz Shop
A122: 4 | B122: Konumunuz | C122: QR005 | D122: =IF(ISBLANK(C122), B122, C122) -> QR005 | F122: Zula | G122: =CONCATENATE(D122,$E$1,F122) -> QR005>Zula
A123: 4 | B123: Your Location | C123: QR-104 | D123: =IF(ISBLANK(C123), B123, C123) -> QR-104 | F123: Info Desk | G123: =CONCATENATE(D123,$E$1,F123) -> QR-104>Info Desk
A124: 4 | B124: Your Location | C124: QR-104 | D124: =IF(ISBLANK(C124), B124, C124) -> QR-104 | F124: Zor Exchange | G124: =CONCATENATE(D124,$E$1,F124) -> QR-104>Zor Exchange
A125: 4 | B125: Your Location | C125: QR-203 | D125: =IF(ISBLANK(C125), B125, C125) -> QR-203 | F125: Apple | G125: =CONCATENATE(D125,$E$1,F125) -> QR-203>Apple
A126: 4 | B126: Your Location | C126: QR-203 | D126: =IF(ISBLANK(C126), B126, C126) -> QR-203 | F126: BigChefs | G126: =CONCATENATE(D126,$E$1,F126) -> QR-203>BigChefs
A127: 4 | B127: Zara | D127: =IF(ISBLANK(C127), B127, C127) -> Zara | F127: Nespresso | G127: =CONCATENATE(D127,$E$1,F127) -> Zara>Nespresso
A128: 4 | B128: Konumunuz | C128: QR-104 | D128: =IF(ISBLANK(C128), B128, C128) -> QR-104 | F128: Metro<br>Metrobüs | G128: =CONCATENATE(D128,$E$1,F128) -> QR-104>Metro<br>Metrobüs
A129: 4 | B129: Konumunuz | C129: QR006 | D129: =IF(ISBLANK(C129), B129, C129) -> QR006 | F129: Divarese | G129: =CONCATENATE(D129,$E$1,F129) -> QR006>Divarese
A130: 4 | B130: Toyzz Shop | D130: =IF(ISBLANK(C130), B130, C130) -> Toyzz Shop | F130: Funloft | G130: =CONCATENATE(D130,$E$1,F130) -> Toyzz Shop>Funloft
A131: 4 | B131: Your Location | C131: QR003 | D131: =IF(ISBLANK(C131), B131, C131) -> QR003 | F131: Pharmacy | G131: =CONCATENATE(D131,$E$1,F131) -> QR003>Pharmacy
A132: 4 | B132: Your Location | C132: QR006 | D132: =IF(ISBLANK(C132), B132, C132) -> QR006 | F132: Apple | G132: =CONCATENATE(D132,$E$1,F132) -> QR006>Apple
A133: 4 | B133: Your Location | C133: QR006 | D133: =IF(ISBLANK(C133), B133, C133) -> QR006 | F133: Zula | G133: =CONCATENATE(D133,$E$1,F133) -> QR006>Zula
...

Sheet QR-Rota-Pivot

Sheet Ofisler
A1: ATLANTIC DENTAL CLINIC | B1: OFIS AVM LOBI | C1: Atlantic Dental Clinic | D1: Ofis AVM Lobi | E1: =PROPER(A1)= PROPER(C1) -> TRUE
A2: ESTEE LAUDER COMPANES TÜRKIYE | B2: OFIS AVM LOBI | C2: Estee Lauder Companes Türkiye | D2: Ofis AVM Lobi | E2: =PROPER(A2)= PROPER(C2) -> TRUE
A3: KARANFIL-BABIL GRUP | B3: OFIS AVM LOBI | C3: =PROPER(A3) -> Karanfil-Babil Grup | D3: Ofis AVM Lobi | E3: =PROPER(A3)= PROPER(C3) -> TRUE
A4: KIBAR HOLDING | B4: OFIS AVM LOBI | C4: Kibar Holding | D4: Ofis AVM Lobi | E4: =PROPER(A4)= PROPER(C4) -> TRUE
A5: LIMAK HOLDING | B5: OFIS AVM LOBI | C5: Limak Holding | D5: Ofis AVM Lobi | E5: =PROPER(A5)= PROPER(C5) -> TRUE
A6: MEDBULK DENIZCILIK | B6: OFIS AVM LOBI | C6: Medbulk Denizcilik | D6: Ofis AVM Lobi | E6: =PROPER(A6)= PROPER(C6) -> TRUE
A7: OLTAN VE KÖLEOĞLU ENERJI | B7: OFIS AVM LOBI | C7: Oltan ve Köleoğlu Enerji | D7: Ofis AVM Lobi | E7: =PROPER(A7)= PROPER(C7) -> TRUE
A8: PEAK | B8: OFIS AVM LOBI | C8: Peak | D8: Ofis AVM Lobi | E8: =PROPER(A8)= PROPER(C8) -> TRUE
A9: POSCO ASSAN TST ÇELIK SAN. A.Ş. | B9: OFIS AVM LOBI | C9: Posco Assan TST Çelik San. A.Ş. | D9: Ofis AVM Lobi | E9: =PROPER(A9)= PROPER(C9) -> TRUE
A10: TOREN A.Ş. | B10: OFIS AVM LOBI | C10: Toren A.Ş. | D10: Ofis AVM Lobi | E10: =PROPER(A10)= PROPER(C10) -> TRUE
A11: ABDULLAH KIĞILI | B11: TA LOBI | C11: Abdullah Kiğili | D11: TA Lobi | E11: =PROPER(A11)= PROPER(C11) -> TRUE
A12: ASSESSMENT SYSTEMS | B12: TA LOBI | C12: =PROPER(A12) -> Assessment Systems | D12: TA Lobi | E12: =PROPER(A12)= PROPER(C12) -> TRUE
A13: AVIC INTERNATIONAL CORPORATION | B13: TA LOBI | C13: =PROPER(A13) -> Avic International Corporation | D13: TA Lobi | E13: =PROPER(A13)= PROPER(C13) -> TRUE
A14: BAŞKA GAYRIMENKUL | B14: TA LOBI | C14: =PROPER(A14) -> Başka Gayrimenkul | D14: TA Lobi | E14: =PROPER(A14)= PROPER(C14) -> TRUE
A15: BULGARI TURKEY | B15: TA LOBI | C15: Bvlgari Turkey | D15: TA Lobi | E15: =PROPER(A15)= PROPER(C15) -> FALSE
A16: ÇAĞDAŞ KIŞLAOĞLU (ESTETIK DIŞ HEKIMI) | B16: TA LOBI | C16: Çağdaş Kışlaoğlu (Estetik Diş Hekimi) | D16: TA Lobi | E16: =PROPER(A16)= PROPER(C16) -> FALSE
A17: ÇAMLICA PETROL LTD. ŞTI. | B17: TA LOBI | C17: Çamlıca Petrol Ltd. Şti. | D17: TA Lobi | E17: =PROPER(A17)= PROPER(C17) -> FALSE
A18: CENTERDENT | B18: TA LOBI | C18: Centerdent | D18: TA Lobi | E18: =PROPER(A18)= PROPER(C18) -> TRUE
A19: DR. ERDEM GÜVEN | B19: TA LOBI | C19: Dr. Erdem Güven | D19: TA Lobi | E19: =PROPER(A19)= PROPER(C19) -> TRUE
A20: ERGÜL KESKIN CONTURE MAKE-UP STUDIO | B20: TA LOBI | C20: Ergül Keskin Conture Make-Up Studio | D20: TA Lobi | E20: =PROPER(A20)= PROPER(C20) -> TRUE
A21: FMG AND GENERATION | B21: TA LOBI | C21: FMG and Generation | D21: TA Lobi | E21: =PROPER(A21)= PROPER(C21) -> TRUE
A22: GREEN AND BLACK MARINE LOGISTICS | B22: TA LOBI | C22: Green and Black Marine Logistics | D22: TA Lobi | E22: =PROPER(A22)= PROPER(C15) -> FALSE
A23: KARANFIL CONSTRUCTION | B23: TA LOBI | C23: Karanfil Construction | D23: TA Lobi | E23: =PROPER(A23)= PROPER(C23) -> TRUE
A24: LEON TIC. A.Ş. | B24: TA LOBI | C24: Leon Tic. A.Ş. | D24: TA Lobi | E24: =PROPER(A24)= PROPER(C24) -> TRUE
A25: LMC PETROKIMYA YATIRIM A.Ş. | B25: TA LOBI | C25: LMC Petrokimya Yatırım A.Ş. | D25: TA Lobi | E25: =PROPER(A25)= PROPER(C25) -> FALSE
A26: MAYHOOLA | B26: TA LOBI | C26: Mayhoola | D26: TA Lobi | E26: =PROPER(A26)= PROPER(C26) -> TRUE
A27: ONIKI HUKUK BÜROSU | B27: TA LOBI | C27: Oniki Hukuk Bürosu | D27: TA Lobi | E27: =PROPER(A27)= PROPER(C27) -> TRUE
A28: OPR. DR. ÜMRAN ILERI (ESTETIK PLASTIK CERRAHI) | B28: TA LOBI | C28: Opr. Dr. Ümran Ileri (Estetik Plastik Cerrahi) | D28: TA Lobi | E28: =PROPER(A28)= PROPER(C28) -> TRUE
A29: PBA IÇ VE DIŞ TIC. | B29: TA LOBI | C29: PBA Iç ve Dış Tic. | D29: TA Lobi | E29: =PROPER(A29)= PROPER(C29) -> FALSE
A30: PEREZOĞLU&ÖZBILEN AVUKATLIK BÜROSU | B30: TA LOBI | C30: Perezoğlu & Özbilen Avukatlık Bürosu | D30: TA Lobi | E30: =PROPER(A30)= PROPER(C30) -> FALSE
A31: PROF.DR. AYLIN BILGIN KARABULUT | B31: TA LOBI | C31: Prof. Dr. Aylin Bilgin Karabulut | D31: TA Lobi | E31: =PROPER(A31)= PROPER(C31) -> FALSE
A32: PROF.DR. SAADETTIN ESKIÇORAPÇI | B32: TA LOBI | C32: Prof. Dr. Saadettin Eskiçorapçı | D32: TA Lobi | E32: =PROPER(A32)= PROPER(C32) -> FALSE
A33: PROF.DR. SERDAR YALÇIN | B33: TA LOBI | C33: Prof. Dr. Serdar Yalçın | D33: TA Lobi | E33: =PROPER(A33)= PROPER(C33) -> FALSE
A34: RESNE GAYRIMENKUL A.Ş. | B34: TA LOBI | C34: Resne Gayrimenkul A.Ş. | D34: TA Lobi | E34: =PROPER(A34)= PROPER(C34) -> TRUE
... A102: ZKURTUL DANIŞMANLIK | B102: TD LOBI | C102: Zkurtul Danışmanlık | D102: TD Lobi | E102: =PROPER(A102)= PROPER(C102) -> FALSE

Sheet Ofisler-2022
A1: 36 COE Teknoloji | B1: TA Lobi | C1: 36 COE TEKNOLOJİ | D1: TA LOBİ
A2: A1 Capital | B2: TD Lobi | C2: A1 CAPITAL | D2: TD LOBİ
A3: Abdullah Kiğili | B3: TA Lobi | C3: ABDULLAH KİĞILI | D3: TA LOBİ
A4: ABS Gayrimenkul | B4: TD Lobi | C4: ABS GAYRİMENKUL | D4: TD LOBİ
A5: ABS Gayrimenkul | B5: TB Lobi | C5: ABS GAYRİMENKUL. | D5: TB LOBİ
A6: ADCO Sağlık Hizm. ve Tic. A.Ş. | B6: TD Lobi | C6: ADCO SAĞLIK HİZM. VE TİC. A.Ş. | D6: TD LOBİ
A7: AI Analiz | B7: TD Lobi | C7: Aİ ANALİZ | D7: TD LOBİ
A8: Ali Atay - Candan Karaca | B8: TD Lobi | C8: ALİ ATAY - CANDAN KARACA | D8: TD LOBİ
A9: Ali Duman Clinic | B9: TB Lobi | C9: ALİ DUMAN CLINIC | D9: TB LOBİ
A10: Arkas Lojistik A.Ş. | B10: TB Lobi | C10: ARKAS LOJİSTİK A.Ş. | D10: TB LOBİ
A11: Armatran Group (CMA Otomotiv) | B11: TB Lobi | C11: ARMATRAN GROUP (CMA Otomotiv- Armatran Otomotiv) | D11: TB LOBİ
A12: ARN Game | B12: TD Lobi | C12: ARN GAME | D12: TD LOBİ
... A54: Kibar Holding | B54: Ofis AVM Lobi | C54: KİBAR HOLDİNG | D54: OFİS AVM LOBİ
A55: Laffan Mücevher Evi | B55: TB Lobi
A56: Leon Tic. A.Ş. | B56: TA Lobi | C56: LEON TİC. A.Ş. | D56: TA LOBİ
A57: Limak Holding | B57: Ofis AVM Lobi | C57: LİMAK HOLDİNG | D57: OFİS AVM LOBİ
A58: LMC Petrokimya Yatırım A.Ş. | B58: TA Lobi | C58: LMC PETROKİMYA YATIRIM A.Ş. | D58: TA LOBİ
A59: MAİ Dış Tic. | B59: TD Lobi
A60: Maktel Inşaat / Faruk Yalçın Hayvan. Bah. | B60: TB Lobi | C60: MAKTEL İNŞAAT / FARUK YALÇIN HAYVANAT BAHÇESİ VE BOTANİK PARKI A.Ş. | D60: TB LOBİ
A61: Marubeni Itochu Steel | B61: TD Lobi | C61: MARUBENI ITOCHU STEEL | D61: TD LOBİ
A62: Masgold Kuyumculuk | B62: TD Lobi | C62: MASGOLD KUYUMCULUK | D62: TD LOBİ
A63: Maslak Gayrimenkul | B63: TD Lobi | C63: MASLAK GAYRİMENKUL | D63: TD LOBİ
A64: Mayhoola | B64: TA Lobi | C64: MAYHOOLA | D64: TA LOBİ
A65: Medbulk Denizcilik | B65: Ofis AVM Lobi | C65: MEDBULK DENİZCİLİK | D65: OFİS AVM LOBİ
A66: Metreküp Mimarlık | B66: TD Lobi | C66: METREKÜP MİMARLIK | D66: TD LOBİ
A67: Mikropor | B67: TB Lobi | C67: MİKROPOR | D67: TB LOBİ
A68: NATUREL ENERJİ A.Ş. | B68: TD LOBİ | C68: NATUREL ENERJİ A.Ş. | D68: TD LOBİ
A69: NGA İnşaat A.Ş. | B69: TB Lobi | C69: NGA İNŞAAT A.Ş. | D69: TB LOBİ
A70: Oasis Investment | B70: TD Lobi | C70: OASIS INVESTMENT | D70: TD LOBİ
A71: Oltan ve Köleoğlu Enerji | B71: Ofis AVM Lobi | C71: OLTAN VE KÖLEOĞLU ENERJİ | D71: OFİS AVM LOBİ
... A90: Sace Spa Istanbul Representative Office | B90: TD Lobi | C90: SLPLUS METAL MADEN SAN. DIŞ. TİC. A.Ş. | D90: TD LOBİ
A91: Senle Beraber Tic. A.Ş. | B91: TD Lobi
A92: SLPLUS Metal Maden San. Dış Tic. A.Ş. | B92: TD Lobi | C92: SYZ PRIVATE BANKING | D92: TD LOBİ
A93: SYZ Private Banking | B93: TD Lobi | C93: Ş.A. YEMİNLİ MALİ MÜŞAVİRLİK | D93: TA LOBİ
A94: Tab Turizm A.Ş. | B94: TD Lobi | C94: THE BO VIERA / BESA GRUP | D94: TA LOBİ
A95: Tarman Group | B95: TA Lobi | C95: TAB TURİZM A.Ş. | D95: TD LOBİ
A96: The Bo Viera / Besa Grup | B96: TA Lobi | C96: TARMAN GROUP | D96: TA LOBİ
A97: TOLGAHAN MÜHENDİSLİK | B97: TD LOBİ | C97: TOLGAHAN MÜHENDİSLİK | D97: TD LOBİ
A98: Toren A.Ş. | B98: Ofis AVM Lobi | C98: TOREN A.Ş. | D98: OFİS AVM LOBİ
A99: Tricon | B99: TB Lobi | C99: TRİCON | D99: TB LOBİ
A100: Turkuaz Turizm Yatırım ve Tic. A.Ş. | B100: TB Lobi | C100: TURKUAZ TURİZM YATIRIM ve TİC. A.Ş. | D100: TB LOBİ
A101: Universal Conselor | B101: TD Lobi | C101: UNIVERSAL CONSELOR | D101: TD LOBİ
A102: Valuegene Consulting Group | B102: TD Lobi | C102: VALUEGENE CONSULTING GROUP | D102: TD LOBİ
A103: Versatie Gayrimenkul | B103: TA Lobi | C103: VERSATİE GAYRİMENKUL | D103: TA LOBİ
... A111: Zorlu Gayrimenkul | B111: yönetim, pazarlama, satış, müdür, ofis, management, marketing, sales, manager, office | C111: ZUUKS BİLİŞİM | D111: TA LOBİ
A112: Zuuks Bilişim | B112: TA Lobi

Sheet Categories
A1: Ana Kategori Kodu | B1: Ana Kategori - TR | C1: Ana Kategori - EN | D1: Ana Kategori - ZH | E1: Alt Kategori Kodu | F1: Alt Kategori - TR | G1: Alt Kategori - EN | H1: Alt Kategori - ZH
A2: shop | B2: Mağazalar | C2: Shops | D2: 商店
E3: accessories_jewellery | F3: Aksesuar & Mücevher | G3: Accessories & Jewellery | H3: 配件&珠宝
E4: shoes_bags | F4: Ayakkabı & Çanta | G4: Shoes & Bags | H4: 鞋&袋
E5: kids | F5: Çocuk | G5: Kids | H5: 孩子们
E6: electronics | F6: Elektronik | G6: Electronics | H6: 数码产品
E7: home_decoration | F7: Ev & Dekorasyon | G7: Home & Decoration | H7: 家
E8: fashion | F8: Giyim | G8: Fashion | H8: 流行服饰
E9: cosmetics_health | F9: Kozmetik & Sağlık | G9: Cosmetics & Health | H9: 化妆品&健康
E10: market | F10: Market | G10: Market | H10: 市场
E11: fitness | F11: Spor | G11: Fitness | H11: 体育保健用品
E12: servicestores | F12: Hizmet Mağazaları | G12: Service Stores | H12: 服务商店
E13: culture_entertainment | F13: Kültür & Eğlence | G13: Culture & Entertainment | H13: 游戏娱乐
A14: food | B14: Yiyecek İçecek | C14: Food Drink | D14: 食品饮料
E15: fastfood | F15: Fast Food | G15: Fast Food | H15: 快餐食品
E16: turkishdelight_confectionery | F16: Lokum & Şekerleme | G16: Turkish Delight & Confectionery | H16: 土耳其软糖和糖果
E17: restaurant_cafe | F17: Restoran & Cafe | G17: Restaurant & Cafe | H17: 餐厅&咖啡厅
A18: services | B18: Hizmetler | C18: Services | D18: 服务

Sheet Broşür
A1: Floor | B1: No | C1: Title | D1: Category
A2: -1 | C2: {“id”:”baby”}
A3: -1 | C3: {“id”:”baby”}
A4: -2 | C4: {“id”:”baby”}
A5: -2 | C5: {“id”:”baby”}
A6: 0 | C6: {“id”:”baby”}
A7: -3 | C7: {“id”:”carpark”}
A8: -1 | C8: {“id”:”entrance”} Levazım
A9: 0 | C9: {“id”:”entrance”} Levazım
A10: -3 | C10: {“id”:”entrance”} Metro
A11: -3 | C11: {“id”:”entrance”} Metro
A12: -3 | C12: {“id”:”entrance”} Otopark
A13: 0 | C13: {“id”:”entrance”} Ulus
A14: 0 | C14: {“id”:”entrance”} Zincirlikuyu
A15: -2 | C15: {“id”:”exchange”} Zor | D15: Hizmet Mağazaları
A16: -2 | C16: {“id”:”infirmary”} | D16: Hizmetler
A17: -2 | C17: {“id”:”infirmary”} | D17: Hizmetler
A18: -1 | C18: {“id”:”info”} | D18: Hizmetler
A19: -2 | C19: {“id”:”info”} | D19: Hizmetler
A20: -3 | C20: {“id”:”metro”}{“id”:”metrobus”}
A21: -1 | C21: {“id”:”pharmacy”} Zorlu Center | D21: Kozmetik & Sağlık
A22: -1 | C22: {“id”:”pharmacy”} Zorlu Center | D22: Kozmetik & Sağlık
A23: 1 | C23: {“id”:”prayer”} | D23: Hizmetler
A24: -1 | C24: {“id”:”taxi”} | D24: Hizmetler
A25: 0 | C25: {“id”:”taxi”} | D25: Hizmetler
A26: -1 | C26: {“id”:”wc”}
A27: -1 | C27: {“id”:”wc”}
A28: -2 | C28: {“id”:”wc”}
A29: -2 | C29: {“id”:”wc”}
A30: 0 | C30: {“id”:”wc”}
A31: 0 | C31: {“id”:”wc”}
A32: 0 | C32: {“id”:”wc”}
A33: 0 | C33: {“id”:”wc”}
A34: 1 | C34: {“id”:”wc”}
A35: 1 | C35: {“id”:”wc”}
A36: 1 | C36: {“id”:”wc”}
A37: 0 | C37: Abdullah Kiğılı | D37: Ofisler
A38: -2 | B38: 13 | C38: Abdullah Kiğılı Exclusive Cut | D38: Giyim
A39: 0 | B39: 10 | C39: Adamo | D39: Giyim
A40: -2 | B40: 18 | C40: Adidas | D40: Giyim
A41: -2 | B41: 17 | C41: Agatha | D41: Aksesuar & Mücevher
A42: -1 | C42: AI Analiz | D42: Ofisler
A43: 0 | B43: 11 | C43: Aigner | D43: Ayakkabı & Çanta
A44: 0 | B44: 34 | C44: Akbank {“id”:”atm”} | D44: Hizmetler
A45: 1 | B45: 09 | C45: Akbank {“id”:”branch”} | D45: Hizmetler
A46: -2 | B46: 10 | C46: Aldo | D46: Ayakkabı & Çanta
A47: 0 | C47: Ali Duman Clinic | D47: Ofisler
A48: 0 | B48: 34 | C48: Alternatif Bank {“id”:”atm”} | D48: Hizmetler
A49: 0 | B49: 09 | C49: Anatoli | D49: Ev & Dekorasyon
A50: 1 | B50: 07 | C50: Any | D50: Ev & Dekorasyon
A51: -1 | B51: 06 | C51: Apple | D51: Elektronik
A52: -2 | B52: 07 | C52: Apple | D52: Elektronik
A53: -1 | B53: 24 | C53: Arby's | D53: Fast Food
A54: 0 | B54: 29 | C54: Arifoğlu | D54: Market
A55: 0 | C55: Artı Yatırım Holding A.Ş. | D55: Ofisler
A56: -1 | B56: 14 | C56: Atasay | D56: Aksesuar & Mücevher
A57: -2 | B57: 01 | C57: Atelier Rebul | D57: Kozmetik & Sağlık
A58: 0 | B58: 10 | C58: Atilla Karat | D58: Aksesuar & Mücevher
A59: -1 | C59: Atış Gayrimenkul Pazarlama Ltd. | D59: Ofisler
A60: -2 | B60: 22 | C60: Aveda HandeHaluk | D60: Kozmetik & Sağlık
A61: -1 | C61: AYF Yatırım | D61: Ofisler
A62: -3 | B62: 02 | C62: Balonevi | D62: Kültür & Eğlence
A63: -1 | B63: 16 | C63: Beymen | D63: Giyim
A64: 0 | B64: 17 | C64: Beymen | D64: Giyim
A65: -1 | B65: 09 | C65: Beymen Club | D65: Giyim
A66: -1 | C66: Bioeksim A.Ş. | D66: Ofisler
A67: -1 | B67: 15 | C67: Bob {“id”:”valet”} (Levazım/Beymen) | D67: Hizmetler
A68: -3 | B68: 02 | C68: Bob {“id”:”valet”} (Otopark) | D68: Hizmetler
A69: 0 | B69: 05 | C69: Bob {“id”:”valet”} (Ulus/Raffles) | D69: Hizmetler
A70: -1 | B70: 17 | C70: Brooks Brothers | D70: Giyim
A71: -1 | C71: Buladı Hukuk Bürosu | D71: Ofisler
A72: 0 | C72: Bulgari Turkey | D72: Ofisler
A73: 0 | B73: 19 | C73: Burberry | D73: Giyim
A74: -2 | B74: 20 | C74: Burberry Children | D74: Çocuk
A75: -1 | B75: 25 | C75: Burger King | D75: Fast Food
A76: 0 | B76: 08 | C76: Bvlgari | D76: Aksesuar & Mücevher
A77: -2 | B77: 10 | C77: Cacharel | D77: Giyim
A78: -1 | B78: 26 | C78: Caffe Nero | D78: Restoran & Cafe
A79: -1 | B79: 13 | C79: Calvin Klein | D79: Giyim
A80: -1 | B80: 29 | C80: Calzedonia | D80: Giyim
A81: 0 | B81: 18 | C81: Cantinery | D81: Restoran & Cafe
A82: 0 | C82: Capital Partners | D82: Ofisler
A83: -1 | B83: 20 | C83: Carl's Jr. | D83: Fast Food
A84: -2 | B84: 02 | C84: Carter's / Oshkosh B'gosh | D84: Çocuk
A85: -1 | C85: CC Finans Danışmanlık | D85: Ofisler
A86: 0 | C86: Centerdent | D86: Ofisler
A87: 1 | B87: 05 | C87: Chakra | D87: Ev & Dekorasyon
A88: -1 | C88: CHS Group | D88: Ofisler
A89: -2 | B89: 22 | C89: Cinemaximum | D89: Kültür & Eğlence
A90: -2 | B90: 06 | C90: Çocuk Etkinlik Alanı | D90: Hizmetler
A91: -2 | B91: 04 | C91: Columbia | D91: Giyim
A92: 0 | B92: 30 | C92: Concierge | D92: Hizmetler
A93: -1 | B93: 06 | C93: COS | D93: Giyim
A94: 0 | B94: 26 | C94: Crossing | D94: Restoran & Cafe
A95: -1 | B95: 15 | C95: Cup of Joy | D95: Restoran & Cafe
A96: 1 | B96: 08 | C96: D&R | D96: Kültür & Eğlence
A97: -2 | B97: 21 | C97: Dagi | D97: Giyim
A98: 0 | B98: 34 | C98: DenizBank {“id”:”atm”} | D98: Hizmetler
A99: -1 | B99: 11 | C99: Diesel | D99: Giyim
A100: 0 | B100: 05 | C100: Dior | D100: Giyim
...

Sheet Broşür v2
A1: Floor | B1: No | C1: Title | D1: Category
A2: -1 | C2: {“id”:”baby”}
A3: -1 | C3: {“id”:”baby”}
A4: -2 | C4: {“id”:”baby”}
A5: -2 | C5: {“id”:”baby”}
A6: 0 | C6: {“id”:”baby”}
A7: -3 | C7: {“id”:”carpark”}
A8: -1 | C8: {“id”:”entrance”} Levazım
A9: 0 | C9: {“id”:”entrance”} Levazım
A10: -3 | C10: {“id”:”entrance”} Metro
A11: -3 | C11: {“id”:”entrance”} Metro
A12: -3 | C12: {“id”:”entrance”} Otopark
A13: 0 | C13: {“id”:”entrance”} Ulus
A14: 0 | C14: {“id”:”entrance”} Zincirlikuyu
A15: -2 | C15: {“id”:”exchange”} Zor | D15: Hizmet Mağazaları
A16: -2 | C16: {“id”:”infirmary”} | D16: Hizmetler
A17: -2 | C17: {“id”:”infirmary”} | D17: Hizmetler
A18: -1 | C18: {“id”:”info”} | D18: Hizmetler
A19: -2 | C19: {“id”:”info”} | D19: Hizmetler
A20: -3 | C20: {“id”:”metro”}{“id”:”metrobus”}
A21: -1 | C21: {“id”:”pharmacy”} Zorlu Center | D21: Kozmetik & Sağlık
A22: -1 | C22: {“id”:”pharmacy”} Zorlu Center | D22: Kozmetik & Sağlık
A23: 1 | C23: {“id”:”prayer”} | D23: Hizmetler
A24: -1 | C24: {“id”:”taxi”} | D24: Hizmetler
A25: 0 | C25: {“id”:”taxi”} | D25: Hizmetler
A26: -1 | C26: {“id”:”wc”}
A27: -1 | C27: {“id”:”wc”}
A28: -2 | C28: {“id”:”wc”}
A29: -2 | C29: {“id”:”wc”}
A30: 0 | C30: {“id”:”wc”}
A31: 0 | C31: {“id”:”wc”}
A32: 0 | C32: {“id”:”wc”}
A33: 0 | C33: {“id”:”wc”}
A34: 1 | C34: {“id”:”wc”}
A35: 1 | C35: {“id”:”wc”}
A36: 1 | C36: {“id”:”wc”}
A37: 0 | C37: Abdullah Kiğılı | D37: Ofisler
A38: -2 | B38: 13 | C38: Abdullah Kiğılı Exclusive Cut | D38: Giyim
A39: 0 | B39: 10 | C39: Adamo | D39: Giyim
A40: -2 | B40: 18 | C40: Adidas | D40: Giyim
A41: -2 | B41: 17 | C41: Agatha | D41: Aksesuar & Mücevher
A42: -1 | C42: AI Analiz | D42: Ofisler
A43: 0 | B43: 11 | C43: Aigner | D43: Ayakkabı & Çanta
A44: 0 | B44: 34 | C44: Akbank {“id”:”atm”} | D44: Hizmetler
A45: 1 | B45: 09 | C45: Akbank {“id”:”branch”} | D45: Hizmetler
A46: -2 | B46: 10 | C46: Aldo | D46: Ayakkabı & Çanta
A47: 0 | C47: Ali Duman Clinic | D47: Ofisler
A48: 0 | B48: 34 | C48: Alternatif Bank {“id”:”atm”} | D48: Hizmetler
A49: 0 | B49: 09 | C49: Anatoli | D49: Ev & Dekorasyon
A50: 1 | B50: 07 | C50: Any | D50: Ev & Dekorasyon
A51: -1 | B51: 06 | C51: Apple | D51: Elektronik
A52: -2 | B52: 07 | C52: Apple | D52: Elektronik
A53: -1 | B53: 24 | C53: Arby's | D53: Fast Food
A54: 0 | B54: 29 | C54: Arifoğlu | D54: Market
A55: 0 | C55: Artı Yatırım Holding A.Ş. | D55: Ofisler
A56: -1 | B56: 14 | C56: Atasay | D56: Aksesuar & Mücevher
A57: -2 | B57: 01 | C57: Atelier Rebul | D57: Kozmetik & Sağlık
A58: 0 | B58: 10 | C58: Atilla Karat | D58: Aksesuar & Mücevher
A59: -1 | C59: Atış Gayrimenkul Pazarlama Ltd. | D59: Ofisler
A60: -2 | B60: 22 | C60: Aveda HandeHaluk | D60: Kozmetik & Sağlık
A61: -1 | C61: AYF Yatırım | D61: Ofisler
A62: -3 | B62: 02 | C62: Balonevi | D62: Kültür & Eğlence
A63: -1 | B63: 16 | C63: Beymen | D63: Giyim
A64: 0 | B64: 17 | C64: Beymen | D64: Giyim
A65: -1 | B65: 09 | C65: Beymen Club | D65: Giyim
A66: -1 | C66: Bioeksim A.Ş. | D66: Ofisler
A67: -1 | B67: 15 | C67: Bob {“id”:”valet”} (Levazım/Beymen) | D67: Hizmetler
A68: -3 | B68: 02 | C68: Bob {“id”:”valet”} (Otopark) | D68: Hizmetler
A69: 0 | B69: 05 | C69: Bob {“id”:”valet”} (Ulus/Raffles) | D69: Hizmetler
A70: -1 | B70: 17 | C70: Brooks Brothers | D70: Giyim
A71: -1 | C71: Buladı Hukuk Bürosu | D71: Ofisler
A72: 0 | C72: Bulgari Turkey | D72: Ofisler
A73: 0 | B73: 19 | C73: Burberry | D73: Giyim
A74: -2 | B74: 20 | C74: Burberry Children | D74: Çocuk
A75: -1 | B75: 25 | C75: Burger King | D75: Fast Food
A76: 0 | B76: 08 | C76: Bvlgari | D76: Aksesuar & Mücevher
A77: -2 | B77: 10 | C77: Cacharel | D77: Giyim
A78: -1 | B78: 26 | C78: Caffe Nero | D78: Restoran & Cafe
A79: -1 | B79: 13 | C79: Calvin Klein | D79: Giyim
A80: -1 | B80: 29 | C80: Calzedonia | D80: Giyim
A81: 0 | B81: 18 | C81: Cantinery | D81: Restoran & Cafe
A82: 0 | C82: Capital Partners | D82: Ofisler
A83: -1 | B83: 20 | C83: Carl's Jr. | D83: Fast Food
A84: -2 | B84: 02 | C84: Carter's / Oshkosh B'gosh | D84: Çocuk
A85: -1 | C85: CC Finans Danışmanlık | D85: Ofisler
A86: 0 | C86: Centerdent | D86: Ofisler
A87: 1 | B87: 05 | C87: Chakra | D87: Ev & Dekorasyon
A88: -1 | C88: CHS Group | D88: Ofisler
A89: -2 | B89: 22 | C89: Cinemaximum | D89: Kültür & Eğlence
A90: -2 | B90: 06 | C90: Çocuk Etkinlik Alanı | D90: Hizmetler
A91: -2 | B91: 04 | C91: Columbia | D91: Giyim
A92: 0 | B92: 30 | C92: Concierge | D92: Hizmetler
A93: -1 | B93: 06 | C93: COS | D93: Giyim
A94: 0 | B94: 26 | C94: Crossing | D94: Restoran & Cafe
A95: -1 | B95: 15 | C95: Cup of Joy | D95: Restoran & Cafe
A96: 1 | B96: 08 | C96: D&R | D96: Kültür & Eğlence
A97: -2 | B97: 21 | C97: Dagi | D97: Giyim
A98: 0 | B98: 34 | C98: DenizBank {“id”:”atm”} | D98: Hizmetler
A99: -1 | B99: 11 | C99: Diesel | D99: Giyim
A100: 0 | B100: 05 | C100: Dior | D100: Giyim
...

Sheet Broşür v3
A1: ='Broşür v2'!A1 -> Floor | B1: ='Broşür v2'!B1 -> No | C1: ='Broşür v2'!C1 -> Title | D1: ='Broşür v2'!D1 -> Category | F1: ='Broşür v2'!A1 -> Floor | G1: ='Broşür v2'!B1 -> No | H1: ='Broşür v2'!C1 -> Title | I1: ='Broşür v2'!D1 -> Category | K1: ='Broşür v2'!A1 -> Floor | L1: ='Broşür v2'!B1 -> No | M1: ='Broşür v2'!C1 -> Title | N1: ='Broşür v2'!D1 -> Category | P1: ='Broşür v2'!A1 -> Floor | Q1: ='Broşür v2'!B1 -> No | R1: ='Broşür v2'!C1 -> Title | S1: ='Broşür v2'!D1 -> Category
A2: ='Broşür v2'!A2 -> -1 | B2: ='Broşür v2'!B2 | C2: ='Broşür v2'!C2 -> {“id”:”baby”} | D2: ='Broşür v2'!D2 | F2: ='Broşür v2'!A21 -> -1 | G2: ='Broşür v2'!B21 | H2: ='Broşür v2'!C21 -> {“id”:”pharmacy”} Zorlu Center | I2: ='Broşür v2'!D21 -> Kozmetik & Sağlık | K2: ='Broşür v2'!A40 -> -2 | L2: ='Broşür v2'!B40 -> 18 | M2: ='Broşür v2'!C40 -> Adidas | N2: ='Broşür v2'!D40 -> Giyim | P2: ='Broşür v2'!A59 -> -1 | Q2: ='Broşür v2'!B59 | R2: ='Broşür v2'!C59 -> Atış Gayrimenkul Pazarlama Ltd. | S2: ='Broşür v2'!D59 -> Ofisler
A3: ='Broşür v2'!A3 -> -1 | B3: ='Broşür v2'!B3 | C3: ='Broşür v2'!C3 -> {“id”:”baby”} | D3: ='Broşür v2'!D3 | F3: ='Broşür v2'!A22 -> -1 | G3: ='Broşür v2'!B22 | H3: ='Broşür v2'!C22 -> {“id”:”pharmacy”} Zorlu Center | I3: ='Broşür v2'!D22 -> Kozmetik & Sağlık | K3: ='Broşür v2'!A41 -> -2 | L3: ='Broşür v2'!B41 -> 17 | M3: ='Broşür v2'!C41 -> Agatha | N3: ='Broşür v2'!D41 -> Aksesuar & Mücevher | P3: ='Broşür v2'!A60 -> -2 | Q3: ='Broşür v2'!B60 -> 22 | R3: ='Broşür v2'!C60 -> Aveda HandeHaluk | S3: ='Broşür v2'!D60 -> Kozmetik & Sağlık
A4: ='Broşür v2'!A4 -> -2 | B4: ='Broşür v2'!B4 | C4: ='Broşür v2'!C4 -> {“id”:”baby”} | D4: ='Broşür v2'!D4 | F4: ='Broşür v2'!A23 -> 1 | G4: ='Broşür v2'!B23 | H4: ='Broşür v2'!C23 -> {“id”:”prayer”} | I4: ='Broşür v2'!D23 -> Hizmetler | K4: ='Broşür v2'!A42 -> -1 | L4: ='Broşür v2'!B42 | M4: ='Broşür v2'!C42 -> AI Analiz | N4: ='Broşür v2'!D42 -> Ofisler | P4: ='Broşür v2'!A61 -> -1 | Q4: ='Broşür v2'!B61 | R4: ='Broşür v2'!C61 -> AYF Yatırım | S4: ='Broşür v2'!D61 -> Ofisler
A5: ='Broşür v2'!A5 -> -2 | B5: ='Broşür v2'!B5 | C5: ='Broşür v2'!C5 -> {“id”:”baby”} | D5: ='Broşür v2'!D5 | F5: ='Broşür v2'!A24 -> -1 | G5: ='Broşür v2'!B24 | H5: ='Broşür v2'!C24 -> {“id”:”taxi”} | I5: ='Broşür v2'!D24 -> Hizmetler | K5: ='Broşür v2'!A43 -> 0 | L5: ='Broşür v2'!B43 -> 11 | M5: ='Broşür v2'!C43 -> Aigner | N5: ='Broşür v2'!D43 -> Ayakkabı & Çanta | P5: ='Broşür v2'!A62 -> -3 | Q5: ='Broşür v2'!B62 -> 02 | R5: ='Broşür v2'!C62 -> Balonevi | S5: ='Broşür v2'!D62 -> Kültür & Eğlence
A6: ='Broşür v2'!A6 -> 0 | B6: ='Broşür v2'!B6 | C6: ='Broşür v2'!C6 -> {“id”:”baby”} | D6: ='Broşür v2'!D6 | F6: ='Broşür v2'!A25 -> 0 | G6: ='Broşür v2'!B25 | H6: ='Broşür v2'!C25 -> {“id”:”taxi”} | I6: ='Broşür v2'!D25 -> Hizmetler | K6: ='Broşür v2'!A44 -> 0 | L6: ='Broşür v2'!B44 -> 34 | M6: ='Broşür v2'!C44 -> Akbank {“id”:”atm”} | N6: ='Broşür v2'!D44 -> Hizmetler | P6: ='Broşür v2'!A63 -> -1 | Q6: ='Broşür v2'!B63 -> 16 | R6: ='Broşür v2'!C63 -> Beymen | S6: ='Broşür v2'!D63 -> Giyim
A7: ='Broşür v2'!A7 -> -3 | B7: ='Broşür v2'!B7 | C7: ='Broşür v2'!C7 -> {“id”:”carpark”} | D7: ='Broşür v2'!D7 | F7: ='Broşür v2'!A26 -> -1 | G7: ='Broşür v2'!B26 | H7: ='Broşür v2'!C26 -> {“id”:”wc”} | I7: ='Broşür v2'!D26 | K7: ='Broşür v2'!A45 -> 1 | L7: ='Broşür v2'!B45 -> 09 | M7: ='Broşür v2'!C45 -> Akbank {“id”:”branch”} | N7: ='Broşür v2'!D45 -> Hizmetler | P7: ='Broşür v2'!A64 -> 0 | Q7: ='Broşür v2'!B64 -> 17 | R7: ='Broşür v2'!C64 -> Beymen | S7: ='Broşür v2'!D64 -> Giyim
A8: ='Broşür v2'!A8 -> -1 | B8: ='Broşür v2'!B8 | C8: ='Broşür v2'!C8 -> {“id”:”entrance”} Levazım | D8: ='Broşür v2'!D8 | F8: ='Broşür v2'!A27 -> -1 | G8: ='Broşür v2'!B27 | H8: ='Broşür v2'!C27 -> {“id”:”wc”} | I8: ='Broşür v2'!D27 | K8: ='Broşür v2'!A46 -> -2 | L8: ='Broşür v2'!B46 -> 10 | M8: ='Broşür v2'!C46 -> Aldo | N8: ='Broşür v2'!D46 -> Ayakkabı & Çanta | P8: ='Broşür v2'!A65 -> -1 | Q8: ='Broşür v2'!B65 -> 09 | R8: ='Broşür v2'!C65 -> Beymen Club | S8: ='Broşür v2'!D65 -> Giyim
A9: ='Broşür v2'!A9 -> 0 | B9: ='Broşür v2'!B9 | C9: ='Broşür v2'!C9 -> {“id”:”entrance”} Levazım | D9: ='Broşür v2'!D9 | F9: ='Broşür v2'!A28 -> -2 | G9: ='Broşür v2'!B28 | H9: ='Broşür v2'!C28 -> {“id”:”wc”} | I9: ='Broşür v2'!D28 | K9: ='Broşür v2'!A47 -> 0 | L9: ='Broşür v2'!B47 | M9: ='Broşür v2'!C47 -> Ali Duman Clinic | N9: ='Broşür v2'!D47 -> Ofisler | P9: ='Broşür v2'!A66 -> -1 | Q9: ='Broşür v2'!B66 | R9: ='Broşür v2'!C66 -> Bioeksim A.Ş. | S9: ='Broşür v2'!D66 -> Ofisler
A10: ='Broşür v2'!A10 -> -3 | B10: ='Broşür v2'!B10 | C10: ='Broşür v2'!C10 -> {“id”:”entrance”} Metro | D10: ='Broşür v2'!D10 | F10: ='Broşür v2'!A29 -> -2 | G10: ='Broşür v2'!B29 | H10: ='Broşür v2'!C29 -> {“id”:”wc”} | I10: ='Broşür v2'!D29 | K10: ='Broşür v2'!A48 -> 0 | L10: ='Broşür v2'!B48 -> 34 | M10: ='Broşür v2'!C48 -> Alternatif Bank {“id”:”atm”} | N10: ='Broşür v2'!D48 -> Hizmetler | P10: ='Broşür v2'!A67 -> -1 | Q10: ='Broşür v2'!B67 -> 15 | R10: ='Broşür v2'!C67 -> Bob {“id”:”valet”} (Levazım/Beymen) | S10: ='Broşür v2'!D67 -> Hizmetler
A11: ='Broşür v2'!A11 -> -3 | B11: ='Broşür v2'!B11 | C11: ='Broşür v2'!C11 -> {“id”:”entrance”} Metro | D11: ='Broşür v2'!D11 | F11: ='Broşür v2'!A30 -> 0 | G11: ='Broşür v2'!B30 | H11: ='Broşür v2'!C30 -> {“id”:”wc”} | I11: ='Broşür v2'!D30 | K11: ='Broşür v2'!A49 -> 0 | L11: ='Broşür v2'!B49 -> 09 | M11: ='Broşür v2'!C49 -> Anatoli | N11: ='Broşür v2'!D49 -> Ev & Dekorasyon | P11: ='Broşür v2'!A68 -> -3 | Q11: ='Broşür v2'!B68 -> 02 | R11: ='Broşür v2'!C68 -> Bob {“id”:”valet”} (Otopark) | S11: ='Broşür v2'!D68 -> Hizmetler
A12: ='Broşür v2'!A12 -> -3 | B12: ='Broşür v2'!B12 | C12: ='Broşür v2'!C12 -> {“id”:”entrance”} Otopark | D12: ='Broşür v2'!D12 | F12: ='Broşür v2'!A31 -> 0 | G12: ='Broşür v2'!B31 | H12: ='Broşür v2'!C31 -> {“id”:”wc”} | I12: ='Broşür v2'!D31 | K12: ='Broşür v2'!A50 -> 1 | L12: ='Broşür v2'!B50 -> 07 | M12: ='Broşür v2'!C50 -> Any | N12: ='Broşür v2'!D50 -> Ev & Dekorasyon | P12: ='Broşür v2'!A69 -> 0 | Q12: ='Broşür v2'!B69 -> 05 | R12: ='Broşür v2'!C69 -> Bob {“id”:”valet”} (Ulus/Raffles) | S12: ='Broşür v2'!D69 -> Hizmetler
A13: ='Broşür v2'!A13 -> 0 | B13: ='Broşür v2'!B13 | C13: ='Broşür v2'!C13 -> {“id”:”entrance”} Ulus | D13: ='Broşür v2'!D13 | F13: ='Broşür v2'!A32 -> 0 | G13: ='Broşür v2'!B32 | H13: ='Broşür v2'!C32 -> {“id”:”wc”} | I13: ='Broşür v2'!D32 | K13: ='Broşür v2'!A51 -> -1 | L13: ='Broşür v2'!B51 -> 06 | M13: ='Broşür v2'!C51 -> Apple | N13: ='Broşür v2'!D51 -> Elektronik | P13: ='Broşür v2'!A70 -> -1 | Q13: ='Broşür v2'!B70 -> 17 | R13: ='Broşür v2'!C70 -> Brooks Brothers | S13: ='Broşür v2'!D70 -> Giyim
... A20: ='Broşür v2'!A20 -> -3 | B20: ='Broşür v2'!B20 | C20: ='Broşür v2'!C20 -> {“id”:”metro”}{“id”:”metrobus”} | D20: ='Broşür v2'!D20 | F20: ='Broşür v2'!A39 -> 0 | G20: ='Broşür v2'!B39 -> 10 | H20: ='Broşür v2'!C39 -> Adamo | I20: ='Broşür v2'!D39 -> Giyim | K20: ='Broşür v2'!A58 -> 0 | L20: ='Broşür v2'!B58 -> 10 | M20: ='Broşür v2'!C58 -> Atilla Karat | N20: ='Broşür v2'!D58 -> Aksesuar & Mücevher | P20: ='Broşür v2'!A77 -> -2 | Q20: ='Broşür v2'!B77 -> 10 | R20: ='Broşür v2'!C77 -> Cacharel | S20: ='Broşür v2'!D77 -> Giyim
